Workbook
Name \0: #REF!
Name \a: #REF!
Name \c: #N/A
Name \d: #REF!
Name \j: #REF!
Name \k: #REF!
Name \l: #REF!
Name \n: #REF!
Name \p: #REF!
Name \t: #REF!
Name \v: #REF!
Name \w: #REF!
Name \x: #REF!
Name \z: #REF!
Name _____NA5: #REF!
Name ___NA5: #REF!
Name __ACC0320: #REF!
Name __FDS_UNIQUE_RANGE_ID_GENERATOR_COUNTER: 1
Name __JJJ3: #REF!
Name __JJJ4: #REF!
Name __JJJ5: #REF!
Name __key1: #REF!
Name __May2007: #REF!
Name __may2008: #REF!
Name __NA1: #REF!
Name __NA2: #REF!
Name __NA3: #REF!
Name __NA4: #REF!
Name __NA5: #REF!
Name _01_Apr: #REF!
Name _01_May: #REF!
Name _ACC0320: #REF!
Name _APR2001: #REF!
Name _AUG2001: #REF!
Name _cat1: #REF!
Name _cat2: #REF!
Name _cat3: #REF!
Name _Dec02: #REF!
Name _Dec03: #REF!
Name _DEC2001: #REF!
Name _FEB2001: #REF!
Name _FEB2002: #REF!
Name _inv1: #REF!
Name _JAN02: #REF!
Name _JAN2001: #REF!
Name _JAN2002: #REF!
Name _JJJ1: #REF!
Name _JJJ2: #REF!
Name _JJJ3: #REF!
Name _JJJ4: #REF!
Name _JJJ5: #REF!
Name _JUL2001: #REF!
Name _JUN2001: #REF!
Name _kl1: #REF!
Name _LD1: #REF!
Name _loc3: #REF!
Name _Ma2005: #REF!
Name _MAR2001: #REF!
Name _MAR2002: #REF!
Name _MAY2001: #REF!

Sheet Project Planner
B1: Project Planner
B2: Select a period to highlight at right. A legend describing the charting follows. | G2: Period Highlight: | H2: 1 | K2: Plan Duration | Q2: Actual Start | V2: % Complete | AA2: Actual (beyond plan) | AI2: % Complete (beyond plan)
B3: ACTIVITY | C3: PLAN START | D3: PLAN DURATION | E3: ACTUAL START | F3: ACTUAL DURATION | G3: PERCENT COMPLETE | H3: PERIODS
H4: 1 | I4: 2 | J4: 3 | K4: 4 | L4: 5 | M4: 6 | N4: 7 | O4: 8 | P4: 9 | Q4: 10 | R4: 11 | S4: 12 | T4: 13 | U4: 14 | V4: 15 | W4: 16 | X4: 17 | Y4: 18 | Z4: 19 | AA4: 20 | AB4: 21 | AC4: 22 | AD4: 23 | AE4: 24 | AF4: 25 | AG4: 26 | AH4: 27 | AI4: 28 | AJ4: 29 | AK4: 30 | AL4: 31 | AM4: 32 | AN4: 33 | AO4: 34 | AP4: 35 | AQ4: 36 | AR4: 37 | AS4: 38 | AT4: 39 | AU4: 40 | AV4: 41 | AW4: 42 | AX4: 43 | AY4: 44 | AZ4: 45 | BA4: 46 | BB4: 47 | BC4: 48 | BD4: 49 | BE4: 50 | BF4: 51 | BG4: 52 | BH4: 53 | BI4: 54 | BJ4: 55 | BK4: 56 | BL4: 57 | BM4: 58 | BN4: 59 | BO4: 60
B5: ='DO NOT USE 2023-2024 Production'!B125 -> Sandia Academy | C5: 1 | D5: 5 | E5: 1 | F5: 4 | G5: 0.25
B6: Activity 02 | C6: 1 | D6: 6 | E6: 1 | F6: 6 | G6: 1
B7: Activity 03 | C7: 2 | D7: 4 | E7: 2 | F7: 5 | G7: 0.35
B8: Activity 04 | C8: 4 | D8: 8 | E8: 4 | F8: 6 | G8: 0.1
B9: Activity 05 | C9: 4 | D9: 2 | E9: 4 | F9: 8 | G9: 0.85
B10: Activity 06 | C10: 4 | D10: 3 | E10: 4 | F10: 6 | G10: 0.85
B11: Activity 07 | C11: 5 | D11: 4 | E11: 5 | F11: 3 | G11: 0.5
B12: Activity 08 | C12: 5 | D12: 2 | E12: 5 | F12: 5 | G12: 0.6
B13: Activity 09 | C13: 5 | D13: 2 | E13: 5 | F13: 6 | G13: 0.75
B14: Activity 10 | C14: 6 | D14: 5 | E14: 6 | F14: 7 | G14: 1
B15: Activity 11 | C15: 6 | D15: 1 | E15: 5 | F15: 8 | G15: 0.6
B16: Activity 12 | C16: 9 | D16: 3 | E16: 9 | F16: 3 | G16: 0
B17: Activity 13 | C17: 9 | D17: 6 | E17: 9 | F17: 7 | G17: 0.5
... B30: Activity 26 | C30: 16 | D30: 28 | E30: 16 | F30: 30 | G30: 0.5

Sheet Sheet2
A3: Sum of Estimated Value
A4: 1.3757634e+08
D5: Joe | E5: Lori
D6: Diana | E6: Kenny
D7: Sandra | E7: Pick one
D8: Sandra | E8: Pick one

Sheet 2026 Sales Pipeline
A1: SCM Sales Pipeline 2026 & Beyond
A2: Customer | B2: Project Name | C2: BDM | D2: Job Number | E2: Contract Value | F2: Building(s) | G2: Floor(s) | H2: Start Date for Production | I2: District Occupancy Date | J2: Confidence Level | K2: Current Status/Notes | L2: Contract Type | M2: Bid Piggyback | N2: Most Recent Proposal (Date) | O2: Job Release [BDM & DH] (Date) | P2: Engineering Release [BDM & Engineer] (Date) | Q2: Hand-off Meeting [BDM & PM] (Date) | R2: Kick-off Meeting [PM & ALL Depts] (Date) | S2: PM | T2: Estimated Value | U2: Estimated DSA Approval (per Engineering) | V2: Quarter | W2: Edited
A3: Romoland SD | B3: Boulder Ridge ES | C3: Diana | D3: 11642 | E3: 335647.68 | F3: (2) 24' x 40' classrooms | G3: 4 | H3: 46028 | I3: 45982 | J3: 1 | K3: To DSA by 9/1 | U3: Early October
A4: Mobile Modular | B4: Stock Classrooms | C4: Adela | D4: 11665 | E4: 7654077 | F4: (75) 24'x40' Classroom Buildings | G4: 150 | H4: 46034 | I4: 46113 | J4: 1 | K4: Revised proposal being presented to the customer | L4: PO- R320096701 | M4: Negotiated | N4: 45980
A5: Muroc Joint USD | B5: Boron HS | C5: Diana | D5: 11638 | E5: 276363.15 | F5: (1) 12x40 Restroom Model B-2 | G5: 1 | H5: 46043 | I5: 45962 | J5: 0.9 | K5: SCM generating CCD for adding the HVAC unit | L5: Executed Agreement received | M5: PB | N5: 45618 | O5: No | P5: No | T5: =IFERROR(E5*J5,0) -> 248726.84 | U5: Approved (Needs CCD for HVAC, assume mid October approval) | V5: =IFERROR(ROUNDUP(MONTH(IF(H5<>"",H5,""))/3, 0),"TBD") -> 1 | W5: =IF(I5<>"",IF(W5="",NOW(),W5),"") -> 45692.547
A6: Oceanside USD | B6: Jefferson MS | C6: Diana | D6: 11596 | E6: 5197374 | F6: (1) 84'x40' Kitchen (2) 96'x40' CR Bldgs. (1) 60'x40' Music Bldg. (2) 24'x40' RR Bldgs. | G6: 32 | H6: 46055 | I6: 46113 | J6: 1 | K6: Pending confirmation of options taken to finalize project pricing and scope. | L6: Yes | M6: Bid | N6: 45617 | O6: No | P6: No | T6: =IFERROR(E6*J6,0) -> 5197374 | U6: Late December | V6: =IFERROR(ROUNDUP(MONTH(IF(H6<>"",H6,""))/3, 0),"TBD") -> 1 | W6: =IF(I6<>"",IF(W6="",NOW(),W6),"") -> 45692.547
A7: Chula Vista USD | B7: Feaster School | C7: Diana | D7: 11636 | E7: 396510.73 | F7: (1) 48x40 | G7: 4 | H7: 46071 | U7: Late October
A8: Imperial County | B8: Little Bulldogs EHS | C8: Diana | D8: 11655 | E8: 754895 | F8: 48'x60' Daycare Kinder | G8: 4 | H8: 46077 | J8: 1 | K8: Finalizing price and project schedule to move forward. | L8: PO26-00973 | U8: NOT RELEASED TO ENGINEERING
A9: Action Day Schools | B9: Lincoln | C9: Joe | D9: 11630 | E9: 572840 | F9: (1) 36X40 Child Care Center | G9: 3 | H9: 46083 | I9: 46174 | J9: 1 | K9: Ryan to submit drawings for HCD review and approval. | L9: PO-6377 | M9: PB | N9: 45814 | O9: 45825 | P9: 45855 | Q9: 45852 | S9: Joe | T9: =IFERROR(E9*J9,0) -> 572840 | U9: HCD approval late December | W9: =IF(I9<>"",IF(W9="",NOW(),W9),"") -> 45692.547
A10: San Jacinto USD | B10: San Jacinto HS | C10: Diana | D10: 11618 | E10: 13511007 | F10: Two Story 170'/120' x 32' | G10: 58 | H10: 46086 | I10: 46327 | J10: 1 | K10: Contract is for 650 days from NTP. Project bids on 2/27/25. District is still reviewing paperwork for accuracy. Will send notification of SCM being the successful bidder after. As of 4/1 the district confirmed that they are still working with their legal team to put together the agreement before issuing us the NTP. | L10: C-1003868 | M10: Bid | N10: No | O10: No | P10: No | Q10: TBD | R10: TBD | U10: Mid December
A11: Menifee Union SD | B11: Ridgemoor ES | C11: Diana | D11: 11645 | E11: =267532.07+202011.77+636160.85 -> 1105704.7 | F11: (4) standard 24’ x 40’ classrooms, (1) 36'x40' Classroom (1) 12’ x 40’ restroom relocatable | G11: 12 | H11: 46093 | I11: 46178 | J11: 0.9 | K11: To DSA by 12/15 | M11: Bid | U11: NOT RELEASED TO ENGINEERING
A12: Keppel Union SD | B12: Pearblossom ES | C12: Sandra | D12: 11628 | E12: =871254/2 -> 435627 | F12: (3) 24'x40' Standard Classroom | G12: 6 | H12: 46094 | I12: 46006 | J12: 1 | K12: DSA app not till late July | L12: PO1-250000001456 | O12: No | S12: Joe | T12: =IFERROR(E12*J12,0) -> 435627 | U12: Late September | V12: =IFERROR(ROUNDUP(MONTH(IF(H12<>"",H12,""))/3, 0),"TBD") -> 1 | W12: =IF(I12<>"",IF(W12="",NOW(),W12),"") -> 45813.652
A13: South San Francisco USD | B13: Monte Verde ES | C13: Diana | D13: 11657 | E13: 887625.9 | F13: (1) 36'x40' Classroom with support rooms | G13: 3 | H13: 46105 | I13: 46174 | J13: 1 | K13: Customer taking to the board 10/6 | L13: Yes
A14: South San Francisco USD | B14: South San Francisco HS | C14: Diana | D14: 11640 | E14: 416593.32 | F14: (1) 24'x60' Office Building | G14: 2 | H14: 46107 | J14: 1 | K14: 8.7.25 District provided a LOI, will have signed proposal 8.24.2025 | L14: Yes | U14: Mid October
A15: South San Francisco USD | B15: Junipero Serra ES | C15: Diana | D15: 11656 | E15: 897625.9 | F15: (1) 36'x40' Classroom with support rooms | G15: 3 | H15: 46107 | I15: 46113 | J15: 1 | K15: In estimating | L15: Yes
A16: Ventura USD | B16: ATLAS School | C16: Diana | D16: 11594 | E16: 382738.04 | F16: (1) 12x60 Restroom | G16: 1 | H16: 46112 | I16: 46204 | J16: 1 | K16: DSA Approved. Per District, this project will be for Summer 2026. | L16: PO26-02865 | M16: PB | P16: Yes | Q16: 45861 | R16: TBD | S16: Joe | T16: =IFERROR(E16*J16,0) -> 382738.04 | U16: Approved | V16: =IFERROR(ROUNDUP(MONTH(IF(H16<>"",H16,""))/3, 0),"TBD") -> 1 | W16: =IF(I16<>"",IF(W16="",NOW(),W16),"") -> 45692.547
A17: Oaks Christian School | B17: Oaks Christian School | C17: Sandra | D17: 11672 | E17: 1999000 | F17: (12) 24x40 and (2) 12x40 RR | G17: 26 | H17: 46121 | J17: 0.5 | K17: DSA App 3/25/26
A18: Pasadena USD | B18: Franklin ES | C18: Sandra | D18: 11661 | E18: 8750000 | F18: Admin, Kitchen, MP | G18: 46 | H18: 46126 | I18: 45785 | J18: 1 | K18: Submitted Final Costs with Piggyback breakdowns and they are beginning to return them reviewed. | U18: Admin in Late Jan & MPR/Kitchen in Late Mar/Early Apr
A19: Pleasant Valley SD | B19: Valle Lindo ES (CAPE Charter School) | C19: Joe | D19: 11629 | E19: =234048+2515+9650 -> 246213 | F19: (1) 24x40 Office/Resource Building | G19: 2 | H19: 46133 | I19: 46174 | J19: 1 | K19: DSA appt 12/2/2025 | L19: PO 9001483 | M19: PB | N19: 45806 | O19: 45824 | P19: 45856 | Q19: 45852 | S19: Joe | T19: =IFERROR(E19*J19,0) -> 246213 | U19: Early December? (Does not appear that the AOR has a DSA appointment) | W19: =IF(I19<>"",IF(W19="",NOW(),W19),"") -> 45692.547
A20: Inglewood USD | B20: Oak St. Prep K- Phase 2 | C20: Sandra | D20: 11648 | E20: =335055.82+802544.94+1440973.64+1887030.71 -> 4465605.1 | F20: (1) 12x40 RR, (7) 36x40 Tk (3) 24x40 Classroom Bldg | G20: 28 | H20: 46141 | I20: 46235 | J20: 1 | K20: Balfour has requested breakdown of why cost went up so much | U20: Late December
A21: Corning Union ESD | B21: Community Day School (Columbia Academy) | C21: Diana | D21: 11660 | E21: 953588.47 | F21: (1) 72x40 Classroom Bldg | G21: 6 | H21: 46148 | I21: 46234 | J21: 0.8 | K21: LLB with United Building Contractors. District approved UBC in May 2025. Building production in Spring 2026. | T21: =IFERROR(E21*J21,0) -> 762870.78 | U21: Early April
A22: ABC USD | B22: Leal ES | C22: Sandra | D22: 11671 | E22: 305786 | F22: (2) 24x40 Classroom Bldgs | G22: 4 | H22: 46156 | J22: 1 | K22: DSA approved they are working on finalizing submittals
A23: Garvey SD | B23: Duff ES | C23: Sandra | D23: 11654 | E23: 803365.69 | F23: 60’x40’ Childcare Building | G23: 5 | H23: 46156 | J23: 1 | K23: In production | M23: Negotiated | U23: NOT RELEASED TO ENGINEERING
A24: Cerritos College | B24: Cerritos Community College | C24: Sandra | D24: 11643 | E24: 2389774.5 | F24: (2) 48x60 and (1) 24x60 TK Buildings | G24: 9 | H24: 46162 | I24: 46265 | J24: 1 | K24: Jonathan executed contract pending bonds and insurance PM working on change orders | L24: No | M24: PB | N24: 45616 | T24: =IFERROR(E24*J24,0) -> 2389774.5 | U24: February | W24: =IF(I24<>"",IF(W24="",NOW(),W24),"") -> 45692.547
A25: Mobile Modular | B25: Melrose | C25: Diana | D25: 11681 | E25: 139000 | F25: (1) 12x40 B2 RR | G25: 1 | H25: 46181
A26: Corning Union ESD | B26: Rancho Tehama ES | C26: Diana | D26: 11659 | E26: 673367.01 | F26: (1) 48'x40' Classrooms | G26: 4 | H26: 46182 | J26: 1 | K26: In DSA | U26: Early April
A27: San Diego USD | B27: SD Cooperative Charter School | C27: Diana | D27: 11644 | E27: 270248.43 | F27: (1) 36'x40' w/ single user RR | G27: 3 | H27: 46188 | I27: 46234 | J27: 0.5 | K27: The proposal was provided the customer is exploring their options due to budget. Might need to lease. | U27: NOT RELEASED TO ENGINEERING
A28: Rosemead USD | B28: Encinita ES | C28: Diana | D28: 11669 | E28: 187350.66 | F28: (1) 24'x40' Open Classroom | G28: 2 | H28: 46191 | J28: 0.9 | K28: Final proposal was sent to the AOR. Hand-off meeting to engineering took place. Waiting on confirmation on a few items from AOR for engineering to start drawings.
A29: Rescue USD | B29: Rescue ES | C29: Frank | D29: 11674 | E29: 169778.33 | F29: (1) 8.5x32 Restroom | G29: 1 | H29: 46195 | I29: 46239 | J29: 1 | K29: Drawings went to DSA for approval on 5/13
A30: Whittier City SD | B30: Jackson ES | C30: Sandra | D30: 11658 | E30: 389762.66 | F30: (1) 24x40 Double Classroom & (1) 12x40 RR | G30: 3 | H30: 46196 | J30: 1 | K30: In DSA | U30: NOT RELEASED TO ENGINEERING
A31: Fullerton SD | B31: Parks Junior High School | C31: Sandra | D31: 11647 | E31: 337086.71 | F31: (2) 24x40 Classroom Building | G31: 4 | H31: 46199 | K31: Pending DSA Approval | U31: NOT RELEASED TO ENGINEERING
A32: Palm Springs USD | B32: Two Bunch Palms ES | C32: Diana | D32: 11573 | E32: 112000 | F32: 8’-6”x16’-7” RR | G32: 1 | H32: 46204 | I32: 46235 | J32: 1 | K32: Project is moving forward, district working on a timeline. Back check appointment 4/8. | L32: No | M32: PB | N32: Pending Adel Release | O32: No | P32: No | R32: TBD | S32: Gino | T32: =IFERROR(E32*J32,0) -> 112000 | U32: Pending Schedule | V32: =IFERROR(ROUNDUP(MONTH(IF(H32<>"",H32,""))/3, 0),"TBD") -> 3 | W32: =IF(I32<>"",IF(W32="",NOW(),W32),"") -> 45692.547
A33: Unified Modular | B33: Unified Modular | C33: Diana | E33: TBD | F33: (1) 24'x40' Classroom Building w/RR and kitchenette | G33: 2 | H33: 46204 | I33: 46237 | J33: 0.1 | K33: Proposal went out 5/5/26 & is for Garvey.
A34: South Fork USD | B34: South Fork MS | C34: Frank | F34: (12) 24X40 Classroom Buildings | G34: =2*12 -> 24 | H34: 46204 | I34: 46266 | J34: 0.2 | K34: 5/14 Diana forwarded contact info and FC following up with customer | T34: =IFERROR('Leads, pre-con'!D7*J34,0) -> 177721.73 | U34: NOT RELEASED TO ENGINEERING
A35: Sunlife Corporate Housing | B35: Edwards AFB | C35: Frank | E35: 551515.38 | F35: (1) 60x40 Open Gym | G35: =5 -> 5 | H35: 46204 | I35: 45964 | J35: 0.3 | K35: 5/14 Diana forwarded contact info and FC following up with customer | M35: Bid | T35: =IFERROR(E35*J35,0) -> 165454.61 | U35: NOT RELEASED TO ENGINEERING
A36: La Habra USD | B36: La Dera ES | C36: Sandra | E36: 192714 | F36: (1) 12x40 TB | G36: 1 | H36: 46204 | J36: 1 | K36: Should receive PO week of 5/11/26; no later than 5/18/26
A37: Orange USD | B37: Panorama ES | C37: Sandra | D37: 11685 | E37: 362689.71 | F37: (2) 24x40 Buildings | G37: 4 | H37: 46204 | J37: 1 | K37: District working on purchase order
A38: MAOF/LAUSD Headstart | B38: Beta Vista Head Start | C38: Sandra | D38: 11679 | E38: 743643.93 | F38: (1) 40x60 Headstart Bldgs | G38: 6 | H38: 46204 | J38: 1 | K38: Received Signed Proposal to begin Drawings - PO to be issued in May | U38: NOT RELEASED TO ENGINEERING
A39: MAOF/LAUSD Headstart | B39: City Terrace Head Start | C39: Sandra | D39: 11680 | E39: 727753.87 | F39: (1) 40x52 Building | G39: 4 | H39: 46211 | J39: 1 | K39: Received Signed Proposal to begin Drawings - PO to be issued in May | U39: NOT RELEASED TO ENGINEERING
A40: Lowell SD | B40: Olita ES | C40: Sandra | D40: 11653 | E40: 1853773 | F40: 108x60 Classrooms w/RR | G40: 9 | H40: 46216 | J40: 1 | K40: In DSA | L40: PO W99B0031 | U40: NOT RELEASED TO ENGINEERING
A41: Tustin USD | B41: Beswick ES | C41: Sandra | D41: 11666 | E41: 154046.05 | F41: (1) 24’x40’ | G41: 2 | H41: 46217 | I41: 46235 | J41: 1 | K41: Submitted Plans to architect received some updates on 2/12/26 | L41: Design only contract | U41: Currently Only Have Contract for Drawings
A42: Mobile Modular | D42: 11670 | E42: 395260.99 | F42: (1) 48' X 40' CR AND (1) 12' X 40' RR BUILDING | G42: 5 | H42: 46218 | K42: PO depending on GC - likely to be received in June 2026 | L42: PO- ENG Only
A43: Helendale SD | B43: Helendale ES | C43: Sandra | D43: 11662 | E43: 260434.8 | F43: (1) 48x40 Classroom | G43: 4 | H43: 46224 | I43: 46174 | J43: 0.5 | K43: Working on piggyback - meeting 5/13/26. | L43: No | M43: PB | N43: Yes | O43: No | P43: No | R43: TBD | S43: TBD | T43: =IFERROR(E43*J43,0) -> 130217.4 | U43: Early to Mid January | V43: =IFERROR(ROUNDUP(MONTH(IF(H43<>"",H43,""))/3, 0),"TBD") -> 3 | W43: =IF(I43<>"",IF(W43="",NOW(),W43),"") -> 45692.547
A44: Lowell SD | B44: Macy ES | C44: Sandra | D44: 11652 | E44: 1513671 | F44: 84x60 Classrooms w/RR | G44: =84/12 -> 7 | H44: 46231 | J44: 0.6 | K44: In DSA | L44: PO W99B0029 | U44: NOT RELEASED TO ENGINEERING
A45: Anaheim Union HSD | B45: Katella HS | C45: Sandra | D45: 11667 | E45: 288840 | F45: (1) 12x40 TB C1 | G45: 1 | H45: 46231 | J45: 0.75 | K45: Will be bid through lease lease back and recommentd SCM @ manufactuer Received Comments and corrections Mark addressed
A46: Anaheim Union HSD | B46: Kennedy HS | C46: Sandra | D46: 11668 | E46: 307679.28 | F46: (1) 12x40 TB Multi User | G46: 1 | H46: 46232 | J46: 0.75 | K46: Will be bid through lease lease back and recommentd SCM @ manufactuer
A47: Rosemead USD | B47: Janson ES | C47: Diana | D47: 11678 | E47: 280662.6 | F47: (1) 24'x40' classroom with two restrooms | G47: 6 | H47: 46233 | I47: 46279 | J47: 1 | K47: Scope finalized on 3/6, repricing received. Next step is drawings | L47: Signed Proposal | M47: PB | O47: Yes | P47: Yes | R47: TBD | T47: =IFERROR(E47*J47,0) -> 280662.6 | U47: Unknown - AOR Submitted PC | W47: =IF(I47<>"",IF(W47="",NOW(),W47),"") -> 45692.547
A48: Cajon Valley Charter School | B48: Cajon Valley Charter School | C48: Diana | E48: TBD | F48: 4 classrooms and 1 restroom building | G48: 9 | H48: 46235 | K48: Did this go away?
A49: Keppel Union SD | B49: Lake Los Angeles ES | C49: Sandra | D49: 11627 | E49: =871254/2 -> 435627 | F49: (3) 24'x40' Standard Classroom | G49: 6 | H49: 46237 | I49: 46083 | J49: 1 | K49: Will be DSA approved but do not want deliver till spring 2026 | L49: PO1-250000001456 | O49: No | R49: TBD | S49: Joe | T49: =IFERROR(E49*J49,0) -> 435627 | U49: Mid November | V49: =IFERROR(ROUNDUP(MONTH(IF(H49<>"",H49,""))/3, 0),"TBD") -> 3 | W49: =IF(I49<>"",IF(W49="",NOW(),W49),"") -> 45813.652
A50: Ventura USD | B50: Montalvo ES | C50: Diana | D50: 11639 | E50: 1200942.4 | F50: (1) 120x40 | G50: 10 | H50: 46244 | I50: 46116 | J50: 1 | K50: Scope has been confirmed we are waiting on the AOR's response to 4 clarification items. Soils report has been povided. | L50: No | M50: PB | N50: No | O50: No | P50: No | R50: TBD | T50: =IFERROR(E50*J50,0) -> 1200942.4 | U50: Late December | V50: =IFERROR(ROUNDUP(MONTH(IF(H50<>"",H50,""))/3, 0),"TBD") -> 3 | W50: =IF(I50<>"",IF(W50="",NOW(),W50),"") -> 45692.547
A51: Oceanside USD | B51: Surfside | C51: Sandra | D51: 11562 | E51: 2884146.4 | F51: (1) 84x60 Student Center | G51: 7 | H51: 46245 | I51: 45992 | J51: 1 | K51: Will be built with the other buildings | L51: Change Order | U51: Late December
A52: Tehama County DoE | B52: Gerber ES | C52: Diana | D52: 11624 | E52: 6969553.7 | F52: BUILDING A (1) 168X40 BUILDING B (1) 156X40 BUILDING C (1) 84X40 MEDICAL THERAPY UNIT (MTU) | G52: =7+7+7+6+7 -> 34 | H52: 46258 | I52: 45992 | J52: 0.66 | K52: Adela to call Judy on 5/6/26 to confirm timing | M52: BID | P52: 45777 | S52: Joe | T52: =IFERROR(E52*J52,0) -> 4599905.4 | U52: Mid November | V52: =IFERROR(ROUNDUP(MONTH(IF(H52<>"",H52,""))/3, 0),"TBD") -> 3 | W52: =IF(I52<>"",IF(W52="",NOW(),W52),"") -> 45722.62
A53: Placentia Yorba Linda | B53: Casa Loma Expanded Learning | C53: Sandra | D53: 11663 | E53: 335998.01 | F53: (1) 12x60 TB | G53: 1 | H53: 46258 | J53: 0.4 | K53: DSA Approved pending site bid so they can award us through the lease lease back contract | T53: =IFERROR(E53*J53,0) -> 134399.2 | U53: Late April/Early May
A54: San Diego USD | B54: Gage ES | C54: Diana | D54: 11664 | E54: 508735.27 | F54: (2) 36'x40' with single user restroom | G54: 6 | H54: 46259 | I54: 46535 | J54: 0.5 | K54: DSA comments were received this week. AOR resubmitting by the end of the month | M54: BID | U54: Early January
A55: Palm Springs USD | B55: Agua Caliente ES | C55: Diana | D55: 11563 | E55: 112000 | F55: 8’-6”x16’-7” RR | G55: 1 | H55: 46266 | I55: 45943 | J55: 1 | K55: Project on hold | L55: No | M55: PB | N55: Pending Adel Release | O55: No | P55: No | R55: TBD | S55: Gino | T55: =IFERROR(E55*J55,0) -> 112000 | U55: Pending Schedule | V55: =IFERROR(ROUNDUP(MONTH(IF(H55<>"",H55,""))/3, 0),"TBD") -> 3 | W55: =IF(I55<>"",IF(W55="",NOW(),W55),"") -> 45692.547
A56: Palm Springs USD | B56: Rancho Mirage ES | C56: Diana | D56: 11571 | E56: 112000 | F56: 8’-6”x16’-7” RR | G56: 1 | H56: 46266 | I56: 45943 | J56: 1 | K56: Project on hold | L56: No | M56: PB | N56: Pending Adel Release | O56: No | P56: No | R56: TBD | S56: Gino | T56: =IFERROR(E56*J56,0) -> 112000 | U56: NOT RELEASED TO ENGINEERING | V56: =IFERROR(ROUNDUP(MONTH(IF(H56<>"",H56,""))/3, 0),"TBD") -> 3 | W56: =IF(I56<>"",IF(W56="",NOW(),W56),"") -> 45692.547
A57: Palm Springs USD | B57: Cahuilla ES | C57: Diana | D57: 11567 | E57: 112000 | F57: 8’-6” x 16’-7” RR | G57: 1 | H57: 46266 | I57: 46174 | J57: 0.25 | K57: Project on hold | L57: No | M57: PB | N57: Pending Adel Release | O57: No | P57: No | R57: TBD | T57: =IFERROR(E57*J57,0) -> 28000 | U57: NOT RELEASED TO ENGINEERING | V57: =IFERROR(ROUNDUP(MONTH(IF(H57<>"",H57,""))/3, 0),"TBD") -> 3 | W57: =IF(I57<>"",IF(W57="",NOW(),W57),"") -> 45692.547
A58: Palm Springs USD | B58: Bubbling ES | C58: Diana | D58: 11565 | E58: 112000 | F58: 8'-6" x 16'-7" RR | G58: 1 | H58: 46266 | I58: 46204 | J58: 1 | K58: Project on hold | L58: No | M58: PB | N58: Pending Adel Release | O58: No | P58: No | R58: TBD | S58: Gino | T58: =IFERROR(E58*J58,0) -> 112000 | U58: NOT RELEASED TO ENGINEERING | V58: =IFERROR(ROUNDUP(MONTH(IF(H58<>"",H58,""))/3, 0),"TBD") -> 3 | W58: =IF(I58<>"",IF(W58="",NOW(),W58),"") -> 45692.547
A59: UCR | B59: Motte | C59: Diana | E59: 683066.25 | F59: (1) 24'x50, (1) 24'x60 (1) 10'x24' Restroom | G59: 5 | H59: 46266 | J59: 0.1 | K59: Project bid on 5/11/26 to GCs - awaiting bid results.
A60: Anaheim Union HSD | B60: Loara | C60: Sandra | D60: 11675 | F60: (1) 12x40 RR | G60: 1 | H60: 46266 | J60: 0.7 | K60: Submitted to DSA will be awarded through a lease lease back contract
A61: Anaheim Union HSD | B61: Cypress | C61: Sandra | D61: 11677 | E61: 341490 | F61: (1) 12x40 RR | G61: 1 | H61: 46267 | J61: 0.7 | K61: Submitted to DSA will be awarded through a lease lease back contract
A62: Mountain View SD | B62: Parkview School TK-8 | C62: Sandra | D62: 11495 | E62: 6700000 | F62: 192X40 2-Story | G62: 32 | H62: 46268 | I62: 46387 | J62: 0.75 | K62: Adela met with district and they are working on a piggyback to include the two story architect noted it is a late fall project. Likely June bid | L62: No | M62: PB | N62: Yes | O62: Yes | P62: Yes | R62: TBD | T62: =IFERROR(E62*J62,0) -> 5025000 | U62: November? (AOR has been very slow with this project) | V62: =IFERROR(ROUNDUP(MONTH(IF(H62<>"",H62,""))/3, 0),"TBD") -> 3 | W62: =IF(I62<>"",IF(W62="",NOW(),W62),"") -> 45692.547
A63: Mobile Modular | B63: Stock | C63: Diana | E63: 1314695 | F63: (10) 12'x40' Restrooms | G63: 10 | H63: 46296 | I63: 45962 | J63: 0.8 | K63: Dealer has confirmed these will be fall/winter production. Per Adela, more updates will be provided between April and May. Pending MM's pipeline/leasing performance. | L63: No | M63: Bid | N63: No | O63: No | P63: No | T63: =IFERROR(E63*J63,0) -> 1051756 | U63: NOT RELEASED TO ENGINEERING | V63: =IFERROR(ROUNDUP(MONTH(IF(H63<>"",H63,""))/3, 0),"TBD") -> 4 | W63: =IF(I63<>"",IF(W63="",NOW(),W63),"") -> 45692.547
A64: Mobile Modular | B64: Charles White Park | C64: Diana | D64: 11682 | E64: 1477409.2 | F64: (1) 64'x 79' Community Building HCD approval | H64: 46296 | I64: 46472 | J64: 0.6 | K64: PO received for the design of the project
A65: Imperial County | B65: Early Care and Education Program - IVEC | C65: Diana | D65: 11649 | F65: 120' x 40' classroom buildings | G65: 10 | H65: 46300 | J65: 0.4 | K65: Likely to start in January 2027. | U65: Late February
A66: Anaheim Union HSD | B66: Savannah | C66: Sandra | D66: 11676 | F66: (1) 12x60 RR | H66: 46307 | K66: Submitted to DSA will be awarded through a lease lease back contract
A67: Long Beach USD | B67: Poly HS Concession | C67: Sandra | D67: 11646 | E67: 710083.39 | F67: (1) 12’x80’ Concession Building | G67: 2 | H67: 46308 | I67: 46114 | J67: 1 | K67: Met with PM onsite and they anticipate delivery in Decemeber | T67: =IFERROR(E67*J67,0) -> 710083.39 | U67: Pending Final Contract
A68: PMSI | B68: Center Mod | C68: Diana | E68: 76987.84 | F68: (1) 12'x60' | G68: 1 | H68: 46321 | I68: 46346 | J68: 0.1 | K68: FOB SCM's gate.
A69: William Scotsman | B69: William Scotsman | C69: Diana | E69: TBD | F69: (4) 36'x40' Classrooms with TI, Delivery & install options | G69: 12 | H69: 46357 | I69: 46419 | J69: 0.1 | K69: Updating scope and submitting to estimating - happening sooner?
A70: Hesperia USD | B70: Joshua Circle | C70: Sandra | E70: 910466.84 | F70: (1) 72x40 TK | G70: 6 | H70: 46357 | I70: 46174 | J70: 1 | K70: Talked to Hesperia on 5/6/26 - likely late 2026 start. | L70: No | M70: PB | P70: Yes | S70: Gino | T70: =IFERROR(E70*J70,0) -> 910466.84 | U70: Approved | V70: =IFERROR(ROUNDUP(MONTH(IF(H70<>"",H70,""))/3, 0),"TBD") -> 4 | W70: =IF(I70<>"",IF(W70="",NOW(),W70),"") -> 45692.547
A71: Menifee USD | B71: Quail Valley ES | C71: Diana | E71: 1414508.7 | F71: (1) 144x40 | G71: 12 | H71: 46388 | I71: 46357 | J71: 0.2 | K71: A 2027 project - waiting on funding | L71: No - Cost Increase | M71: RFP | N71: Yes | O71: No | P71: Hold | T71: =IFERROR(E71*J71,0) -> 282901.74 | U71: NOT RELEASED TO ENGINEERING | V71: =IFERROR(ROUNDUP(MONTH(IF(H71<>"",H71,""))/3, 0),"TBD") -> 1 | W71: =IF(I71<>"",IF(W71="",NOW(),W71),"") -> 45692.547
A72: Mobile Modular | B72: Crestview Charter | C72: Diana | D72: 11650 | E72: 4271574.3 | F72: (1) 132' x 40' 2-story Building | G72: 22 | H72: 46388 | I72: 46600 | J72: 1 | K72: Repricing of project to start 3/23 | L72: PO - 298000690 | M72: Bid | N72: N/A | U72: July
A73: South Kern | B73: Rosamond High Early College | C73: Diana | E73: 145661.82 | F73: (1) 8.6x21'-6" Restroom Building | G73: 1 | H73: 46388 | I73: 46478 | J73: 0.5 | K73: This project resurfaced today. Architect is to send District specs for repricing.
A74: Folsom Cordova USD | B74: Granite Springs ES | C74: Frank | D74: 11686 | E74: 7087082 | F74: (1) 156'x 40 & (1) 144'x 40' | G74: 25 | H74: 46388 | I74: 46569 | J74: 1 | K74: 5/14 Kickoff meeting scheduled to release to engineering
A75: Griffin Technology Academies | B75: Mare Island Technology Academy | C75: Joe | D75: 11372 | E75: =24946125-12110305 -> 12835820 | F75: BUILDING B (1) 96x40 2-story BUILDING C (1) 168x40 2-story + Elevator | G75: =(96/12*2)+(168/12*2) -> 44 | H75: 46388 | I75: 46266 | J75: 0.5 | K75: Per BHM, NTP on hold until March 2026 | L75: Subcontract C-13340-S | M75: Bid | N75: Bid | S75: Joe | T75: =IFERROR(E75*J75,0) -> 6417910 | U75: Approved | V75: =IFERROR(ROUNDUP(MONTH(IF(H75<>"",H75,""))/3, 0),"TBD") -> 1 | W75: =IF(I75<>"",IF(W75="",NOW(),W75),"") -> 45692.547
A76: Oxnard SD | B76: Freemont MS | C76: Sandra | D76: 11684 | E76: TBD | F76: (2) 36x40 Buildings | G76: 6 | H76: 46388 | K76: Update as of 5/6/26 - production start in Jan 2027; full bin submittal
A77: Romoland SD | B77: Granite Hills School | C77: Diana | E77: 882755.16 | F77: (6) 24'x40' Classrooms | G77: 12 | H77: 46392 | I77: 46514 | J77: 0.25 | K77: Likely to purchase by August 2026.
A78: Menifee USD | B78: Menifee ES | C78: Diana | D78: 11631 | E78: 10198770 | F78: (1)168' x 40' (1)108' x 40' (1)156' x 40' (1)72' x 40' (1)84' x 40' (1)120' x 40' | G78: 59 | H78: 46432 | I78: July 1/2028 | J78: 0.5 | K78: In DSA | U78: Late May
A79: Wasco Union HSD | B79: Wasco HS | C79: Joe | D79: 11582 | E79: =1346682.56+1623583.67 -> 2970266.2 | F79: (5) 30X32 Classrooms (1) 30X32 Restroom | G79: =(5*3)+(1*3) -> 18 | H79: 46447 | I79: 46510 | J79: 1 | K79: Per District, project on pause until March 2027 | L79: PO 250310 | M79: Bid | N79: Bid | O79: 45597 | P79: 45617 | S79: Joe | T79: =IFERROR(E79*J79,0) -> 2970266.2 | U79: Approved | V79: =IFERROR(ROUNDUP(MONTH(IF(H79<>"",H79,""))/3, 0),"TBD") -> 1 | W79: =IF(I79<>"",IF(W79="",NOW(),W79),"") -> 45692.547
A80: Lowell SD | B80: Meadow Green ES | C80: Sandra | D80: 11651 | E80: 1523311.2 | F80: 84x60 Classrooms w/RR | G80: 7 | H80: 46464 | J80: 1 | K80: In DSA | L80: PO W99B0030 | U80: NOT RELEASED TO ENGINEERING
A81: Redlands USD | B81: Moore MS | C81: Diana | E81: 203200.93 | F81: (1) 12'x40' Restroom buildings | G81: 1 | H81: 46478 | I81: 46600 | J81: 0.8 | K81: Following up on PO to start drawings
A82: Redlands USD | B82: Cope MS | C82: Diana | D82: 11683 | E82: 203200.93 | F82: (1) 12'x40' Restroom Bldg | G82: 1 | H82: 46508 | I82: 46600 | J82: 1 | K82: Drawings in process
A83: Stanislaus USD | B83: Chrysler ES | C83: Diana | F83: (8) 24x40 permanent classroom buildings | G83: =4*2 -> 8 | H83: 46539 | I83: 46631 | J83: 0.2 | K83: Early stage of project. Pending Adela to call architect - Diana to have update by 5/28/26. | T83: =IFERROR(E83*J83,0) -> 0 | U83: NOT RELEASED TO ENGINEERING | W83: =IF(I83<>"",IF(W83="",NOW(),W83),"") -> 45692.547
A84: Mike Forrest | B84: Mike Forrest | C84: Diana | E84: 15001894 | F84: Two Story Building | H84: 46664 | J84: 0.1 | K84: Pending scope clarification for pricing
A85: Unified Modular | B85: Unified Modular | C85: Diana | F85: (1) 24'x40' w/ 3-single user restrooms | G85: 2 | I85: 46239 | J85: 0.1
A86: Safeworx-Pomona USD | B86: Lincoln ES | C86: Sandra | E86: 604126 | F86: (1) 36x40, (1) 48x40 (1) 24x40 and (1) 12x40 TB | G86: 10 | K86: Requested additional photos but we still do not have very many photos of any standard 24x40 buildings.
A87: Mt. San Antonio College | B87: Mt. SAC | C87: Diana | E87: 758144.44 | F87: 36x60 Building A | G87: 3 | H87: Pending | J87: 0.75 | K87: Finalizing proposal for buildings A-E. Project on hold due to personnel changes. No update | L87: No | N87: Yes | O87: Yes | P87: Yes | R87: TBD | T87: =IFERROR(E87*J87,0) -> 568608.33 | U87: Approved | W87: =IF(I87<>"",IF(W87="",NOW(),W87),"")
A88: Mt. San Antonio College | B88: Mt. SAC | C88: Diana | E88: 733915.11 | F88: 36x60 Building B | G88: 3 | H88: Pending | J88: 0.75 | K88: Finalizing proposal for buildings A-E. Project on hold due to personnel changes. No change | L88: No | N88: Yes | O88: Yes | P88: Yes | R88: TBD | T88: =IFERROR(E88*J88,0) -> 550436.33 | U88: Approved | W88: =IF(I88<>"",IF(W88="",NOW(),W88),"")
A89: Mt. San Antonio College | B89: Mt. SAC | C89: Diana | E89: 787663.96 | F89: 36x60 Building C | G89: 3 | H89: Pending | J89: 0.75 | K89: Finalizing proposal for buildings A-E. Project on hold due to personnel changes. No change | L89: No | N89: Yes | O89: Yes | P89: Yes | R89: TBD | T89: =IFERROR(E89*J89,0) -> 590747.97 | U89: Approved | W89: =IF(I89<>"",IF(W89="",NOW(),W89),"")
A90: Mt. San Antonio College | B90: Mt. SAC | C90: Diana | E90: 743756.62 | F90: 36x60 Building D | G90: 3 | H90: Pending | J90: 0.75 | K90: Finalizing proposal for buildings A-E. Project on hold due to personnel changes | L90: No | N90: Yes | O90: Yes | P90: Yes | R90: TBD | T90: =IFERROR(E90*J90,0) -> 557817.46 | U90: Approved | W90: =IF(I90<>"",IF(W90="",NOW(),W90),"")
A91: Mt. San Antonio College | B91: Mt. SAC | C91: Diana | E91: 743756.62 | F91: 36x60 Building E | G91: 3 | H91: Pending | J91: 0.75 | K91: Finalizing proposal for buildings A-E. Project on hold due to personnel changes | L91: No | R91: TBD | T91: =IFERROR(E91*J91,0) -> 557817.46 | U91: Approved | W91: =IF(I91<>"",IF(W91="",NOW(),W91),"")
A92: Menifee USD | B92: Freedom Crest ES | C92: Diana | E92: 2467455.7 | F92: (1) 72x40 & (1) 108x40 | G92: 15 | H92: TBD - Funding | I92: 46574 | J92: 0.2 | K92: 2027 project | L92: No - Cost Increase | M92: RFP | N92: Yes | O92: No | P92: Hold | T92: =IFERROR(E92*J92,0) -> 493491.15 | U92: NOT RELEASED TO ENGINEERING | W92: =IF(I92<>"",IF(W92="",NOW(),W92),"") -> 45692.547
A93: Beaumont USD | B93: Starlight Elementary School | C93: Diana | E93: 328527.46 | F93: Wood Foundation with ramps: (2) 24x40 & or 1 (1) 48x40 (1) 12x40 restroom - Boy/Girl Staff/Staff | G93: 5 | I93: 46600 | J93: 0.75 | K93: Pricing updates requested 3/7 - pending approval to proceed
A94: Beaumont USD | B94: Sundance Elementary School | C94: Diana | E94: 328527.46 | F94: Wood Foundation with ramps: (2) 24x40 & or 1 (1) 48x40 (1) 12x40 restroom - Boy/Girl Staff/Staff | G94: 5 | I94: 46600 | J94: 0.75 | K94: Pricing updates requested 3/7 - pending approval to proceed
A95: Menifee USD | B95: Oak Meadows ES | C95: Diana | E95: 2885231.4 | F95: (1) 288x40 | G95: 24 | I95: 46209 | J95: 0.2 | K95: 2027 project | L95: No - Cost Increase | M95: RFP | N95: Yes | O95: No | P95: Hold | T95: =IFERROR(E95*J95,0) -> 577046.29 | U95: NOT RELEASED TO ENGINEERING | W95: =IF(I95<>"",IF(W95="",NOW(),W95),"") -> 45692.547
A96: Mobile Modular | B96: Stock Restrooms | C96: Diana | E96: 298624.09 | F96: (2) 8’-6”x 16’-7" and (2) 8’-6”x 21-7" Restrooms | K96: Mobile Modular bidding on this - postponed
A97: Oceanside USD | B97: El Camino HS | C97: Diana | E97: 7499019.9 | F97: Two Story - 8 classroom building, two restroom building B/G/S, weight room - 4,000 S.F., P.E. Classroom | I97: 46539 | J97: 0.1 | K97: Proposal sent to Adela on 1/21/26 - on hold pending location on campus of two-story
A98: Oceanside USD | B98: North Terrace | C98: Diana | E98: 21141092 | F98: (1) 112X72, (1) 112X36, (1) 96X36 classroom buildings and support space, Two Story (1) 180'x40' and (1) 185'x40', MPR Support Buildings | K98: Pricing changes request on 2/19 - Diana working on proposal Adela contacting district on 5/7/26 re: Balfour Beatty LLB award
A99: SDUSD | B99: Jerabek ES | C99: Diana | F99: (4) 24'x40' Classrooms (1) 12'x40' Restroom | J99: 0.1 | K99: AOR reviewing our PC - meeting on 5/22/26 if they need to purchase or can pull from stock. | U99: NOT RELEASED TO ENGINEERING
A100: Unified Modular | B100: Garvy SD | C100: Diana | E100: 164934.27 | F100: (1) 12'x40' Restroom Building Model C-2 | G100: 1 | J100: 0.4 | K100: beta
...

Sheet ML Analysis
B2: Customer Name | C2: Project Name | D2: BDM | E2: Contract Value | F2: Building(s) | G2: Floor Count | H2: Start Date | I2: Current Status/Notes | J2: Lost Code | K2: Bid or Piggyback | L2: Lost to | M2: Enviroplex | N2: Class Leasing | O2: Mobile Modular | P2: AMS | Q2: GLOBAL | R2: SCM | S2: Var% to AMS | Y2: Customer Name | Z2: Lost Code
B3: Sierra Sands USD | C3: Murray MS | D3: Joe | F3: BUILDING C (1) 36X40 + (3) 30X32 BUILDING E (7) 30X32 | H3: 45658 | I3: Ryan to find out if we can meet bid due date | J3: Schedule | K3: PB | Y3: Sierra Sands USD | Z3: Schedule
B4: Ballico-Cressey SD | C4: Cressey ES | D4: Joe | E4: 3052557.5 | F4: (2) 72x40 TK (1) 12x40 RR | G4: 13 | I4: AMS $2,748,000 Global $2,854,000 SCM $3,052,557 | J4: Price | K4: PB | L4: AMS | P4: 2748000 | Q4: 2854000 | R4: 3052557 | S4: =(R4-P4)/P4 -> 0.1108286 | Y4: Ballico-Cressey SD | Z4: Price
B5: Victor Valley ESD | C5: Challenger ES | D5: Adela | E5: 382000 | F5: (1) 24x40 RR/Concession Bldg | I5: Timing, Pricing, Pass on location, Lost Funding, or went with Lease or Stick | J5: Price | Y5: Victor Valley ESD | Z5: Price
B6: Victor Valley ESD | C6: Lomitas ES | D6: Adela | E6: 260298 | F6: (1)24’x40 Restroom | I6: Over 80 deals we've looked at and didn't proceed with. | J6: Price | Y6: Victor Valley ESD | Z6: Price
B7: Tsumiki Preschool | C7: Tsumiki Preschool | D7: Diana | F7: (1) 36'x60' | I7: Cost of a new building was too much for the customer's budget | J7: price | Y7: Tsumiki Preschool | Z7: price
B8: Simi Valley | C8: Hillside MS | D8: Diana | E8: 291416.77 | F8: (2) 24'x40' | G8: 4 | H8: 45366 | I8: Schedule too tight to meet. | J8: Schedule | Y8: Simi Valley | Z8: Schedule
B9: La Mesa-Spring Valley | C9: Parkway Academy MS | D9: Diana | F9: (1) 24'x40' | I9: Cost of a new building was too much for the customer's budget | J9: Funding | Y9: La Mesa-Spring Valley | Z9: Funding
B10: Jefferson SD | C10: Corral Hollow ES | D10: Joe | E10: 2990052.7 | F10: BUILDING A (1) 36x40 TK BUILDING B (1) 108x40 TK BUILDING C (1) 36x40 TK BUILDING D (1) 108x40 PE CR | G10: 24 | I10: District does not have the funding to move forward per PJHM | J10: Funding | K10: PB | Y10: Jefferson SD | Z10: Funding
B11: Merced City SD | C11: Franklin ES | D11: Joe | E11: 6826236 | F11: WING A (1) 196X40 WING B (1) 160X40 | G11: 29 | H11: 45748 | I11: 1. AMS $5,948,000.00 ($878K below SCM) 2. Global $6,546,000.00 ($280K below SCM) 3. Silver Creek $6,826,236.00 | J11: Price | K11: Bid | L11: AMS | P11: 5948000 | Q11: 6546000 | R11: 6826236 | S11: =(R11-P11)/P11 -> 0.14765232 | Y11: Merced City SD | Z11: Price
B12: Bishop USD | C12: MOT Yard | D12: Joe | E12: 878824.03 | F12: (1) 72X40 Office Bldg | G12: 6 | H12: TBD | I12: Our price is too high. District expoloring other options | J12: Price | K12: PB | Y12: Bishop USD | Z12: Price
B13: Sylvan USD | C13: Somerset MS | D13: Joe | E13: 461894.85 | F13: (1) 60x40 Childcare | G13: 5 | H13: 45566 | I13: Lost deal to AMS $415,287.00 | J13: Price | K13: PB | L13: AMS | P13: 415287 | R13: 461894.85 | S13: =(R13-P13)/P13 -> 0.11223046 | Y13: Sylvan USD | Z13: Price
B14: Downey USD | C14: Downey USD | D14: Adela | F14: (13) TK Classrooms | I14: Pricing too high | J14: Price | K14: PB | Y14: Downey USD | Z14: Price
B15: Hemet USD | C15: Hemet HS | D15: Adela-Sandra | E15: 570182.81 | F15: (4) 24x40 | G15: 8 | H15: TBD | I15: Lost to Competitor | J15: Price | K15: PB | Y15: Hemet USD | Z15: Price
B16: Orange USD | D16: Adela-Sandra | E16: 257193 | F16: (2) 24X40 | G16: 4 | H16: TBD | I16: Lost to Competitor | J16: Price | K16: PB | Y16: Orange USD | Z16: Price
B17: Academy for Advancement of Children with Autism | C17: AACA | D17: Adela-Sandra | E17: 584811.41 | F17: 96x60 Classroom | G17: 8 | H17: TBD | I17: Lost to Competitor | J17: Price | K17: PB | Y17: Academy for Advancement of Children with Autism | Z17: Price
B18: South San Francisco USD | C18: Los Cerritos ES | D18: Joe | E18: 157240.21 | F18: (1) 12x40 RR | G18: 1 | H18: 45597 | I18: Project will go out to bid. | J18: Price | K18: PB | Y18: South San Francisco USD | Z18: Price
B19: ASYMCA | C19: ASYMCA | D19: Diana | E19: 1915724.6 | F19: (2) 60'x60 CR Bldgs. | G19: 12 | H19: 45580 | I19: Customer had concerns with SCM's pricing after all the finishes were upgraded. They moved on and procure the buildings from Phoenix Modular. | J19: Price | K19: PB | L19: Phoenix Modular | Y19: ASYMCA | Z19: Price
B20: San Jacinto USD | C20: Facilities & Operations | D20: Adela-Sandra | E20: 2884615 | F20: (1) 144'x48' | G20: 12 | H20: 45778 | I20: On hold | J20: MISC | K20: PB | Y20: San Jacinto USD | Z20: MISC
B21: Blok Modular | C21: Las Palmas | D21: Diana | F21: (1) 12'x40', (1) 12'x24', (1) 12'x50', (1) 12'x40' RR Bldgs. | G21: 5 | H21: TBD | I21: SCM pricing was 30% higher than our competitors, per Blok's owner. | J21: Price | K21: PB | S21: 0.3 | Y21: Blok Modular | Z21: Price
B22: Fall River JUSD | C22: Fall River ES | D22: Joe | F22: (4) 24x40 2:12 PC Classrooms | G22: 8 | H22: 45658 | I22: 8/20 Per Steve, proceed with estimating 8/21 submitted to estimating SCM to outsource delivery, installation and service to DVMB. Our pricing is three times the District's budget. | J22: MISC | K22: PB | Y22: Fall River JUSD | Z22: MISC
B23: Marysville JUSD | C23: Arboga ES | D23: Joe | E23: 260240.33 | F23: (1) 40X32 | G23: 4 | H23: 45627 | I23: Lost to Mobile Modular $209,597 | J23: price | K23: Bid | O23: 209597 | R23: 260240.33 | Y23: Marysville JUSD | Z23: price
B24: Cajon Valley USD | C24: Johnson ES | D24: Diana | F24: (1) 24'x40' Classroom | G24: 2 | H24: 45778 | I24: Lost deal to AMS per the district we were higher. SCM provided a list of why our buidlings are more expensive than AMS. | J24: price | K24: PB | L24: AMS | Y24: Cajon Valley USD | Z24: price
B25: Cajon Valley USD | C25: Avocado ES | D25: Diana | F25: (3) 30'X32' Classrooms | G25: 9 | H25: 45778 | I25: Lost deal to AMS per the district we were higher. SCM provided a list of why our buidlings are more expensive than AMS. | J25: price | K25: PB | L25: AMS | Y25: Cajon Valley USD | Z25: price
B26: Waterford USD | C26: Moon PS | D26: Joe | E26: 5166484 | F26: (2) 144x40 TK Bldgs | G26: 24 | H26: 46113 | I26: Low Bidder: Global $4,440,000 $385/SF ($726,484) AMS $4,498,000 $390/SF ($668,484) SCM $5,166,484 $448/SF | J26: price | K26: Bid | L26: Global | P26: 4498000 | Q26: 4440000 | R26: 5166484 | S26: =(R26-P26)/P26 -> 0.14861805 | Y26: Waterford USD | Z26: price
B27: Arcadia USD | F27: (10) 24x40 | G27: 20 | H27: 45809 | Y27: Arcadia USD
B28: San Rafael City Schools | C28: Terra Linda HS | D28: Adela-Sandra | E28: 644754.52 | F28: 24x40 Concession/RR 8-6x21-6 Storage/Ticket | G28: 3 | H28: TBD | I28: Customer was notified that SCM could not proceed with project if they required us to meet project bid manual | K28: GC | Y28: San Rafael City Schools
B29: PMSI - Michael Thompson | C29: 36'x48' | D29: Diana | E29: 206387.63 | F29: 36'x48' HCD building | G29: 3 | H29: TBD | I29: Lost deal due to pricing. | J29: price | Y29: PMSI - Michael Thompson | Z29: price
B30: Cal State Long Beach | C30: Cal State Long Beach | D30: Sandra | F30: (1) 12x40 TB | G30: 1 | I30: Customer has decided to lease bldg | J30: MISC | Y30: Cal State Long Beach | Z30: MISC
B31: Irvine Community College | C31: Irvine Community College | D31: Sandra | F31: (1) 48x40 Locker Room | G31: 4 | H31: TBD | I31: Bought a used building | J31: MISC | Y31: Irvine Community College | Z31: MISC
B32: LAUSD- Irving Steam Magnet | D32: Adela-Sandra | E32: 0 | F32: 72x40 | G32: 6 | H32: 45748 | I32: Provided Quote 10/14/24 | Y32: LAUSD- Irving Steam Magnet
B33: Hueneme ESD | C33: Larsen ES & Hollywood ES | D33: Diana | E33: 0 | F33: (6) 72'x40' TK Buildings | G33: 36 | H33: 45748 | I33: SCM agreed to not bid. Bid Results are as follows: Class Leasing $2,434,693.00 ($140.896) , NextMod $2,736,417.84 ($158.3575), Global Modular $3,398,500.00 ($196.672) SF. total: 17,280 | J33: MISC | Y33: Hueneme ESD | Z33: MISC
B34: Blok Modular | C34: Fort Irwin | D34: Diana | F34: (1) 12'x24' DOH | G34: 1 | H34: TBD | I34: SCM pricing was too high | J34: Price | Y34: Blok Modular | Z34: Price
B35: SDUSD | C35: Hardy ES | D35: Diana | F35: (4) 36'x40 CRs w/ RRs, (6) 24'x40' Open CRs, (1) 12'x40' RR | G35: 25 | H35: 2026 | I35: SCM pricing was too high | J35: Price | K35: 2026 | Y35: SDUSD | Z35: Price
B36: Cypress College | D36: Sandra | E36: 365832.45 | F36: 24x40 Bldg | G36: 2 | H36: TBD | I36: Lost due to timeline | J36: Schedule | Y36: Cypress College | Z36: Schedule
B37: Unified Modular | C37: Montebello USD | D37: Diana | F37: (1) 24'X40' CR | G37: 2 | H37: N/A | I37: Customer submitted proposal pending board approval. Project not awarded to our customer | J37: Funding | Y37: Unified Modular | Z37: Funding
B38: San Mateo County Community College District | C38: Cañada College | D38: Joe | E38: 5000000 | F38: (1) 107X37 Building A (1) 120x37 Building B | G38: 17 | H38: 45839 | I38: No bid per Dennis and Ryan. Unable to provide a Cross Laminated Mass Timer (CLT) modular building per bid specs. | J38: Technical | K38: 46023 | Y38: San Mateo County Community College District | Z38: Technical
B39: Bush Construction | C39: Firebaugh-Las Deltas USD Bailey PS | D39: Joe | E39: 6388910.2 | F39: (1) 24x40 Office Building (7) 72x40 TK | G39: 44 | H39: 45901 | I39: Class Leasing - 1st place $5.7M $287/SF 145/145 Best Value Scoring SCM - 2nd place $6.3M $370/SF 109/145 Best Value Scoring Enviroplex - 3rd place $8.8M $438/SF 82/145 Best Value Scoring | J39: Price | K39: PB | L39: Class Leasing | M39: 8800000 | N39: 5700000 | R39: 6300000 | Y39: Bush Construction | Z39: Price
B40: DV Modular | C40: DV Modular | D40: Diana | F40: (1) 24'x60' Open Building | G40: 2 | I40: SCM pricing was too high compared to SF pricing dealer had submitted to their customer | J40: Price | K40: PB | Y40: DV Modular | Z40: Price
B41: Fairfax SD | C41: District Office | D41: Joe | E41: 7000000 | F41: (1) 200X60 Admin Bldg | G41: 30 | H41: 46023 | I41: no bid, building not modular friendly. 27' high | J41: Technical | K41: Winter 2025 | Y41: Fairfax SD | Z41: Technical
B42: Jurupa Valley USD | C42: Jurupa MS | D42: Sandra | E42: 0 | F42: (1) 48x40 | G42: 4 | I42: Provided revised proposal on a wide open 48x40. Architect reviewing with customer. | J42: MISC | K42: Summer 2025 | Y42: Jurupa Valley USD | Z42: MISC
B43: Lathrop Construction | C43: Foothill HS | D43: Joe | E43: 5000000 | F43: (1) 158x50 Weight/Fitness Building | G43: TBD | H43: 46023 | I43: Lathrop did not get the project. | J43: Funding | K43: Summer 2026 | Y43: Lathrop Construction | Z43: Funding
B44: Montebello USD | C44: Ford Adult School | D44: Diana | F44: 10ea. 24’x40’ Classrooms 1ea. 24’x40’ RR Building 1ea. 24’x40’ Career Center Bldg. 1ea. 48’x40’ Admin Bldg. 1ea. 48’x40’ Enrollment Bldg. 1ea. 96’x40’ MPR Building | G44: 40 | H44: 45748 | I44: Global Modular - 1st place $6,451,000 - Awarded to Lowest Bidder Silver Creek - $7,306,383 Next Mod was disqualified from bidding however their bid amount was $6,193,000. | J44: Price | K44: Bid | L44: Global | Q44: 6451000 | R44: 7306383 | Y44: Montebello USD | Z44: Price
B45: Golden Plains USD | C45: Tranquility HS | D45: Joe | F45: (1) 48x40 Concession Building (1) 12x40 Breezeway (1) 72x40 PE Classroom Building | G45: 11 | H45: 45873 | I45: No bid | J45: Technical | K45: 46118 | Y45: Golden Plains USD | Z45: Technical
B46: Alhambra USD | C46: Ramona ES | D46: Sandra | E46: 319344.66 | F46: (1) 48x40 Serving Room | G46: 4 | H46: 45748 | I46: went to Next Mod because of price and drawing time | J46: Schedule | Y46: Alhambra USD | Z46: Schedule
B47: Arc Construction | D47: Sandra | I47: Project required price for Slab on Grade Bldg | Y47: Arc Construction
B48: City of Los Angeles Department of Public Works | C48: Slauson Connect Recreation Center | D48: Diana | F48: (1) 8,740 Sq Ft Two Story | I48: Lost deal due to timing. Pricing window was too short. | J48: Schedule | K48: Completion 2026 | Y48: City of Los Angeles Department of Public Works | Z48: Schedule
B49: Los Angeles Community College District | D49: Sandra | F49: 5 offices, restrooms, ADA Ramp, Stairs, Conference room and breakroom | I49: Reached out to customer twice via call and email still awaiting response - Non Responsive | Y49: Los Angeles Community College District
B50: Huntington Beach | C50: Marina HS | D50: Sandra | E50: 1712677.8 | F50: (8) 24x40 | G50: 16 | H50: 45748 | I50: Project has been canceled working on any costs that we have on the project | J50: Funding | K50: Summer 2025 | Y50: Huntington Beach | Z50: Funding
B51: Hemet USD | C51: Dartmouth-ELOP | D51: Sandra | E51: 1318085 | F51: (1) 204x40 | G51: 17 | I51: AMS provided lower cost | J51: Price | K51: Bid | L51: AMS | Y51: Hemet USD | Z51: Price
B52: Hemet USD | C52: ELOP | D52: Sandra | E52: 2426901.9 | F52: (2) 84x40 and (2) 60x40 | G52: 24 | I52: AMS provided lower cost | J52: Price | K52: Bid | L52: AMS | Y52: Hemet USD | Z52: Price
B53: Del Mar Union | C53: Carmel Del Mar ES | D53: Diana | E53: 370756.69 | F53: (1) 48'x40' (2) CR Bldg. | G53: 4 | H53: 45839 | I53: The district is not replacing their old portables as part of the ongoing modernization | J53: MISC | K53: Summer 2025 | Y53: Del Mar Union | Z53: MISC
B54: Del Mar Union | C54: Del Mar Hills Academy | D54: Diana | E54: 347067.59 | F54: (1) 48'x40' (2) CR Bldg. | G54: 4 | H54: 45992 | I54: The district is not replacing their old portables as part of the ongoing modernization | J54: MISC | K54: 45992 | Y54: Del Mar Union | Z54: MISC
B55: Mobile Modular | C55: FOB - Garfield HS Science Classroom | D55: Joe | E55: 361412.11 | F55: (1) 36x40 Science Classroom | G55: 3 | H55: Winter 2025 | I55: Mobile Modular to go with their used inventory for this project ILO brand new | J55: MISC | K55: Negotiated | Y55: Mobile Modular | Z55: MISC
B56: Palmdale SD | C56: Palmdale Academy Charter School (PACS) | D56: Joe | F56: (1) 204x96 Two Story | I56: ROM pricing in august/sept to AOR. Site Build over budget, switching to modular. Project dead per Adel | J56: Funding | Y56: Palmdale SD | Z56: Funding
B57: City of Shafter | C57: Aquatic Center | D57: Joe | F57: (1) 125x25 Aquatic Center | G57: 10 | I57: The client has decided to stick build with slab on grade. | J57: MISC | K57: No | Y57: City of Shafter | Z57: MISC
B58: Indoff | C58: Lake Tahoe Community College | D58: Joe | F58: (3) 36x60 Training Facility | G58: 9 | I58: Competitor pricing at $130/SF. SCM is at $325-$425/SF. | J58: Price | K58: No | Y58: Indoff | Z58: Price
B59: Lancaster SD | C59: Sunnydale ES | D59: Joe | F59: (1) SCIENCE LAB (1) MUSIC BUILDING (3) CLASSROOM BUILIDNGS | H59: 46023 | I59: We were not prequalified with PQbids due to missing 2 years of audited financials | J59: Pre-qual | K59: No | Y59: Lancaster SD | Z59: Pre-qual
B60: Island Union ESD | C60: Island Union ES | D60: Joe | F60: (2) 36x40 UPK Buildings | G60: 6 | I60: No bid due to addendum 3 requirement of 3.5:12 roof pitch | J60: Technical | K60: No | Y60: Island Union ESD | Z60: Technical
B61: Calistoga JUSD | C61: Calistoga ES | D61: Joe | E61: 2000000 | F61: (4) TK Classrooms | G61: TBD | H61: 45931 | I61: LLB. Partner up with GC for Best Value. 9/27 Landmark earned Best Value by earning the most points, 317 | J61: MISC | K61: No | Y61: Calistoga JUSD | Z61: MISC
B62: PMSI Ewles Materials 12x56 | C62: PMSI Ewles Materials 12x56 | D62: Diana/Quinton | E62: 126603.27 | F62: (1) 12'x56' with axels | G62: 1 | I62: SCM pricing was too high | J62: Price | Y62: PMSI Ewles Materials 12x56 | Z62: Price
B63: Reef-Sunset USD | C63: Tamarack ES | D63: Joe | E63: 3843937 | F63: (2) 72X40 CLASSROOM BLDGS (2) 96X40 CLASSROOM BLDGS (2) 12x40 RESTROOM BLDGS | G63: 30 | H63: 46266 | I63: ENVIROPLEX $203.39/SF SCM $249.77/SF | J63: Price | K63: 45695 | L63: Envir | Y63: Reef-Sunset USD | Z63: Price
B64: Selma USD | C64: Jackson ES | D64: Joe | E64: 978861.98 | F64: (1) 72x40 TK | G64: 6 | H64: 45962 | I64: 1) Enviroplex $892,570 ($310/SF) 2) SCM $978,682 ($340/SF) 3) AMS $1,040,000 ($361/SF) 4) Global $1,094, 837 ($380/SF) 5) NextMod $1,226,880 ($426/SF) | J64: Price | K64: No | L64: Envir | M64: 892570 | P64: 1040000 | Q64: 1094837 | R64: 978682 | S64: =(R64-P64)/P64 -> -0.058959615 | Y64: Selma USD | Z64: Price
B65: Unified Modular | C65: Classroom Buildings | D65: Diana | F65: (1) 24'x40' w/ single user RR and (1) 36'x40' w/ single user RR | G65: 5 | H65: TBD | I65: Customer did not need the new units after all | J65: MISC | Y65: Unified Modular | Z65: MISC
B66: Pacific Mobile | C66: Multi-Story Housing Units | D66: Joe | I66: Per Steve, No | J66: MISC | Y66: Pacific Mobile | Z66: MISC
B67: Cumming Group | C67: Primo Facchini | D67: Joe | F67: ADA portable restrooms | I67: They're looking for porta potties, not modular restroom buildings. | J67: MISC | Y67: Cumming Group | Z67: MISC
B68: Orange USD | C68: Imperial ES | D68: Sandra | E68: 221547 | F68: (1) 36x40 Classroom | G68: 3 | H68: 45901 | I68: Due to time restraints the customer has elected to refurbish some of their existing units | J68: Schedule | Y68: Orange USD | Z68: Schedule
B69: Orange USD | C69: Villa Park ES | D69: Sandra | E69: 221547 | F69: (1) 36x40 Classroom | G69: 3 | H69: 45901 | I69: Due to time restraints the customer has elected to refurbish some of their exsisting units | J69: Schedule | Y69: Orange USD | Z69: Schedule
B70: Orange USD | C70: Panorama ES | D70: Sandra | F70: (1) 36x40 Classroom & Demo (1) 24x40 Bldg | G70: 3 | H70: 45901 | I70: Due to time restraints the customer has elected to refurbish some of their exsisting units | J70: Schedule | Y70: Orange USD | Z70: Schedule
B71: Garden Grove USD | C71: Multiple Sites | D71: Sandra | F71: 12x40 TB, 24x40 and 36x40 Classrooms | G71: 6 | I71: Our price was too high | J71: Price | Y71: Garden Grove USD | Z71: Price
B72: PMSI Dixon Lake Ranger Station | C72: PMSI Dixon Lake Ranger Station | D72: Diana/Quinton | E72: 288275.57 | F72: (1) 24'x64' with axels | G72: 2 | I72: Our price was too high | J72: Price | K72: No | Y72: PMSI Dixon Lake Ranger Station | Z72: Price
B73: OCFA | C73: Laundry Facility | D73: Diana | F73: (1) 66'x42' | G73: 9 | H73: TBD - Bid Process | I73: Customer has submitted pricing for final review. Customer requested a rendering to present their report/request to go modular to the board. Modular design was not the preferred construction method. | J73: MISC | Y73: OCFA | Z73: MISC
B74: LAUSD - Charter School | C74: Jordan MS | D74: Joe | E74: 619211 | F74: (1) 48x40 MPR | G74: 4 | I74: The Board chose iMod Systems for their ability for future relocation and reconfigurable alternatives. | J74: MISC | K74: 45730 | Y74: LAUSD - Charter School | Z74: MISC
B75: GMH Builders | C75: Sonoma Mountain ECS | D75: Joe | F75: (2) 24x40 Classroom Bldgs | G75: 4 | I75: GMH was not selected for the LLB | J75: MISC | K75: No | Y75: GMH Builders | Z75: MISC
B76: Hensel Phelps | C76: West Valley Community College | D76: Joe | F76: (3) 12x40 Toilet Buildings (5) 24x40 Locker Room Buildings (1) 36x40 Training Room Building | G76: 16 | I76: 3 year lease bid for locker room and toilet buildings | K76: No | Y76: Hensel Phelps
B77: Benicia USD | C77: Benicia HS | D77: Joe | F77: (1) 12X40 Restroom/Storage/Snack Bar | G77: 1 | I77: District went with AMS | J77: Price | K77: No | Y77: Benicia USD | Z77: Price
B78: Mobile Modular | C78: FOB | D78: Joe | E78: 463131 | F78: (4) 24x40 HCD Classroom Buildings | G78: 8 | H78: 45901 | I78: Lost to Class Leasing | J78: price | K78: 45782 | L78: AMS | Y78: Mobile Modular | Z78: price
B79: Sweetwater Lease | D79: Diana | F79: (50) CR's and RR - various bldg. configurations | I79: SCM pricing was too high. | J79: price | K79: No | Y79: Sweetwater Lease | Z79: price
B80: Visalia USD | C80: Valley Oak MS | D80: Joe | F80: (1) 67x36 Classroom Building | G80: 5 | H80: 46113 | I80: No bid, Slab on Grade. | J80: Technical | K80: No | Y80: Visalia USD | Z80: Technical
B81: Jurupa Valley USD | C81: Jurupa MS | D81: Sandra | E81: 302389 | F81: (1) 48x40 | G81: 4 | H81: 45931 | I81: Customer went with AMS because they were able to receive plans in two weeks vs the time frame we provided | J81: Schedule | K81: Yes | Y81: Jurupa Valley USD | Z81: Schedule
B82: US Army Corps of Engineers | C82: USACE Santa Ana Dam Resident Office Complex | D82: Sandra | F82: (1) 36x60 Office HCD | G82: 3 | H82: TBD | I82: Proceeded with a leased bldg | J82: misc | Y82: US Army Corps of Engineers | Z82: misc
B83: Paul Morrissey | C83: La Sierra University | D83: Sandra | F83: Went with a lease bldg | I83: Went with a leased building | J83: misc | Y83: Paul Morrissey | Z83: misc
B84: Oceanside USD | C84: Multiple Sites | D84: Sandra | F84: 30x32 CR, 24x40 CR and Restroom Buildings | G84: 17 | I84: Lost due to Price | J84: price | Y84: Oceanside USD | Z84: price
B85: Palisades USD | C85: Multiple Sites | D85: Sandra | F85: (11) 24x40 CR, (11) 36x40 and (4) TB | G85: 59 | H85: TBD | I85: Ended up Leasing the buildings | J85: misc | Y85: Palisades USD | Z85: misc
B86: William Scotsman | C86: Bakersfield City USD | D86: Diana | E86: 124123.35 | F86: (1) 30'x32' Classroom building | G86: 3 | H86: 45992 | I86: Customer decided to replace the burned unit with an existing unit that the district already owned. | J86: MISC | K86: 45749 | Y86: William Scotsman | Z86: MISC
B87: McKinleyville USD | C87: Prairie ES | D87: Joe | E87: 4502174 | F87: (3) 72x40 TK | G87: 18 | I87: Lost to AMS $3,381,200 (delta is $1,120,974) | J87: Price | L87: AMS | P87: 3381200 | R87: 4502174 | S87: =(R87-P87)/P87 -> 0.33153141 | Y87: McKinleyville USD | Z87: Price
B88: ICEF Inglewood | C88: Ingelwood | D88: Sandra | E88: 13178400 | F88: 2 Story Modular Classroom Bldg | I88: Went away due to school funding/property issues. Ryan said it may come back but not until ne | J88: Funding | Y88: ICEF Inglewood | Z88: Funding
B89: Ventura USD | C89: Loma Vista ES | D89: Joe | F89: (1) 30x32 CR | G89: 3 | H89: 45870 | I89: District hired Levi to modernize their existing building instead of buying a new one. | J89: Misc | Y89: Ventura USD | Z89: Misc
B90: South Fork USD | C90: South Fork ES | D90: Joe | E90: 1123134.6 | F90: (1) 100x32 Classroom / Office / Toilet Building | G90: 10 | H90: 45992 | I90: 1) NextMod $971,769 ($303/SF) ($151K) 2) Global $1,028,000 ($321/SF) ($95K) 3) SCM $1,123,134 ($350/SF) Nonresponsive AMS & JTS | J90: Price | K90: Bid | L90: Next Mod | Y90: South Fork USD | Z90: Price
B91: Marysville JUSD | C91: Dobbins ES | D91: Joe | E91: 240181 | F91: (1) 30x32 Classroom | G91: 3 | H91: 45992 | I91: 1) Class Leasing $188K (- $38/SF) 2) Mobile Modular $202K (- $23/SF) 3) SCM $240K 4) Global $318K (+ $98/SF) | J91: Price | K91: 45790 | L91: Class Leasing | N91: 188000 | O91: 202000 | Q91: 318000 | R91: 240000 | Y91: Marysville JUSD | Z91: Price
B92: Sylvan USD | C92: District Office | D92: Joe | E92: 2028742 | F92: (1) 72X40 Office Bldg (1) 72X40 Training Room Bldg | G92: 12 | I92: District will lease buildings | J92: MISC | Y92: Sylvan USD | Z92: MISC
B93: San Marcos USD | C93: WoodlandPark MS | D93: Joe | E93: 514400 | F93: (8) 24x40 classroom buildings | G93: 16 | H93: 45931 | I93: SCM not the lowest responsible bid | J93: Price | Y93: San Marcos USD | Z93: Price
B94: Fullerton SD - | C94: Raymond ES | D94: Sandra | E94: 783641.04 | F94: (3) 12x40 TB | G94: 3 | I94: 8.7.2025 Awarded to Class Leasing $7,000 less per building | J94: Price | L94: Class Leasing | Y94: Fullerton SD - | Z94: Price
B95: Bear Valley | C95: Northshore ES | D95: Sandra | E95: 276319.99 | F95: (1) 36x40 | G95: 3 | I95: Awarded to SCK- Upon speaking to Customer Architect said he was able to receive a proposal from our competitor very quickly while ours took over a week and half | J95: Price | L95: SCK | Y95: Bear Valley | Z95: Price
B96: Fullerton SD | C96: Raymond ES | D96: Sandra | E96: 645921.6 | F96: (1) 48x40 and (2) 24x40 Classroom Bldgs | G96: 8 | I96: 8.7.2025 Awarded to Class Leasing due to pricing $22,00 less | J96: Price | L96: Class Leasing | Y96: Fullerton SD | Z96: Price
B97: Palmdale SD | C97: Various | D97: Sandra | F97: Multiple Sizes | I97: Lost Bid 8/6/25 AMS 1.06 and SCM 1.68 | J97: Price | L97: AMS | P97: 1.06 | R97: 1.68 | S97: =(R97-P97)/P97 -> 0.58490566 | Y97: Palmdale SD | Z97: Price
B98: Helendale SD | D98: Sandra | F98: (1) 48'X40' Open Classroom | G98: 4 | I98: 8.7.205 Awarded to Class Leasing | J98: Price | L98: Class Leasing | Y98: Helendale SD | Z98: Price
B99: Magnolia SD | C99: Peter Marshall ES | D99: Diana | E99: 1489729.6 | F99: 150x32 Classroom Pod | G99: 15 | H99: 46023 | I99: The customer has shared that SCM was higher than the next lowest quote and that if anything changes he will reach out to Adela. | J99: Price | Y99: Magnolia SD | Z99: Price
V113: Customer Name | W113: Project Name | X113: Contract Value | Y113: AMS | Z113: SCM | AA113: Var% to AMS
V114: Ballico-Cressey SD | W114: Cressey ES | X114: 3052557.5 | Y114: 2748000 | Z114: 3052557 | AA114: 0.1108286
...

Sheet Sales Summary Report
B2: Revenue by Quarter | C2: 153459650 | D2: 129681327 | H2: Project by Highest Contract Value
B3: Row Labels | C3: Sum of Contract | D3: Sum of Estimated Value | E3: # of Projects | F3: Sum of Floor(s) | H3: Contract Value | I3: Project Name | J3: PM
B4: 1 | C4: 41948855 | D4: 30764797 | E4: 31 | F4: 298 | H4: 12835820 | I4: Mare Island Technology Academy | J4: Lori
B5: 2 | C5: 32932478 | D5: 32852017 | E5: 34 | F5: 225 | H5: 11797264 | I5: Surfside | J5: Kenny
B6: 3 | C6: 41001710 | D6: 40791530 | E6: 11 | F6: 185 | H6: 8000000 | I6: Marshall ES | J6: (blank)
B7: 4 | C7: 36278842 | D7: 26470050 | E7: 27 | F7: 229 | H7: 5766106.2 | I7: Parkview School TK-8 | J7: Moanes
B8: TBD | C8: 3931270.7 | D8: 272710 | E8: 15 | F8: 62 | H8: 5697280 | I8: Health Center | J8: (blank)
B9: (blank) | C9: 73369068 | D9: 17208899 | E9: 80 | F9: 506 | H9: 5159577.8 | I9: Jefferson MS | J9: Kenny
B10: Grand Total | C10: 2.2946222e+08 | D10: 1.4836e+08 | E10: 198 | F10: 1505 | H10: 4494585.5 | I10: Monterey Vista ES | J10: (blank)
B11: Revenue by BDM | H11: 3153674.9 | I11: Arcadia HS | J11: (blank)
B12: Row Labels | C12: Sum of Estimated Value | H12: 3006336.8 | I12: Vineland ES | J12: Lori
B13: Diana | C13: 27942871 | H13: 2970266.2 | I13: Wasco HS | J13: Lori
B14: Diana/Quinton | C14: 125464.19 | H14: 2885231.4 | I14: Oak Meadows ES | J14: (blank)
B15: Joe | C15: 31855842 | H15: 2816398 | I15: Harding ES | J15: Kenny
B16: Quinton/Diana | C16: 249912.61 | H16: 2740000 | I16: Hans Christensen ES | J16: Kenny
B17: Sandra | C17: 89882583 | H17: 2532016.4 | I17: Rancho Starbuck Intermediate | J17: Moanes
B18: (blank) | C18: 0 | H18: 2467455.7 | I18: Freedom Crest ES | J18: (blank)
B19: Grand Total | C19: 1.5005667e+08 | H19: 2448024.2 | I19: Torrance ES | J19: Moanes
H20: 2392640.9 | I20: Carr ES | J20: Moanes
B21: Pipeline Distribution by PM | H21: 2137747.9 | I21: Callie Kirkpatrick ES | J21: (blank)
B22: Row Labels | C22: Sum of Estimated Value | D22: # of Projects | H22: 2123331.7 | I22: New Phelan ES | J22: (blank)
B23: Gino | C23: 21511074 | D23: 36 | H23: 2105834.8 | I23: Cerritos Community College | J23: (blank)
B24: Kenny | C24: 26412531 | D24: 10 | H24: 2028742 | I24: District Office | J24: (blank)
B25: Lori | C25: 21042883 | D25: 8 | H25: 2000000 | I25: Calistoga ES | J25: (blank)
B26: Mehdi | C26: 20036800 | D26: 1 | H26: 1998719.7 | I26: Oak St. Prep K | J26: Moanes
B27: Moanes | C27: 25083318 | D27: 25 | H27: 1927490 | I27: Helendale ES | J27: (blank)
B28: TBD | C28: 417361.4 | D28: 2 | H28: 1870996.9 | I28: New Phelan ES | J28: (blank)
B29: (blank) | C29: 35552706 | D29: 86 | H29: 1852667.4 | I29: Arcadia HS | J29: (blank)
B30: Grand Total | C30: 1.5005667e+08 | D30: 168 | H30: 1848439.6 | I30: Fremont ES - iHigh Virtual Academy | J30: Kenny
H31: 1801375 | I31: El Portal ES | J31: Moanes
H32: 1573755 | I32: Only Love Children's Center #4 | J32: (blank)
H33: 1565922.8 | I33: Colton | J33: Gino
H34: 1444491.4 | I34: Sandia Academy | J34: Gino
I35: Yucca Loma ES | J35: Gino
B36: Detailed Job by Quarter | H36: 1420634.9 | I36: Beaumont Adult School | J36: Gino
B37: Quarter | C37: Project Name | D37: Sum of Contract | E37: Sum of Estimated Value | F37: Sum of Floor(s) | H37: 1414508.7 | I37: Quail Valley ES | J37: (blank)
B38: 1 | C38: Health Center | D38: 5697280 | E38: 4272960 | F38: 24 | H38: 1387218.6 | I38: Peter Marshall ES | J38: Moanes
C39: Arcadia HS | D39: 5006342.3 | E39: 2503171.1 | F39: 21 | H39: 1381085.5 | I39: Various Sites | J39: Kenny
C40: Beaumont Adult School | D40: 1420634.9 | E40: 1420634.9 | F40: 12 | H40: 1304554.6 | I40: Farragut ES | J40: (blank)
C41: Beyer HS | D41: 246171.81 | E41: 246171.81 | F41: 1 | H41: 1240813.2 | I41: New Phelan ES | J41: (blank)
C42: Claremont HS | D42: 191440 | E42: 191440 | F42: 2 | H42: 1196120 | I42: Veterans ES | J42: Lori
C43: Colton | D43: 1565922.8 | E43: 1565922.8 | F43: 6 | H43: 1093635 | I43: Maple Hills ES | J43: Moanes
C44: East LA College Shop Bldg | D44: 888608.67 | E44: 177721.73 | F44: 8 | H44: 1000000 | I44: Lucerne ES | J44: (blank)
C45: ELAC South Gate | D45: 473556.18 | E45: 94711.236 | F45: 2 | H45: 998332 | I45: Harada ES | J45: Gino
C46: Emerson ES | D46: 244043 | E46: 244043 | F46: 2 | H46: 993401 | I46: Williams ES | J46: Moanes
C47: Farragut ES | D47: 1304554.6 | E47: 195683.18 | F47: 8 | H47: 975443.22 | I47: Los Amigos ES | J47: (blank)
C48: Fire Academy | D48: 227900.33 | E48: 227900.33 | F48: 2 | H48: 888608.67 | I48: East LA College Shop Bldg | J48: (blank)
C49: Hans Christensen ES | D49: 2740000 | E49: 2740000 | F49: 15 | H49: 875686 | I49: Janson ES | J49: (blank)
C50: Harada ES | D50: 998332 | E50: 998332 | F50: 9 | H50: 865637.29 | I50: Olivelands ES | J50: Lori
... C53: Jefferson ES | D53: 792600 | E53: 792600 | F53: 12 | H53: 817329 | I53: Hollyvale | J53: Gino
C54: Joshua Circle ES | D54: 280655 | E54: 280655 | F54: 4 | I54: Joshua Circle | J54: Gino
C55: Juniper ES | D55: 280655 | E55: 280655 | F55: 4 | I55: Mesa Grande ES | J55: Gino
C56: Kennedy ES | D56: 728293 | E56: 728293 | F56: 4 | H56: 793546.71 | I56: Savannah ES | J56: (blank)
C57: Lincoln Elementary | D57: 112000 | E57: 112000 | F57: 1 | H57: 792600 | I57: Jefferson ES | J57: Gino
C58: Meridian ES | D58: 199336 | E58: 199336 | F58: 1 | H58: 787663.96 | I58: Mt. SAC | J58: (blank)
C59: Mesa Grande | D59: 623161 | E59: 623161 | F59: 5 | H59: 758144.44 | I59: Mt. SAC | J59: (blank)
C60: Mesa Grande ES | D60: 817329 | E60: 817329 | F60: 6 | H60: 757775.58 | I60: Summerwind Trails School | J60: Gino
C61: New Phelan ES | D61: 5235141.8 | E61: 1308785.4 | F61: 56 | I61: Mountain View MS | J61: (blank)
C62: Newland ES | D62: 138298.63 | E62: 138298.63 | F62: 2 | H62: 743756.62 | I62: Mt. SAC | J62: (blank)
C63: Oka ES | D63: 262487.93 | E63: 262487.93 | F63: 4 | H63: 733915.11 | I63: Mt. SAC | J63: (blank)
C64: Pasadera Early Childhood Education Center | D64: 1641711.3 | E64: 1641711.3 | F64: 7 | H64: 728293 | I64: Kennedy ES | J64: Kenny
C65: Pearblossom ES | D65: 431353 | E65: 431353 | F65: 6 | H65: 713569.32 | I65: Cabot Yerxa ES | J65: Gino
C66: Peter Marshall ES | D66: 1387218.6 | E66: 1387218.6 | F66: 15 | H66: 680121 | I66: Bella Vista ES | J66: Gino
C67: Plavan ES | D67: 260370.01 | E67: 260370.01 | F67: 4 | I67: Cahuilla ES | J67: Gino
C68: Quail Valley ES | D68: 1414508.7 | E68: 282901.74 | F68: 12 | I68: Cathedral City ES | J68: Gino
C69: Sandia Academy | D69: 1444491.4 | E69: 1444491.4 | F69: 12 | H69: 680000 | I69: Rio Vista ES | J69: Gino
C70: Temescal ES | D70: 332944 | E70: 332944 | F70: 3 | H70: 663910.13 | I70: Juniper | J70: Gino
C71: Torrance ES | D71: 2448024.2 | E71: 2448024.2 | F71: 14 | H71: 660578.04 | I71: Meadows Arts & Technology ES | J71: (blank)
C72: Various Sites | D72: 1381085.5 | E72: 1381085.5 | F72: 17 | H72: 659821.97 | I72: Alhambra HS | J72: (blank)
C73: Vineland ES | D73: 3006336.8 | E73: 3006336.8 | F73: 21 | H73: 642710.45 | I73: Adelanto HS | J73: (blank)
C74: Yucca Loma ES | D74: 1444491.4 | E74: 1444491.4 | F74: 12 | H74: 627320.93 | I74: LAWP | J74: (blank)
B75: 1 Total | D75: 48904658 | E75: 37720601 | F75: 358 | H75: 623161 | I75: Mesa Grande | J75: Gino
B76: 2 | C76: ACE/RMS | D76: 479820.52 | E76: 479820.52 | F76: 4 | H76: 614235.61 | I76: San Gorgonio MS | J76: Gino
C77: Anderson ES | D77: 320692 | E77: 320692 | F77: 4 | H77: 603711.04 | I77: Walnut Valley Collegewood ES | J77: Moanes
C78: Bella Vista ES | D78: 680121 | E78: 680121 | F78: 7 | H78: 602407.01 | I78: John H. Hiemes ES | J78: (blank)
C79: Beverly Hills HS | D79: 263148.49 | E79: 263148.49 | F79: 1 | H79: 581379.31 | I79: Covina HS | J79: Moanes
C80: Cabot Yerxa ES | D80: 713569.32 | E80: 713569.32 | F80: 6 | H80: 480954.99 | I80: Katherine Finch ES | J80: Gino
C81: Cathedral City ES | D81: 680121 | E81: 680121 | F81: 7 | H81: 479846.47 | I81: Nuview Elementary | J81: Gino
C82: Covina HS | D82: 581379.31 | E82: 581379.31 | F82: 2 | H82: 479820.52 | I82: ACE/RMS | J82: Gino
C83: Geoge Lucas Park Restroom | E83: 0 | F83: 1 | H83: 473556.18 | I83: ELAC South Gate | J83: (blank)
C84: Hans Christensen ES | D84: 244569.11 | E84: 244569.11 | F84: 1 | H84: 463190.78 | I84: East Hills Academy | J84: Kenny
C85: Hutchison MS | D85: 2244195.3 | E85: 2244195.3 | F85: 6 | H85: 432627 | I85: Alpine ES | J85: (blank)
C86: Imperial ES | D86: 221547 | E86: 221547 | F86: 3 | I86: Antelope ES | J86: (blank)
C87: Julius Corsini ES | D87: 193345.99 | E87: 193345.99 | F87: 1 | I87: Daisy Gibson ES | J87: (blank)
C88: Jurupa MS | D88: 302389 | E88: 287269.55 | F88: 4 | I88: Lake Los Angeles ES | J88: (blank)
C89: Katherine Finch ES | D89: 480954.99 | E89: 480954.99 | F89: 4 | H89: 420981.5 | I89: Hollyvale ES | J89: Gino
C90: Laurel ES | D90: 157449.02 | E90: 157449.02 | F90: 1 | H90: 408151 | I90: Silver Valley Health Center | J90: Gino
C91: Monte Vista ES | D91: 847260.19 | E91: 847260.19 | F91: 9 | H91: 373723.44 | I91: ATLAS School | J91: (blank)
C92: Nuview Elementary | D92: 479846.47 | E92: 479846.47 | F92: 5 | I92: Portola ES | J92: (blank)
C93: Ocean View ES | D93: 157449.02 | E93: 157449.02 | F93: 1 | H93: 332944 | I93: Temescal ES | J93: Gino
C94: Olive Drive ES | D94: 847983.87 | E94: 847983.87 | F94: 6 | H94: 320692 | I94: Anderson ES | J94: Moanes
C95: Olivelands ES | D95: 865637.29 | E95: 865637.29 | F95: 6 | H95: 318976 | I95: Only Love Children's Center #2 | J95: (blank)
C96: Orchard ES | D96: 157449.02 | E96: 157449.02 | F96: 1 | H96: 302389 | I96: Jurupa MS | J96: (blank)
C97: Rio Vista ES | D97: 680000 | E97: 680000 | F97: 7 | H97: 287144 | I97: Pearblossom ES | J97: TBD
C98: San Gorgonio MS | D98: 614235.61 | E98: 614235.61 | F98: 7 | H98: 280655 | I98: Joshua Circle ES | J98: Gino
C99: Silver Valley Health Center | D99: 408151 | E99: 408151 | F99: 3 | I99: Juniper ES | J99: Gino
C100: Summerwind Trails School | D100: 757775.58 | E100: 757775.58 | F100: 9 | H100: 276363.15 | I100: Boron HS | J100: (blank)
C101: Surfside | D101: 11797264 | E101: 11797264 | F101: 66 | H101: 263148.49 | I101: Beverly Hills HS | J101: Moanes
C102: Veterans ES | D102: 1196120 | E102: 1196120 | F102: 9 | H102: 262487.93 | I102: Oka ES | J102: Moanes
C103: Villa Park ES | D103: 221547 | E103: 221547 | F103: 3 | H103: 260434.8 | I103: Helendale ES | J103: TBD
...

Sheet Leads, pre-con
A1: Customer | B1: Project Name | C1: BDM | D1: Contract Value | E1: Building(s) | F1: Floor(s) | G1: Start Date for Production | H1: Confidence Level | I1: Current Status/Notes
A2: Asher University | B2: Asher University | C2: Sandra | E2: (2) 168X40 Classroom and Admin Office | F2: 56 | H2: 0.2 | I2: Customer aquired property working on funding. Still waiting on city to approve new roads to site
A3: Endovate Charter School | B3: Endovate Charter School | C3: Sandra | E3: (5) 36x20 Classroms and (1) 12x40TB | F3: 15 | H3: 0.25 | I3: Provided them information to submit for their board to review they are finalizing whether they will proceed with current floorplans or change.
A4: Hope Academy | C4: Sandra | E4: TK | F4: 12 | G4: 46235 | H4: 0.1 | I4: Followed up with customer and they are redesigning their site in hopes of saving some money
A5: Santa Moncia Malibu USD | B5: Middle School | C5: Sandra | E5: Two Story (2) 96’x40’ | F5: 1 | I5: Adela still meeting with customer to review
A6: LA Community College District | B6: ELAC South Gate | C6: Sandra | D6: 473556.18 | E6: 24x40 RR/Concession | F6: 2 | H6: 0.2 | I6: Waiting for funding
A7: LA Community College District | B7: East LA College Shop Bldg | C7: Sandra | D7: 888608.67 | E7: (4) 24x40 | F7: 8 | H7: 0.2 | I7: No Start Date/Waiting on Funding
A8: Savannah SD | B8: Cypress King ES | C8: Sandra | D8: =145075.18+190722.58+190573.12 -> 526370.88 | E8: (2)24’x40’ Office and (1) 12x40 | F8: 5 | G8: 46230 | H8: 0.2 | I8: Architect submitted Soils report for Ryans review. She would like him to design the foundation
A9: Chula Vista USD | B9: Fahari Jeffers | C9: Diana | F9: 108'x40' Two Story | K9: No update | U9: NOT RELEASED TO ENGINEERING
A10: Corcoran Police Station | C10: Diana | K10: 8.7.2025 Customer waiting for a proposal | L10: No | M10: Bid | N10: No | O10: No | P10: No | T10: =IFERROR(E10*J10,0) -> 0 | U10: NOT RELEASED TO ENGINEERING | V10: =IFERROR(ROUNDUP(MONTH(IF(H10<>"",H10,""))/3, 0),"TBD") -> TBD | W10: =IF(I10<>"",IF(W10="",NOW(),W10),"")

Sheet 2 Week Look-Ahead
A2: 2 WEEK LOOK-AHEAD
A5: WE | B5: JOB # | C5: PROJECT | D5: BUILDING | E5: WEEK OF JULY 7 | F5: WEEK OF JULY 14 | G5: DSA Date | H5: COMMENTS
A6: Diana Tavarez
A7: 1 | C7: Tehama Department of Education | D7: (1) 36'x40' | H7: No ETA. Waiting on revised floor plan
A8: 2 | C8: Redlands USD Model C-2 RR | D8: (1) 12'x40' Restroom | G8: 46196
A9: 3 | C9: Charles White Park | D9: (1) 64'x79' | H9: In progress
A10: 4 | C10: SDUSD Jerabek ES | D10: (4) 24'x40'classrooms, (1) 12'x40' Restroom | G10: 46178 | H10: AOR is reviewing our PC's and is to provide updates.
C11: Beaumont USD - (4) Sites | D11: 24'x40's and 32' RRs | G11: 46235
B12: Sandra Adame
A13: 5 | C13: Orange USD | D13: (2) 24x40 Classroom Bldgs with RR | H13: Wtg on PO
A14: 6 | C14: Oxnard SD-Freemont MS | D14: (2) 36x40 Lockerroom Buildings | H14: Ryan, Adela, and I met with customer.
A15: 7 | C15: ABC USD- Niemes ES | D15: 60x40 | H15: Proposal in review w/customer
B16: Frank Carrillo
A17: 8 | C17: Folsom Cordova USD - Granite Springs ES | D17: (1) 144x40, (1) 156x40 & (1) 48x40 | H17: Kickoff scheduled for Monday 5/18

Sheet Lost Deals
A1: Lost Code | B1: Customer Name | C1: Project Name | D1: BDM | E1: Contract Value | F1: Building(s) | G1: Floor Count | H1: Start Date | I1: Current Status/Notes | J1: Bid or Piggyback | K1: Estimated Project Completion | L1: Confidence Level | M1: Estimated Value
A2: Schedule | B2: Sierra Sands USD | C2: Murray MS | D2: Joe | F2: BUILDING C (1) 36X40 + (3) 30X32 BUILDING E (7) 30X32 | H2: 45658 | I2: Ryan to find out if we can meet bid due date | J2: Bid | K2: Summer 2025 | L2: 0.3 | M2: =E2*L2 -> 0
A3: Price | B3: Ballico-Cressey SD | C3: Cressey ES | D3: Joe | E3: 3052557.5 | F3: (2) 72x40 TK (1) 12x40 RR | G3: 13 | I3: AMS $2,748,000 Global $2,854,000 SCM $3,052,557 | J3: Bid | K3: Summer 2025 | L3: 0 | M3: =E3*L3 -> 0
A4: Price | B4: Victor Valley ESD | C4: Challenger ES | D4: Adela | E4: 382000 | F4: (1) 24x40 RR/Concession Bldg | I4: Timing, Pricing, Pass on location, Lost Funding, or went with Lease or Stick
A5: Price | B5: Victor Valley ESD | C5: Lomitas ES | D5: Adela | E5: $260.298.00 | F5: (1)24’x40 Restroom | I5: Over 80 deals we've looked at and didn't proceed with.
A6: Price | B6: Tsumiki Preschool | C6: Tsumiki Preschool | D6: Diana | E6: 390038.78 | F6: (1) 36'x60' | I6: Cost of a new building was too much for the customer's budget
A7: Schedule | B7: Simi Valley | C7: Hillside MS | D7: Diana | E7: 291416.77 | F7: (2) 24'x40' | G7: 4 | H7: 45366 | I7: Schedule too tight to meet.
A8: Funding | B8: La Mesa-Spring Valley | C8: Parkway Academy MS | D8: Diana | E8: 138449 | F8: (1) 24'x40' | G8: 4 | I8: Cost of a new building was too much for the customer's budget
A9: Funding | B9: Jefferson SD | C9: Corral Hollow ES | D9: Joe | E9: 2990052.7 | F9: BUILDING A (1) 36x40 TK BUILDING B (1) 108x40 TK BUILDING C (1) 36x40 TK BUILDING D (1) 108x40 PE CR | G9: 24 | I9: District does not have the funding to move forward per PJHM | J9: PB | K9: Summer 2025 | L9: 0 | M9: =E9*L9 -> 0
A10: Price | B10: Merced City SD | C10: Franklin ES | D10: Joe | E10: 6826236 | F10: WING A (1) 196X40 WING B (1) 160X40 | G10: 29 | H10: 45748 | I10: 1. AMS $5,948,000.00 ($878K below SCM) 2. Global $6,546,000.00 ($280K below SCM) 3. Silver Creek $6,826,236.00 | J10: Bid | K10: Fall 2025 | L10: 0 | M10: =E10*L10 -> 0
A11: Price | B11: Bishop USD | C11: MOT Yard | D11: Joe | E11: 878824.03 | F11: (1) 72X40 Office Bldg | G11: 6 | H11: TBD | I11: Our price is too high. District expoloring other options | J11: PB | K11: Summer 2025 | L11: 0 | M11: =E11*L11 -> 0
A12: Price | B12: Sylvan USD | C12: Somerset MS | D12: Joe | E12: 461894.85 | F12: (1) 60x40 Childcare | G12: 5 | H12: 45566 | I12: Lost deal to AMS $415,287.00 | J12: PB | K12: Summer 2025 | L12: 0 | M12: =E12*L12 -> 0
A13: Price | B13: Downey USD | C13: Downey USD | D13: Adela | F13: (13) TK Classrooms | I13: Pricing too high
A14: Price | B14: Hemet USD | C14: Hemet HS | D14: Adela-Sandra | E14: 570182.81 | F14: (4) 24x40 | G14: 8 | H14: TBD | I14: Lost to Competitor | J14: PB | K14: N/A | L14: 0.05
A15: Price | B15: Orange USD | D15: Adela-Sandra | E15: 257193 | F15: (2) 24X40 | G15: 4 | H15: TBD | I15: Lost to Competitor | J15: PB | K15: N/A | L15: 0.25
A16: Price | B16: Academy for Advancement of Children with Autism | C16: AACA | D16: Adela-Sandra | E16: 584811.41 | F16: 96x60 Classroom | G16: 8 | H16: TBD | I16: Lost to Competitor | J16: PB | K16: N/A | L16: 0.5
A17: Other | B17: South San Francisco USD | C17: Los Cerritos ES | D17: Joe | E17: 157240.21 | F17: (1) 12x40 RR | G17: 1 | H17: 45597 | I17: Project will go out to bid. | K17: PB | L17: No
A18: Other | B18: ASYMCA | C18: ASYMCA | D18: Diana | E18: 1915724.6 | F18: (2) 60'x60 CR Bldgs. | G18: 12 | H18: 45580 | I18: Customer had concerns with SCM's pricing after all the finishes were upgraded. They moved on and procure the buildings from Phoenix Modular. | K18: Negotiated
B19: San Jacinto USD | C19: Facilities & Operations | D19: Adela-Sandra | E19: 2884615 | F19: (1) 144'x48' | G19: 12 | H19: 45778 | I19: On hold | J19: PB | K19: TBD | L19: =E19*A19 -> 0
A20: Price | B20: Blok Modular | C20: Las Palmas | D20: Diana | E20: 1004331.7 | F20: (1) 12'x40', (1) 12'x24', (1) 12'x50', (1) 12'x40' RR Bldgs. | G20: 5 | H20: TBD | I20: SCM pricing was 30% higher than our competitors, per Blok's owner.
A21: Price | B21: Fall River JUSD | C21: Fall River ES | D21: Joe | E21: 1452611.5 | F21: (4) 24x40 2:12 PC Classrooms | G21: =4*2 -> 8 | H21: 45658 | I21: 8/20 Per Steve, proceed with estimating 8/21 submitted to estimating SCM to outsource delivery, installation and service to DVMB. Our pricing is three times the District's budget. | J21: PB | K21: 45838 | L21: =E21*A21 -> #VALUE!
A22: Price | B22: Marysville JUSD | C22: Arboga ES | D22: Joe | E22: 260240.33 | F22: (1) 40X32 | G22: 4 | H22: 45627 | I22: Lost to Mobile Modular $209,597 | J22: Bid | K22: End 2024 | L22: =E22*A22 -> #VALUE!
A23: Price | B23: Cajon Valley USD | C23: Johnson ES | D23: Diana | E23: 132747 | F23: (1) 24'x40' Classroom | G23: 2 | H23: 45778 | I23: Lost deal to AMS per the district we were higher. SCM provided a list of why our buidlings are more expensive than AMS. | J23: PB | K23: Summer 2025
A24: Price | B24: Cajon Valley USD | C24: Avocado ES | D24: Diana | E24: 414860 | F24: (3) 30'X32' Classrooms | G24: 9 | H24: 45778 | I24: Lost deal to AMS per the district we were higher. SCM provided a list of why our buidlings are more expensive than AMS. | J24: PB | K24: Summer 2025
A25: Price | B25: Waterford USD | C25: Moon PS | D25: Joe | E25: 5166484 | F25: (2) 144x40 TK Bldgs | G25: 24 | H25: 46113 | I25: Low Bidder: Global $4,440,000 $385/SF ($726,484) AMS $4,498,000 $390/SF ($668,484) SCM $5,166,484 $448/SF | J25: Bid | K25: Summer 2026 | L25: =E25*A25 -> #VALUE! | M25: TBD
A26: Other | B26: Arcadia USD | E26: No BOM | F26: (10) 24x40 | G26: 20 | H26: 45809 | I26: Only showing ISS for Crs, no BOM for CR buildings | M26: TBD
A27: Other | B27: San Rafael City Schools | C27: Terra Linda HS | D27: Adela-Sandra | E27: =504039.5+140715.02 -> 644754.52 | F27: 24x40 Concession/RR 8-6x21-6 Storage/Ticket | G27: 3 | H27: TBD | I27: Customer was notified that SCM could not proceed with project if they required us to meet project bid manual | J27: GC | K27: Summer 2024 | L27: =E27*A27 -> #VALUE!
A28: Price | B28: PMSI - Michael Thompson | C28: 36'x48' | D28: Diana | E28: 206387.63 | F28: 36'x48' HCD building | G28: 3 | H28: TBD | I28: Lost deal due to pricing.
A29: Price | B29: Cal State Long Beach | C29: Cal State Long Beach | D29: Sandra | E29: No BOM | F29: (1) 12x40 TB | G29: 1 | I29: Customer has decided to lease bldg
A30: Other | B30: Irvine Community College | C30: Irvine Community College | D30: Sandra | E30: No BOM | F30: (1) 48x40 Locker Room | G30: 4 | H30: TBD | I30: Bought a used building
A31: Price | B31: LAUSD- Irving Steam Magnet | D31: Adela-Sandra | E31: 0 | F31: 72x40 | G31: 6 | H31: 45748 | I31: Provided Quote 10/14/24
A32: Other | B32: Hueneme ESD | C32: Larsen ES & Hollywood ES | D32: Diana | E32: 0 | F32: (6) 72'x40' TK Buildings | G32: 36 | H32: 45748 | I32: SCM agreed to not bid. Bid Results are as follows: Class Leasing $2,434,693.00 ($140.896) , NextMod $2,736,417.84 ($158.3575), Global Modular $3,398,500.00 ($196.672) SF. total: 17,280
A33: Price | B33: Blok Modular | C33: Fort Irwin | D33: Diana | E33: 111382 | F33: (1) 12'x24' DOH | G33: 1 | H33: TBD | I33: SCM pricing was too high
A34: Price | B34: SDUSD | C34: Hardy ES | D34: Diana | E34: 1900832 | F34: (4) 36'x40 CRs w/ RRs, (6) 24'x40' Open CRs, (1) 12'x40' RR | G34: 25 | H34: 2026 | I34: SCM pricing was too high | J34: 2026 | K34: N/A
A35: Schedule | B35: Cypress College | D35: Sandra | E35: 365832.45 | F35: 24x40 Bldg | G35: 2 | H35: TBD | I35: Lost due to timeline
A36: Other | B36: Unified Modular | C36: Montebello USD | D36: Diana | E36: 241705 | F36: (1) 24'X40' CR | G36: 2 | H36: N/A | I36: Customer submitted proposal pending board approval. Project not awarded to our customer
A37: Other | B37: San Mateo County Community College District | C37: Cañada College | D37: Joe | E37: 5000000 | F37: (1) 107X37 Building A (1) 120x37 Building B | G37: =8+9 -> 17 | H37: 45839 | I37: No bid per Dennis and Ryan. Unable to provide a Cross Laminated Mass Timer (CLT) modular building per bid specs. | J37: 46023 | K37: Bid
A38: Price | B38: Bush Construction | C38: Firebaugh-Las Deltas USD Bailey PS | D38: Joe | E38: 6388910.2 | F38: (1) 24x40 Office Building (7) 72x40 TK | G38: 44 | H38: 45901 | I38: Class Leasing - 1st place $5.7M $287/SF 145/145 Best Value Scoring SCM - 2nd place $6.3M $370/SF 109/145 Best Value Scoring Enviroplex - 3rd place $8.8M $438/SF 82/145 Best Value Scoring | J38: Fall 2026 | K38: 45600 | L38: TBD
A39: Price | B39: DV Modular | C39: DV Modular | D39: Diana | E39: 293614 | F39: (1) 24'x60' Open Building | G39: 2 | I39: SCM pricing was too high compared to SF pricing dealer had submitted to their customer
A40: Other | B40: Fairfax SD | C40: District Office | D40: Joe | E40: 7000000 | F40: (1) 200X60 Admin Bldg | G40: 30 | H40: 46023 | I40: no bid, building not modular friendly. 27' high | J40: Winter 2025 | K40: No | L40: TBD
A41: Other | B41: Jurupa Valley USD | C41: Jurupa MS | D41: Sandra | E41: 0 | F41: (1) 48x40 | G41: 4 | I41: Provided revised proposal on a wide open 48x40. Architect reviewing with customer. | J41: Summer 2025 | K41: Yes | L41: TBD
A42: Other | B42: Lathrop Construction | C42: Foothill HS | D42: Joe | E42: 5000000 | F42: (1) 158x50 Weight/Fitness Building | G42: TBD | H42: 46023 | I42: Lathrop did not get the project. | J42: Summer 2026 | K42: No
A43: Price | B43: Montebello USD | C43: Ford Adult School | D43: Diana | E43: N/A | F43: 10ea. 24’x40’ Classrooms 1ea. 24’x40’ RR Building 1ea. 24’x40’ Career Center Bldg. 1ea. 48’x40’ Admin Bldg. 1ea. 48’x40’ Enrollment Bldg. 1ea. 96’x40’ MPR Building | G43: 40 | H43: 45748 | I43: Global Modular - 1st place $6,451,000 - Awarded to Lowest Bidder Silver Creek - $7,306,383 Next Mod was disqualified from bidding however their bid amount was $6,193,000. | J43: June 2025 (Per current bid docs) | K43: N/A
A44: Other | B44: Golden Plains USD | C44: Tranquility HS | D44: Joe | F44: (1) 48x40 Concession Building (1) 12x40 Breezeway (1) 72x40 PE Classroom Building | G44: =4+1+6 -> 11 | H44: 45873 | I44: No bid | J44: 46118 | K44: No
A45: Price | B45: Alhambra USD | C45: Ramona ES | D45: Sandra | E45: 319344.66 | F45: (1) 48x40 Serving Room | G45: 4 | H45: 45748 | I45: went to Next Mod because of price and drawing time
A46: Other | B46: Arc Construction | D46: Sandra | I46: Project required price for Slab on Grade Bldg
A47: Schedule | B47: City of Los Angeles Department of Public Works | C47: Slauson Connect Recreation Center | D47: Diana | E47: No BOM | F47: (1) 8,740 Sq Ft Two Story | I47: Lost deal due to timing. Pricing window was too short. | J47: Completion 2026
A48: No Response | B48: Los Angeles Community College District | D48: Sandra | F48: 5 offices, restrooms, ADA Ramp, Stairs, Conference room and breakroom | I48: Reached out to customer twice via call and email still awaiting response - Non Responsive
A49: Canceled Job | B49: Huntington Beach | C49: Marina HS | D49: Sandra | E49: 1712677.8 | F49: (8) 24x40 | G49: 16 | H49: 45748 | I49: Project has been canceled working on any costs that we have on the project | J49: Summer 2025 | L49: TBD
A50: Price | B50: Hemet USD | C50: Dartmouth-ELOP | D50: Sandra | E50: 1318085 | F50: (1) 204x40 | G50: 17 | I50: AMS provided lower cost
A51: Price | B51: Hemet USD | C51: ELOP | D51: Sandra | E51: 2426901.9 | F51: (2) 84x40 and (2) 60x40 | G51: 24 | I51: AMS provided lower cost
A52: Other | B52: Del Mar Union | C52: Carmel Del Mar ES | D52: Diana | E52: 370756.69 | F52: (1) 48'x40' (2) CR Bldg. | G52: 4 | H52: 45839 | I52: The district is not replacing their old portables as part of the ongoing modernization | J52: Summer 2025 | K52: Yes
A53: Other | B53: Del Mar Union | C53: Del Mar Hills Academy | D53: Diana | E53: 347067.59 | F53: (1) 48'x40' (2) CR Bldg. | G53: 4 | H53: 45992 | I53: The district is not replacing their old portables as part of the ongoing modernization | J53: 45992 | K53: Yes
A54: Other | B54: Mobile Modular | C54: FOB - Garfield HS Science Classroom | D54: Joe | E54: 361412.11 | F54: (1) 36x40 Science Classroom | G54: 3 | H54: Winter 2025 | I54: Mobile Modular to go with their used inventory for this project ILO brand new | J54: Negotiated | K54: Winter 2025
A55: Price | B55: Palmdale SD | C55: Palmdale Academy Charter School | D55: Joe | F55: (1) 204x96 Two Story | I55: ROM pricing in august/sept to AOR. Site Build over budget, switching to modular. | M55: 0
A56: Other | C56: (PACS) | I56: Project dead per Adel
A57: Site Build | B57: City of Shafter | C57: Aquatic Center | D57: Joe | E57: 8310122 | F57: (1) 125x25 Aquatic Center | G57: 10 | I57: The client has decided to stick build with slab on grade. | J57: No | K57: No | L57: No | M57: 0
A58: Price | B58: Indoff | C58: Lake Tahoe Community College | D58: Joe | E58: No BOM | F58: (3) 36x60 Training Facility | G58: 9 | I58: Competitor pricing at $130/SF. SCM is at $325-$425/SF. | J58: No | K58: No | L58: No | M58: 0
B59: Lancaster SD | C59: Sunnydale ES | D59: Joe | E59: No BOM | F59: (1) SCIENCE LAB | H59: 46023 | I59: We were not prequalified with PQbids due to missing 2 years of audited financials | J59: No | K59: No | L59: No | M59: 0
F60: (1) MUSIC BUILDING
A61: Other | F61: (3) CLASSROOM BUILIDNGS
A62: Other | B62: Island Union ESD | C62: Island Union ES | D62: Joe | E62: 993525 | F62: (2) 36x40 UPK Buildings | G62: 6 | I62: No bid due to addendum 3 requirement of 3.5:12 roof pitch | J62: No | K62: No | L62: No | M62: 0
B63: Calistoga JUSD | C63: Calistoga ES | D63: Joe | E63: 2000000 | F63: (4) TK Classrooms | G63: TBD | I63: LLB. Partner up with GC for Best Value. | J63: No | K63: No | L63: No | M63: 0
I64: 9/27 Landmark earned Best Value by earning the most points, 317
A65: Price | B65: PMSI Ewles Materials 12x56 | C65: PMSI Ewles Materials 12x56 | D65: Diana/Quinton | E65: 126603 | F65: (1) 12'x56' with axels | G65: 1 | I65: SCM pricing was too high | M65: 0
B66: Reef-Sunset USD | C66: Tamarack ES | D66: Joe | E66: 3843937 | F66: (2) 72X40 CLASSROOM BLDGS | G66: 30 | H66: 46266 | I66: ENVIROPLEX $203.39/SF | J66: No | K66: 45695 | L66: No | M66: 0
A67: Price | F67: (2) 96X40 CLASSROOM BLDGS | I67: SCM $249.77/SF
F68: (2) 12x40 RESTROOM BLDGS
B69: Selma USD | C69: Jackson ES | D69: Joe | E69: 978862 | F69: (1) 72x40 TK | G69: 6 | I69: 1) Enviroplex $892,570 ($310/SF) | J69: No | K69: No | L69: No | M69: 0
I70: 2) SCM $978,682 ($340/SF)
I71: 3) AMS $1,040,000 ($361/SF)
I72: 4) Global $1,094, 837 ($380/SF)
A73: Price | I73: 5) NextMod $1,226,880 ($426/SF)
A74: Other | B74: Unified Modular | C74: Classroom Buildings | D74: Diana | E74: In estimating | F74: (1) 24'x40' w/ single user RR and (1) 36'x40' w/ single user RR | G74: 5 | H74: TBD | I74: Customer did not need the new units after all | J74: No
A75: Other | B75: Pacific Mobile | C75: Multi-Story Housing Units | D75: Joe | I75: Per Steve, No
A76: Other | B76: Cumming Group | C76: Primo Facchini | D76: Joe | F76: ADA portable restrooms | I76: They're looking for porta potties, not modular restroom buildings.
A77: Other | B77: Orange USD | C77: Imperial ES | D77: Sandra | E77: 221547 | F77: (1) 36x40 Classroom | G77: 3 | H77: 45901 | I77: Due to time restraints the customer has elected to refurbish some of their existing units | J77: LOI | M77: 0
A78: Other | B78: Orange USD | C78: Villa Park ES | D78: Sandra | E78: 221547 | F78: (1) 36x40 Classroom | G78: 3 | H78: 45901 | I78: Due to time restraints the customer has elected to refurbish some of their exsisting units | J78: LOI | M78: 0
A79: Other | B79: Orange USD | C79: Panorama ES | D79: Sandra | F79: (1) 36x40 Classroom & Demo (1) 24x40 Bldg | G79: 3 | H79: 45901 | I79: Due to time restraints the customer has elected to refurbish some of their exsisting units
A80: Price | B80: Garden Grove USD | C80: Multiple Sites | D80: Sandra | F80: 12x40 TB, 24x40 and 36x40 Classrooms | G80: 6 | I80: Our price was too high
A81: Price | B81: PMSI Dixon Lake Ranger Station | C81: PMSI Dixon Lake Ranger Station | D81: Diana/Quinton | E81: 288276 | F81: (1) 24'x64' with axels | G81: 2 | I81: Our price was too high | J81: No | K81: No | L81: No | M81: 0
A82: Other | B82: OCFA | C82: Laundry Facility | D82: Diana | E82: N/A | F82: (1) 66'x42' | G82: 9 | H82: TBD - Bid Process | I82: Customer has submitted pricing for final review. Customer requested a rendering to present their report/request to go modular to the board. Modular design was not the preferred construction method. | M82: 0
A83: Other | B83: LAUSD - Charter School | C83: Jordan MS | D83: Joe | E83: 619211 | F83: (1) 48x40 MPR | G83: 4 | I83: The Board chose iMod Systems for their ability for future relocation and reconfigurable alternatives. | J83: No | K83: ######## | L83: No | M83: 0
A84: Other | B84: GMH Builders | C84: Sonoma Mountain ECS | D84: Joe | F84: (2) 24x40 Classroom Bldgs | G84: 4 | I84: GMH was not selected for the LLB | J84: No | K84: No | L84: No | M84: 0
B85: Hensel Phelps | C85: West Valley Community College | D85: Joe | F85: (3) 12x40 Toilet Buildings | G85: 16 | I85: 3 year lease bid for locker room and toilet buildings | K85: No | L85: No | M85: 0
F86: (5) 24x40 Locker Room Buildings
A87: Other | F87: (1) 36x40 Training Room Building
A88: Price | B88: Benicia USD | C88: Benicia HS | D88: Joe | F88: (1) 12X40 Restroom/Storage/Snack Bar | G88: 1 | I88: District went with AMS | J88: No | K88: No | L88: No | M88: 0
A89: Price | B89: Mobile Modular | C89: FOB | D89: Joe | E89: 463131 | F89: (4) 24x40 HCD Classroom Buildings | G89: 8 | H89: 45901 | I89: Lost to Class Leasing | J89: No | K89: 45782 | L89: No | M89: 0
A90: Price | B90: Sweetwater Lease | D90: Diana | F90: (50) CR's and RR - various bldg. configurations | I90: SCM pricing was too high. | J90: No | K90: No | L90: No | M90: 0
A91: Other | B91: Visalia USD | C91: Valley Oak MS | D91: Joe | E91: No BOM | F91: (1) 67x36 Classroom Building | G91: 5 | H91: 46113 | I91: No bid, Slab on Grade. | J91: No | K91: No | L91: No | M91: 0
A92: Schedule | B92: Jurupa Valley USD | C92: Jurupa MS | D92: Sandra | E92: 302389 | F92: (1) 48x40 | G92: 4 | I92: Customer went with AMS because they were able to receive plans in two weeks vs the time frame we provided | J92: No | K92: Yes | L92: No | M92: 0 | N92: TBD due to scope changes
A93: Other | B93: US Army Corps of Engineers | C93: USACE Santa Ana Dam Resident Office Complex | D93: Sandra | F93: (1) 36x60 Office HCD | G93: 3 | H93: TBD | I93: Proceeded with a leased bldg | J93: NO | M93: 0
A94: Other | B94: Paul Morrissey | C94: La Sierra University | D94: Sandra | F94: Went with a lease bldg | I94: Went with a leased building
A95: Price | B95: Oceanside USD | C95: Multiple Sites | D95: Sandra | F95: 30x32 CR, 24x40 CR and Restroom Buildings | G95: 17 | I95: Lost due to Price
A96: Other | B96: Palisades USD | C96: Multiple Sites | D96: Sandra | F96: (11) 24x40 CR, (11) 36x40 and (4) TB | G96: 59 | H96: TBD | I96: Ended up Leasing the buildings
A97: Other | B97: William Scotsman | C97: Bakersfield City USD | D97: Diana | E97: 124123.35 | F97: (1) 30'x32' Classroom building | G97: 3 | I97: Customer decided to replace the burned unit with an existing unit that the district already owned. | K97: 45749
A98: Price | B98: McKinleyville USD | C98: Prairie ES | D98: Joe | E98: 4502174 | F98: (3) 72x40 TK | G98: 18 | I98: Lost to AMS $3,381,200 (delta is $1,120,974) | M98: 0
A99: Other | B99: ICEF Inglewood | C99: Ingelwood | D99: Sandra | E99: 13178400 | F99: 2 Story Modular Classroom Bldg | I99: Went away due to school funding/property issues. Ryan said it may come back but not until ne
A100: Other | B100: Ventura USD | C100: Loma Vista ES | D100: Joe | F100: (1) 30x32 CR | G100: 3 | H100: 45870 | I100: District hired Levi to modernize their existing building instead of buying a new one. | M100: 0
...

Sheet Sheet3
A3: Lost Code | B3: Count of Customer Name
A4: Funding | B4: 7
A5: MISC | B5: 23
A6: Pre-qual | B6: 1
A7: Price | B7: 46
A8: Schedule | B8: 9
A9: Technical | B9: 5
A10: (blank) | B10: 6

Sheet Closed Deals 23 & 24
A1: Customer | B1: Project Name | C1: BDM | D1: Job Number | E1: Contract Value | F1: Building(s) | G1: Floor(s) | H1: Start Date for Production | I1: Estimated DSA Approval (per Engineering) | J1: Contract Type | K1: Current Status/Notes | L1: Confidence Level | M1: Bid Piggyback | N1: Estimated Completion Date | O1: Most Recent Proposal (Date) | P1: Engineering Release (Date) | Q1: Job Release (Date) | R1: PM | S1: Estimated Value | T1: Kick-off Meeting | U1: Hand-off Meeting
A2: Magnolia SD | B2: Dr. Albert Schweitzer 60x32 | C2: Sandra | D2: 11443 | E2: 632019.37 | F2: 60x32 | G2: 5 | H2: 45163 | I2: Approved | J2: PO | K2: N/A | L2: 1 | M2: PB | N2: August, 2024 | P2: Yes | Q2: Yes | R2: Moanes | S2: =IFERROR(E2*L2,0) -> 632019.37
A3: Modesto CS | B3: El Vista ES | C3: Joe | D3: 11446 | E3: 5500000 | F3: (1) 156X60 MPR/Cafeteria | G3: 26 | H3: 45163 | I3: Approved | J3: Signed Proposal | K3: N/A | L3: 1 | M3: PB | N3: 45474 | O3: Yes | P3: Yes | Q3: Yes | R3: Kenny | S3: =IFERROR(E3*L3,0) -> 5500000
A4: Mountain View SD | B4: Miramonte ES | C4: Sandra | D4: 11403 | E4: 181837 | F4: 12x40 Restroom | G4: 1 | H4: 45180 | I4: Approved | J4: PO | K4: N/A | L4: 1 | M4: PB | N4: November/December,2023 | P4: Yes | Q4: Yes | R4: Gino | S4: =IFERROR(E4*L4,0) -> 181837
A5: Mountain View SD | B5: Monte Vista ES | C5: Sandra | D5: 11401 | E5: 181837 | F5: 12x40 Restroom | G5: 1 | H5: 45181 | I5: Approved | J5: PO | K5: N/A | L5: 1 | N5: November/December,2023 | P5: Yes | Q5: Yes | R5: Gino | S5: =IFERROR(E5*L5,0) -> 181837
A6: Coachella USD | B6: North Shore ES | C6: Sandra | D6: 11397 | E6: 13916167 | F6: New Campus | G6: 83 | H6: 45187 | I6: Approved | J6: Contract | K6: N/A | L6: 1 | M6: PB | N6: September, 2024 | P6: Yes | Q6: Yes | R6: Kenny | S6: =IFERROR(E6*L6,0) -> 13916167
A7: Calexico USD | B7: Calexico HS | C7: Sandra | D7: 11447 | E7: 13852000 | F7: Two Story | G7: 56 | H7: 45239 | I7: Approved | J7: Contract | K7: N/A | L7: 1 | M7: PB | N7: June, 2024 | P7: Yes | Q7: Yes | R7: Kenny | S7: =IFERROR(E7*L7,0) -> 13852000
A8: Lathrop Construction | B8: Santa Rosa Junior College - A1 RR | C8: Joe | D8: 11448 | E8: 129445 | F8: (1) 12x40 Restroom | G8: 1 | H8: 45243 | I8: Approved | J8: PO-1169-007 | K8: N/A | L8: 1 | M8: PB | N8: 45231 | O8: Yes | P8: Yes | Q8: Yes | R8: Moanes | S8: =IFERROR(E8*L8,0) -> 129445
A9: Corona-Norco | B9: Highland | C9: Sandra | D9: 11416 | E9: 3408324 | F9: (3) 72x40 & (1) 36x40 | G9: 21 | H9: 45299 | I9: Approved | J9: Contract | K9: N/A | L9: 1 | M9: PB | N9: 45505 | P9: Yes | Q9: Yes | R9: Mehdi | S9: =IFERROR(E9*L9,0) -> 3408324
A10: Corona-Norco | B10: Victress Bower | C10: Sandra | D10: 11417 | E10: 795151 | F10: 60x40 | G10: 5 | H10: 45302 | I10: Approved | J10: Contract | K10: N/A | L10: 1 | M10: PB | N10: 45505 | P10: Yes | Q10: Yes | R10: Mehdi | S10: =IFERROR(E10*L10,0) -> 795151
A11: Magnolia SD | B11: Dr. Albert Schweitzer | C11: Sandra | D11: 11443 | E11: 890992.27 | F11: 100x32 | G11: 10 | H11: 45308 | I11: Approved | J11: PO | K11: N/A | L11: 1 | M11: PB | N11: August, 2024 | P11: Yes | Q11: Yes | R11: Moanes | S11: =IFERROR(E11*L11,0) -> 890992.27
A12: Menifee USD | B12: Ridgemoor ES | C12: Sandra | D12: 11474 | E12: 2842622.5 | F12: (1) 144x40 & (1) 72x40 | G12: 18 | H12: 45309 | I12: Approved | J12: Contract | K12: N/A | L12: 1 | M12: PB | N12: Summer 2024 | P12: Yes | Q12: Yes | R12: Kenny | S12: =IFERROR(E12*L12,0) -> 2842622.5
A13: Magnolia SD | B13: Dr. Peter Marshall | C13: Sandra | D13: 11450 | E13: 1158613.1 | F13: 130x32 | G13: 13 | H13: 45317 | I13: Approved | J13: PO | K13: N/A | L13: 1 | M13: PB | N13: August, 2024 | P13: Yes | Q13: Yes | R13: Moanes | S13: =IFERROR(E13*L13,0) -> 1158613.1
A14: Hesperia Unified | B14: Mission Crest ES | C14: Sandra | D14: 11433 | E14: 863719 | F14: 72x40 TK | G14: 6 | H14: 45321 | I14: Approved | J14: Contract | K14: N/A | L14: 1 | M14: PB | N14: August, 2024 | P14: Yes | Q14: Yes | R14: Gino | S14: =IFERROR(E14*L14,0) -> 863719
A15: Hesperia Unified | B15: Maple School of Innovation | C15: Sandra | D15: 11436 | E15: 817329 | F15: 72x40 TK | G15: 6 | H15: 45322 | I15: Approved | J15: Contract | K15: N/A | L15: 1 | M15: PB | N15: August, 2024 | P15: Yes | Q15: Yes | R15: Gino | S15: =IFERROR(E15*L15,0) -> 817329
A16: Oro Grande SD | B16: Riverside Prep Weight Room | C16: Sandra | D16: 11444 | E16: 823142.22 | F16: 84X40 | G16: 7 | H16: 45330 | I16: Approved | J16: Contract | K16: N/A | L16: 1 | M16: PB | N16: Completed | P16: Yes | Q16: Yes | R16: Gino | S16: =IFERROR(E16*L16,0) -> 823142.22
A17: Chino Valley USD | B17: Cal Aero Preserve Acad | C17: Sandra | D17: 11453 | E17: 287193.06 | F17: 36x40 Fun Club | G17: 3 | H17: 45341 | I17: Approved | J17: PO 242047 | K17: N/A | L17: 1 | M17: PB | N17: 45505 | P17: Yes | Q17: Yes | R17: Mehdi | S17: =IFERROR(E17*L17,0) -> 287193.06
A18: Chino Valley USD | B18: E.J. Marshall ES | C18: Sandra | D18: 11454 | E18: 287193.06 | F18: 36X40 Fun Club | G18: 3 | H18: 45341 | I18: Approved | J18: PO 242044 | K18: N/A | L18: 1 | M18: PB | N18: 45505 | P18: Yes | Q18: Yes | R18: Mehdi | S18: =IFERROR(E18*L18,0) -> 287193.06
A19: Banning USD | B19: Florida Discovery PK | C19: Sandra | D19: 11475 | E19: 3242817 | F19: (2) 84x40 & (1) 72x40 | G19: 20 | H19: 45341 | I19: Approved | J19: Contract | K19: N/A | L19: 1 | M19: PB | N19: 45505 | P19: Yes | Q19: Yes | R19: Mehdi | S19: =IFERROR(E19*L19,0) -> 3242817
A20: Chino Valley USD | B20: Glenmeade ES | C20: Sandra | D20: 11452 | E20: 287193.06 | F20: 36X40 Fun Club | G20: 3 | H20: 45344 | I20: Approved | J20: PO 242038 | K20: N/A | L20: 1 | M20: PB | N20: 45505 | P20: Yes | Q20: Yes | R20: Mehdi | S20: =IFERROR(E20*L20,0) -> 287193.06
A21: Chino Valley USD | B21: Doris Dickson ES | C21: Sandra | D21: 11460 | E21: 287193.06 | F21: 36X40 Fun Club | G21: 3 | H21: 45349 | I21: Approved | J21: PO 242081 | K21: N/A | L21: 1 | M21: PB | N21: 45505 | P21: Yes | Q21: Yes | R21: Mehdi | S21: =IFERROR(E21*L21,0) -> 287193.06
A22: Hesperia Unified | B22: Lime Street ES TK | C22: Sandra | D22: 11437 | E22: 817329 | F22: 72X40 | G22: 6 | H22: 45349 | I22: Approved | J22: Contract | K22: N/A | L22: 1 | M22: PB | N22: August, 2024 | P22: Yes | Q22: Yes | R22: Gino | S22: =IFERROR(E22*L22,0) -> 817329
A23: Cajon Valley USD | B23: Anza ES | C23: Diana | D23: 11466 | E23: 335097.99 | F23: (3) 24x40 | G23: 6 | H23: 45351 | I23: Approved | J23: PO 12405687 | K23: N/A | L23: 1 | M23: PB | N23: 45505 | O23: 45239 | P23: Yes | Q23: Yes | R23: Gino | S23: =IFERROR(E23*L23,0) -> 335097.99
A24: Anaheim Union HSD | B24: Magnolia | C24: Sandra | D24: 11496 | E24: 126540.94 | F24: 8-6x16-7 Restroom | G24: 1 | H24: 45364 | I24: Approved | J24: Contract | K24: N/A | L24: 1 | M24: PB | N24: 45383 | P24: Yes | Q24: Yes | R24: Gino | S24: =IFERROR(E24*L24,0) -> 126540.94
A25: Cajon Valley USD | B25: Rancho San Diego ES | C25: Diana | D25: 11471 | E25: 251606.72 | F25: (2) 30x32 | G25: 6 | H25: 45352 | I25: Approved | J25: PO 12405692 | K25: N/A | L25: 1 | M25: PB | N25: 45505 | O25: 45239 | P25: Yes | Q25: Yes | R25: Gino | S25: =IFERROR(E25*L25,0) -> 251606.72
A26: Chino Valley USD | B26: Michael G. Wickman ES | C26: Sandra | D26: 11455 | E26: 287193.06 | F26: 36x40 Fun Club | G26: 3 | H26: 45355 | I26: Approved | J26: PO 242050 | K26: N/A | L26: 1 | M26: PB | N26: 45505 | P26: Yes | Q26: Yes | R26: Mehdi | S26: =IFERROR(E26*L26,0) -> 287193.06
A27: Cajon Valley USD | B27: Flying Hills ES | C27: Diana | D27: 11468 | E27: 251606.72 | F27: (2) 30x32 | G27: 6 | H27: 45359 | I27: Approved | J27: PO 12405689 | K27: N/A | L27: 1 | M27: PB | N27: 45505 | O27: 45239 | P27: Yes | Q27: Yes | R27: Gino | S27: =IFERROR(E27*L27,0) -> 251606.72
A28: Cajon Valley USD | B28: Naranca ES | C28: Diana | D28: 11470 | E28: 132697 | F28: (1) 24x40 w/RR | G28: 2 | H28: 45362 | I28: Approved | J28: PO 12450691 | K28: N/A | L28: 1 | M28: PB | N28: 45505 | O28: 45239 | P28: Yes | Q28: Yes | R28: Gino | S28: =IFERROR(E28*L28,0) -> 132697
A29: Hesperia Unified | B29: Cottonwood ES | C29: Sandra | D29: 11440 | E29: 817329 | F29: 72X40 TK | G29: 6 | H29: 45362 | I29: Approved | J29: Contract | K29: N/A | L29: 1 | M29: PB | N29: July, 2024 | P29: Yes | Q29: Yes | R29: Gino | S29: =IFERROR(E29*L29,0) -> 817329
A30: Hesperia Unified | B30: Kingston ES | C30: Sandra | D30: 11438 | E30: 817329 | F30: 72x40 TK | G30: 6 | H30: 45369 | I30: Approved | J30: Contract | K30: N/A | L30: 1 | M30: PB | N30: July, 2024 | P30: Yes | Q30: Yes | R30: Gino | S30: =IFERROR(E30*L30,0) -> 817329
A31: Cajon Valley USD | B31: Hillsdale MS | C31: Diana | D31: 11469 | E31: 194365.2 | F31: (1) 12x40 RR | G31: 1 | H31: 45371 | I31: Approved | J31: PO 12405690 | K31: N/A | L31: 1 | M31: PB | N31: 45505 | O31: 45239 | P31: Yes | Q31: Yes | R31: Gino | S31: =IFERROR(E31*L31,0) -> 194365.2
A32: Anaheim ESD | B32: Jefferson | C32: Sandra | D32: 11494 | E32: 637606.79 | F32: (1) 24x40 and (1) 12x40 Restroom | G32: 7 | H32: 45377 | I32: Approved | J32: LOI | K32: Shipped | L32: 1 | M32: PB | N32: Summer 2024 | P32: Yes | R32: Moanes | S32: =IFERROR(E32*L32,0) -> 637606.79
A33: Hesperia Unified | B33: Mesquite Trails ES 72X40 TK | C33: Sandra | D33: 11434 | E33: 817329 | F33: 72X40 TK | G33: 6 | H33: 45377 | I33: Approved | J33: Contract | K33: N/A | L33: 1 | M33: PB | N33: August, 2024 | P33: Yes | Q33: Yes | R33: Gino | S33: =IFERROR(E33*L33,0) -> 817329
A34: Hesperia Unified | B34: Eucalyptus | C34: Sandra | D34: 11439 | E34: 817329 | F34: 72X40 TK | G34: 6 | H34: 45383 | I34: Approved | J34: Contract | K34: N/A | L34: 1 | M34: PB | N34: July, 2024 | P34: Yes | Q34: Yes | R34: Gino | S34: =IFERROR(E34*L34,0) -> 817329
A35: Helendale SD | B35: Helendale | C35: Sandra | D35: 11504 | E35: 298215.84 | F35: (2) 24x40 | G35: 4 | H35: 45387 | I35: Approved | J35: PO 240296 | K35: N/A | L35: 1 | M35: PB | N35: 45474 | P35: Yes | Q35: Yes | R35: Moanes | S35: =IFERROR(E35*L35,0) -> 298215.84
A36: Walnut Valley USD | B36: Evergreen ES | C36: Sandra | D36: 11430 | E36: 326942.82 | F36: 36x40 Daycare | G36: 3 | H36: 45390 | I36: Approved | J36: P23-04716 | K36: Shipped | L36: 1 | M36: PB | P36: Yes | Q36: Yes | R36: Moanes | S36: =IFERROR(E36*L36,0) -> 326942.82
A37: Helendale SD | B37: Helendale | C37: Sandra | D37: 11427 | E37: 391547.55 | F37: (1) 36x40 | G37: 3 | H37: 45392 | I37: Approved | J37: PO | K37: N/A | L37: 1 | M37: PB | N37: 45474 | P37: Yes | Q37: Yes | R37: Moanes | S37: =IFERROR(E37*L37,0) -> 391547.55
A38: Cajon Valley USD | B38: Crest ES | C38: Diana | D38: 11467 | E38: 256043.7 | F38: (2) 30x32 | G38: 6 | H38: 45393 | I38: Approved | J38: PO 12405688 | K38: N/A | L38: 1 | M38: PB | N38: 45505 | O38: 45239 | P38: Yes | Q38: Yes | R38: Gino | S38: =IFERROR(E38*L38,0) -> 256043.7
A39: Sylvan USD | B39: Ustach MS | C39: Joe | D39: 11482 | E39: 325719.08 | F39: (2) 24x40 CR | G39: 4 | H39: 45393 | I39: Approved | J39: PO 242111 | K39: N/A | L39: 1 | M39: PB | N39: 45509 | O39: Yes | P39: Yes | Q39: Yes | R39: Kenny | S39: =IFERROR(E39*L39,0) -> 325719.08
A40: Sylvan USD | B40: Freedom ES | C40: Joe | D40: 11478 | E40: 325719.08 | F40: (2) 24x40 CR | G40: 4 | H40: 45394 | I40: Approved | J40: PO 242113 | K40: N/A | L40: 1 | M40: PB | N40: 45509 | O40: Yes | P40: Yes | Q40: Yes | R40: Kenny | S40: =IFERROR(E40*L40,0) -> 325719.08
A41: Sylvan USD | B41: Sylvan ES | C41: Joe | D41: 11481 | E41: 325719.08 | F41: (2) 24x40 CR | G41: 4 | H41: 45400 | I41: Approved | J41: PO 242110 | K41: N/A | L41: 1 | M41: PB | N41: 45509 | O41: Yes | P41: Yes | Q41: Yes | R41: Kenny | S41: =IFERROR(E41*L41,0) -> 325719.08 | T41: TBD
A42: Sylvan USD | B42: Crossroads ES | C42: Joe | D42: 11477 | E42: 325719.08 | F42: (2) 24x40 CR | G42: 4 | H42: 45401 | I42: Approved | J42: PO 242114 | K42: N/A | L42: 1 | M42: PB | N42: 45509 | O42: Yes | P42: Yes | Q42: Yes | R42: Kenny | S42: =IFERROR(E42*L42,0) -> 325719.08
A43: Sylvan USD | B43: Stockard Coffee ES | C43: Joe | D43: 11480 | E43: 325719.08 | F43: (2) 24x40 CR | G43: 4 | H43: 45405 | I43: Approved | J43: PO 242109 | K43: N/A | L43: 1 | M43: PB | N43: 45509 | O43: Yes | P43: Yes | Q43: Yes | R43: Kenny | S43: =IFERROR(E43*L43,0) -> 325719.08
A44: Sylvan USD | B44: Orchard ES | C44: Joe | D44: 11476 | E44: 162859.54 | F44: (1) 24x40 CR | G44: 2 | H44: 45406 | I44: Approved | J44: PO 242112 | K44: N/A | L44: 1 | M44: PB | N44: 45509 | O44: Yes | P44: Yes | Q44: Yes | R44: Kenny | S44: =IFERROR(E44*L44,0) -> 162859.54
A45: Sylvan USD | B45: Somerset MS | C45: Joe | D45: 11479 | E45: 325719.08 | F45: (2) 24x40 CR | G45: 4 | H45: 45407 | I45: Approved | J45: PO 242108 | K45: N/A | L45: 1 | M45: PB | N45: 45509 | O45: Yes | P45: Yes | Q45: Yes | R45: Kenny | S45: =IFERROR(E45*L45,0) -> 325719.08
A46: Chino Valley USD | B46: Borba ES | C46: Sandra | D46: 11456 | E46: 256019.13 | F46: 36x40 Fun Club | G46: 3 | H46: 45408 | I46: Approved | J46: PO 241423 | K46: N/A | L46: 1 | M46: PB | N46: 45505 | P46: Yes | Q46: Yes | R46: Mehdi | S46: =IFERROR(E46*L46,0) -> 256019.13
A47: Chino Valley USD | B47: Levi H. Dickey ES | C47: Sandra | D47: 11457 | E47: 256019.13 | F47: 36x40 Fun Club | G47: 3 | H47: 45413 | I47: Approved | J47: PO 241422 | K47: N/A | L47: 1 | M47: PB | N47: 45505 | P47: Yes | Q47: Yes | R47: Mehdi | S47: =IFERROR(E47*L47,0) -> 256019.13
A48: Chino Valley USD | B48: Rolling Ridge ES | C48: Sandra | D48: 11461 | E48: 475267.38 | F48: 60x40 Fun Club | G48: 5 | H48: 45413 | I48: Approved | J48: PO 241419 | K48: N/A | L48: 1 | M48: PB | N48: August, 2024 | P48: Yes | Q48: Yes | R48: Mehdi | S48: =IFERROR(E48*L48,0) -> 475267.38
A49: Chino Valley USD | B49: Walnut Avenue ES | C49: Sandra | D49: 11458 | E49: 256019.13 | F49: 36x40 Fun Club | G49: 3 | H49: 45415 | I49: Approved | J49: PO 241421 | K49: N/A | L49: 1 | M49: PB | N49: 45505 | P49: Yes | Q49: Yes | R49: Mehdi | S49: =IFERROR(E49*L49,0) -> 256019.13
A50: Walnut Valley USD | B50: Vejar ES | C50: Sandra | D50: 11432 | E50: 197993.06 | F50: 24x40 Classroom | G50: 2 | H50: 45415 | I50: Approved | J50: P23-03994 | K50: Shipped | L50: 1 | M50: PB | N50: Summer 2024 | P50: Yes | Q50: Yes | R50: Moanes | S50: =IFERROR(E50*L50,0) -> 197993.06
A51: Chino Valley USD | B51: Lyle Briggs ES | C51: Sandra | D51: 11459 | E51: 256019.13 | F51: 36x40 Fun Club | G51: 3 | H51: 45421 | I51: Approved | J51: PO 241420 | K51: N/A | L51: 1 | M51: PB | N51: 45505 | P51: Yes | Q51: Yes | R51: Mehdi | S51: =IFERROR(E51*L51,0) -> 256019.13
A52: AMCO Structures | B52: Volunteers of America | C52: Diana | D52: 60002 | E52: 349965 | F52: Labor Only | G52: 11 | H52: 45428 | I52: Approved | J52: Signed Proposal | K52: Unit went to site, had electrical repairs needed due to light locations. Just reported issue w/ plumbing manifold, awaiting site visit to review conditions | L52: 1 | M52: Negotiated | N52: 45717 | O52: N/A | P52: N/A | Q52: N/A | R52: Carlo | S52: =IFERROR(E52*L52,0) -> 349965
A53: Magnolia SD | B53: Dr. Jonas Salk | C53: Sandra | D53: 11465 | E53: 3042905.3 | F53: 182x64 | G53: 18 | H53: 45429 | I53: Approved | J53: PO | K53: N/A | L53: 1 | M53: PB | N53: August, 2024 | P53: Yes | Q53: Yes | R53: Moanes | S53: =IFERROR(E53*L53,0) -> 3042905.3
A54: Magnolia SD | B54: Dr. Jonas Salk | C54: Sandra | D54: 11464 | E54: 2536354.6 | F54: 152x64 | G54: 15 | H54: 45435 | I54: Approved | J54: PO | K54: N/A | L54: 1 | M54: PB | N54: August, 2024 | P54: Yes | Q54: Yes | R54: Moanes | S54: =IFERROR(E54*L54,0) -> 2536354.6
A55: Anaheim ESD | B55: Stoddard ES | C55: Sandra | D55: 11485 | E55: 97864.21 | F55: (1) 8-6x21-6 Restroom | G55: 1 | H55: 45443 | I55: Approved | J55: LOI | K55: N/A | L55: 1 | M55: PB | N55: Summer 2024 | P55: Yes | Q55: Yes | R55: Moanes | S55: =IFERROR(E55*L55,0) -> 97864.21
A56: Cajon Valley USD | B56: WD Hall ES | C56: Diana | D56: 11472 | E56: 226400.2 | F56: (2) 24x40 | G56: 4 | H56: 45446 | I56: Approved | J56: PO 12405693 | K56: N/A | L56: 1 | M56: PB | N56: 45505 | O56: 45239 | P56: Yes | Q56: Yes | R56: Gino | S56: =IFERROR(E56*L56,0) -> 226400.2
A57: Sacramento City USD | B57: McClatchy HS | C57: Sandra | D57: 11514 | E57: =203159.84+218489.03 -> 421648.87 | F57: (1)8-6x21-6 Restroom (1)8'-6"x 32'-0" Restoom | G57: 2 | H57: 45450 | I57: Approved | J57: Signed Contract | K57: N/A | L57: 1 | M57: PB | N57: Summer 2024 | P57: Yes | Q57: Yes | R57: Kenny | S57: =IFERROR(E57*L57,0) -> 421648.87
A58: Newport Mesa | B58: California MS | C58: Sandra | D58: 11490 | E58: 323781.38 | F58: (2) 24x40 | G58: 4 | H58: 45456 | I58: Approved | J58: PO T78A0164 | K58: Shipped | L58: 1 | M58: PB | N58: Mid-July 2024 | P58: Yes | Q58: Yes | R58: Mehdi | S58: =IFERROR(E58*L58,0) -> 323781.38
A59: AMCO Structures | B59: Port of Long Beach | C59: Diana | D59: 60005 | E59: 30875 | F59: Labor Only | G59: 3 | H59: 45461 | I59: Approved | J59: Yes | K59: SC completed SOW to frame & 3D building. Has since assisted w/ some door install and FRP wall cover install. Bldg almost complete, will be shipping next week | L59: 1 | M59: Negotiated | N59: Complete | O59: N/A | P59: N/A | Q59: N/A | S59: =IFERROR(E59*L59,0) -> 30875
A60: Newport Mesa | B60: Newport Heights | C60: Sandra | D60: 11493 | E60: 640215.2 | F60: (3) 24x40 & (1) 12x40 | G60: 7 | H60: 45462 | I60: Approved | J60: PO T78A0167 | K60: Shipped | L60: 1 | M60: PB | N60: Mid-July 2024 | P60: Yes | Q60: Yes | R60: Mehdi | S60: =IFERROR(E60*L60,0) -> 640215.2
A61: Newport Mesa | B61: Killybrooke ES | C61: Sandra | D61: 11491 | E61: 802105.8 | F61: (4) 24x40 & (1) 12x40 | G61: 9 | H61: 45463 | I61: Approved | J61: PO T78A0165 | K61: Shipped | L61: 1 | M61: PB | N61: Mid-July 2024 | P61: Yes | Q61: Yes | R61: Mehdi | S61: =IFERROR(E61*L61,0) -> 802105.8
A62: Unified Modular | B62: Baldwin Park | C62: Diana | D62: 11515 | E62: 235020.48 | F62: (2) 24x40 | G62: 4 | H62: 45464 | I62: Approved | J62: 5/9/24 PO | K62: Buildings have been picked up. | L62: 1 | M62: Negotiated | N62: 45471 | O62: 45418 | P62: 45441 | Q62: Yes | R62: Diana | S62: =IFERROR(E62*L62,0) -> 235020.48
A63: Newport Mesa | B63: Eastbluff ES | C63: Sandra | D63: 11492 | E63: =647562.76+316433.8 -> 963996.56 | F63: (5) 24x40 & (1) 12x40 | G63: 11 | H63: 45470 | I63: Approved | J63: PO T78A0166 | K63: Shipped | L63: 1 | M63: PB | N63: Mid-July 2024 | P63: Yes | Q63: Yes | R63: Mehdi | S63: =IFERROR(E63*L63,0) -> 963996.56
A64: Red Bluff Union ESD | B64: Jackson Heights ES | C64: Sandra | D64: 11497 | E64: 1884496.9 | F64: 140x32 Classroom | G64: 14 | H64: 45476 | I64: Approved | J64: Signed Contract | K64: Shipped | L64: 1 | M64: BID | N64: 45627 | P64: No | R64: Kenny | S64: =IFERROR(E64*L64,0) -> 1884496.9
A65: Ventura USD | B65: E.P. Foster | C65: Sandra | D65: 11484 | E65: 348250 | F65: (1) 12x60 Restroom | G65: 1 | H65: 45476 | I65: Approved | J65: LOI | K65: N/A | L65: 1 | M65: PB | N65: Summer 2024 | P65: Yes | Q65: Yes | R65: Gino | S65: =IFERROR(E65*L65,0) -> 348250
A66: Palm Springs USD | B66: Cielo Vista | C66: Sandra | D66: 11511 | E66: 139024.21 | F66: (1) 10x32 Restroom | G66: 1 | H66: 45482 | I66: Approved | J66: PO | K66: Shipped/Working on raising heights on restroom fixtures | L66: 1 | M66: PB | N66: Summer 2024 | P66: Yes | Q66: Yes | R66: Gino | S66: =IFERROR(E66*L66,0) -> 139024.21
A67: WillScot | B67: Savanna Daycare | C67: Joe | D67: 11449 | E67: 1165385.4 | F67: (1) 60x60 | G67: 5 | H67: 45483 | I67: Approved | J67: PO 1002338384 | K67: Mo is managing the project | L67: 1 | N67: 45474 | O67: Yes | P67: Yes | Q67: Yes | R67: Moanes | S67: =IFERROR(E67*L67,0) -> 1165385.4
A68: Fillmore USD | B68: Adult School | C68: Sandra | D68: 11508 | E68: 149552.4 | F68: 12x40 A Restroom | G68: 1 | H68: 45485 | I68: Approved | J68: Signed Proposal | L68: 1 | M68: PB | N68: 45505 | P68: Yes | Q68: Yes | R68: Moanes | S68: =IFERROR(E68*L68,0) -> 149552.4
A69: Fillmore USD | B69: Piru ES | C69: Sandra | D69: 11445 | E69: 176813.85 | F69: 12x40 C2 Restroom | G69: 1 | H69: 45488 | I69: Approved | J69: PO R24-00296 | L69: 1 | M69: PB | N69: Summer 2024 | P69: Yes | Q69: Yes | R69: Moanes | S69: =IFERROR(E69*L69,0) -> 176813.85
A70: AMCO Structures | B70: Legacy | C70: Diana | D70: 60010 | E70: 17048 | F70: 24x40 Labor Only | G70: 2 | H70: 45489 | I70: Approved | J70: Contract | K70: SC completed SOW to frame & 3D building. | L70: 1 | M70: Negotiated | N70: Complete | O70: N/A | P70: N/A | Q70: N/A | R70: Carlo | S70: =IFERROR(E70*L70,0) -> 17048
A71: AMCO Structures | B71: Mt. Carmel | C71: Diana | D71: 60011 | E71: 20836 | F71: 24x60 Labor Only | G71: 2 | H71: 45490 | I71: Approved | J71: Contract | K71: SC completed SOW to frame & 3D building. | L71: 1 | M71: Negotiated | N71: Complete | O71: N/A | P71: N/A | Q71: N/A | R71: Carlo | S71: =IFERROR(E71*L71,0) -> 20836
A72: El Sol Academy (Charter) | B72: El Sol | C72: Sandra | D72: 11451 | E72: 1459935.4 | F72: 92x43 Music Room | G72: 9 | H72: 45490 | I72: Approved | J72: Contract | K72: Customer currently working onsite | L72: 1 | M72: PB | N72: 45536 | P72: Yes | Q72: Yes | R72: Mehdi | S72: =IFERROR(E72*L72,0) -> 1459935.4
A73: AMCO Structures | B73: Farm Aviation | C73: Diana | D73: 60012 | E73: 17048 | F73: 24x40 Labor Only | G73: 2 | H73: 45504 | I73: Approved | J73: Contract | K73: SC completed SOW to frame & 3D building. | L73: 1 | M73: Negotiated | N73: Complete | O73: N/A | P73: N/A | Q73: N/A | R73: Carlo | S73: =IFERROR(E73*L73,0) -> 17048
A74: AMCO Structures | B74: Watt EV | C74: Diana | D74: 60013 | E74: 14200 | F74: 20x40 Labor Only | G74: 2 | H74: 45506 | I74: Approved | J74: Contract | K74: SC completed SOW to frame & 3D building. | L74: 1 | M74: Negotiated | N74: Complete | O74: N/A | P74: N/A | Q74: N/A | R74: Carlo | S74: =IFERROR(E74*L74,0) -> 14200
A75: San Jacinto USD | B75: Engagement Center | C75: Sandra | D75: 11516 | E75: 634535.44 | F75: 36x40 Office Building | G75: 3 | H75: 45509 | I75: Approved | J75: Contract | K75: Change of deliver date due to rebid on site work | L75: 1 | M75: PB | N75: Completed | P75: Yes | R75: Gino | S75: =IFERROR(E75*L75,0) -> 634535.44
A76: AMCO Structures | B76: Chowchilla Building A | C76: Diana | D76: 60007 | E76: 145000 | F76: Labor Only | G76: 9 | H76: 45511 | I76: Approved | J76: Yes | K76: Project online and progressing, all 9 mods are 3D | L76: 1 | M76: Negotiated | N76: 45646 | O76: N/A | P76: N/A | Q76: N/A | R76: Carlo | S76: =IFERROR(E76*L76,0) -> 145000
A77: Hesperia USD | B77: Carmel ES | C77: Sandra | D77: 11441 | E77: 817329 | F77: 72X40 TK | G77: 6 | H77: 45519 | I77: Approved | J77: Contract | L77: 1 | M77: PB | N77: August, 2024 | P77: Yes | Q77: Yes | R77: Gino | S77: =IFERROR(E77*L77,0) -> 817329
A78: AMCO Structures | B78: Chowchilla Building B | C78: Diana | D78: 60008 | E78: 145000 | F78: Labor Only | G78: 9 | H78: 45524 | I78: Approved | J78: Yes | K78: 1st chassis online 8/15 | L78: 1 | M78: Negotiated | N78: 45646 | O78: N/A | P78: N/A | Q78: N/A | R78: Carlo | S78: =IFERROR(E78*L78,0) -> 145000
A79: Cajon Valley USD | B79: Magnolia ES | C79: Diana | D79: 11518 | E79: 537106.98 | F79: (3) 30'x32' Classrooms w/ single User RR, (1) 24'x40' Open CR | G79: 11 | H79: 45526 | I79: Approved | J79: PO 12500432 | K79: Customer would like buildings delivered as soon as possible. Need to find out if Architect is ready to open box. We can't start production, we need materials/inventory. (1) 24'x40' Building Shipping 10/4 | L79: 1 | M79: PB | N79: 45639 | O79: 45443 | P79: 45469 | Q79: 45469 | R79: Kenny | S79: =IFERROR(E79*L79,0) -> 537106.98
A80: Walnut Valley USD | B80: Walnut ES | C80: Sandra | D80: 11429 | E80: 198022.13 | F80: 24x40 Classroom | G80: 2 | H80: 45527 | I80: Approved | J80: P23-03995 | K80: Shipped | L80: 1 | M80: PB | N80: Summer 2024 | P80: Yes | Q80: Yes | R80: Moanes | S80: =IFERROR(E80*L80,0) -> 198022.13
A81: Lawndale ESD | B81: Green ES | C81: Sandra | D81: 11463 | E81: 673076.84 | F81: 60x40 Head Start Classroom | G81: 5 | H81: 45531 | I81: Approved | J81: PO-4216 | L81: 1 | M81: PB | N81: Summer 2024 | P81: Yes | Q81: Yes | R81: Mehdi | S81: =IFERROR(E81*L81,0) -> 673076.84
A82: Stanislaus USD | B82: Agnes Baptist ES | C82: Sandra | D82: 11462 | E82: 194636 | F82: (2) 8-’6’ x 16’-7’ RR | G82: 2 | H82: 45538 | I82: Approved | J82: PO 240998 | L82: 1 | M82: PB | O82: Yes | P82: Yes | Q82: Yes | R82: Kenny | S82: =IFERROR(E82*L82,0) -> 194636
A83: WillScot | B83: Stockpile | C83: Diana | D83: 11522 | E83: 5171824.8 | F83: (8) C2 Restrooms, (16) 36x40 and (8) 48x40 | G83: 88 | H83: 45539 | I83: Approved | J83: Yes | K83: Final proposal presented 8/15/24 to WillScot. POs received 8/20. | L83: 1 | M83: Negotiated | O83: Yes | P83: Yes | Q83: Yes | R83: Moanes | S83: =IFERROR(E83*L83,0) -> 5171824.8
A84: Corona Norco USD | B84: Highland ES Refurb | C84: Sandra | D84: 60014 | E84: 601290.05 | F84: (5) 24x40 Classroom Buildings | G84: 10 | H84: 45544 | J84: Yes | K84: Buildings are currently being worked on in yard | L84: 1 | R84: Gino | S84: =IFERROR(E84*L84,0) -> 601290.05
A85: Walnut Valley USD | B85: Collegewood ES | C85: Sandra | D85: 11431 | E85: 198022.13 | F85: 24x40 Classroom | G85: 2 | H85: 45546 | I85: Approved | J85: P23-04714 | L85: 1 | M85: PB | P85: Yes | Q85: Yes | R85: Moanes | S85: =IFERROR(E85*L85,0) -> 198022.13
A86: Hesperia USD | B86: Topaz Preparatory Academy | C86: Sandra | D86: 11542 | E86: 763488 | F86: (3) 24'x40' (1) 12'x40' RR | G86: 7 | H86: 45552 | I86: Approved | J86: Yes | L86: 1 | M86: PB | N86: 45749 | R86: Gino | S86: =IFERROR(E86*L86,0) -> 763488
A87: Hesperia USD | B87: Mission Crest ES | C87: Sandra | D87: 11544 | E87: 473993 | F87: (3) 24'x40' | G87: 6 | H87: 45553 | I87: Approved | J87: Yes | L87: 1 | M87: PB | N87: 45693 | R87: Gino | S87: =IFERROR(E87*L87,0) -> 473993
A88: Central Union HSD | B88: Central Union | C88: Sandra | D88: 11503 | E88: 3541658.8 | F88: (2) 168x40 | G88: 28 | H88: 45559 | I88: Approved | J88: Yes | L88: 1 | M88: PB | N88: Sept Delivery, Jan Occupy | R88: Kenny | S88: =IFERROR(E88*L88,0) -> 3541658.8
A89: Hesperia USD | B89: Cottonwood ES | C89: Sandra | D89: 11545 | E89: 420981.5 | F89: (3) 24'x40' | G89: 6 | H89: 45560 | I89: Approved | J89: Yes | L89: 1 | M89: PB | R89: Gino | S89: =IFERROR(E89*L89,0) -> 420981.5
A90: Hesperia USD | B90: Mesquite Trails ES | C90: Sandra | D90: 11541 | E90: 420981.5 | F90: (3) 24'x40' | G90: 6 | H90: 45566 | I90: Approved | J90: Yes | L90: 1 | M90: PB | N90: 45688 | R90: Gino | S90: =IFERROR(E90*L90,0) -> 420981.5
A91: Hesperia USD | B91: Maple ES | C91: Sandra | D91: 11549 | E91: 420981.5 | F91: (3) 24'x40' | G91: 6 | H91: 45575 | I91: Approved | J91: Yes | L91: 1 | M91: PB | N91: 45743 | R91: Gino | S91: =IFERROR(E91*L91,0) -> 420981.5
A92: Hesperia USD | B92: Cypress School of the Arts | C92: Sandra | D92: 11548 | E92: 473993 | F92: (3) 24'x40' | G92: 6 | H92: 45589 | I92: Approved | J92: Yes | L92: 1 | M92: PB | N92: 45692 | R92: Gino | S92: =IFERROR(E92*L92,0) -> 473993
A93: Hesperia USD | B93: Krystal ES | C93: Sandra | D93: 11554 | E93: 280655 | F93: (2) 24'x40' | G93: 4 | H93: 45593 | I93: Approved | J93: Yes | L93: 1 | M93: PB | N93: 45754 | R93: Gino | S93: =IFERROR(E93*L93,0) -> 280655
A94: AMCO Structures | B94: Long Beach Police Training Academy | C94: Diana | D94: 60016 | E94: 236317 | F94: Labor + Concrete | G94: 20 | H94: 45595 | I94: Approved | J94: Yes | L94: 1 | M94: Negotiated | N94: Summer 2025 | R94: Carlo | S94: =IFERROR(E94*L94,0) -> 236317
A95: Hesperia USD | B95: Eucalyptus ES | C95: Sandra | D95: 11543 | E95: 420981.5 | F95: (3) 24'x40' | G95: 6 | H95: 45596 | I95: Approved | J95: Yes | L95: 1 | M95: PB | N95: 45747 | R95: Gino | S95: =IFERROR(E95*L95,0) -> 420981.5
A96: Hesperia USD | B96: Kingston ES | C96: Sandra | D96: 11553 | E96: 280655 | F96: (2) 24'X40' | G96: 4 | H96: 45596 | I96: Approved | J96: Yes | L96: 1 | M96: PB | N96: 45765 | R96: Gino | S96: =IFERROR(E96*L96,0) -> 280655
A97: Hesperia USD | B97: Carmel ES | C97: Sandra | D97: 11547 | E97: 420981.5 | F97: (3) 24'x40' | G97: 6 | H97: 45602 | I97: Approved | J97: Yes | L97: 1 | M97: PB | N97: 45709 | R97: Gino | S97: =IFERROR(E97*L97,0) -> 420981.5
A98: Hesperia USD | B98: Lime Street | C98: Sandra | D98: 11555 | E98: 420981.5 | F98: (3) 24'x40' | G98: 6 | H98: 45603 | I98: Approved | J98: Yes | L98: 1 | M98: PB | N98: 45748 | R98: Gino | S98: =IFERROR(E98*L98,0) -> 420981.5
A99: Granada Hills Charter | B99: Granada Hills | C99: Sandra | D99: 11557 | E99: 23747788 | F99: 3-story Classroom + MPR | G99: 106 | H99: 45628 | I99: HCD Approved (In review at LADBS) | J99: Yes | K99: In Engineering- Working on Project Release | L99: 1 | M99: Negotiated | N99: Summer 2025 | O99: Yes | P99: No | Q99: Yes | R99: Mehdi | S99: =IFERROR(E99*L99,0) -> 23747788
A100: Apple Valley USD | B100: Desert Knolls ES | C100: Sandra | D100: 11487 | E100: 1444491.4 | F100: (2) 72X40 | G100: 12 | H100: 45637 | I100: Approved | J100: Won bid | L100: 1 | M100: Bid | N100: 45809 | R100: Gino | S100: =IFERROR(E100*L100,0) -> 1444491.4 | T100: TBD
...

Sheet Closed Deals 25
A1: SCM Sales Pipeline 2025
A2: Customer | B2: Project Name | C2: BDM | D2: Job Number | E2: Contract Value | F2: Building(s) | G2: Floor(s) | H2: Start Date for Production | I2: District Occupancy Date | J2: Confidence Level | K2: Current Status/Notes | L2: Contract Type | M2: Bid Piggyback | N2: Most Recent Proposal (Date) | O2: Job Release [BDM & DH] (Date) | P2: Engineering Release [BDM & Engineer] (Date) | Q2: Hand-off Meeting [BDM & PM] (Date) | R2: Kick-off Meeting [PM & ALL Depts] (Date) | S2: PM | T2: Estimated Value | U2: Estimated DSA Approval (per Engineering) | V2: Quarter | W2: Edited
A3: Apple Valley USD | B3: Sandia Academy | C3: Diana | D3: 11488 | E3: 1444491.4 | F3: (2) 72X40 | G3: 12 | H3: 45664 | I3: 45810 | J3: 1 | L3: Yes | M3: BID | R3: TBD | S3: Gino | T3: =IFERROR(E3*J3,0) -> 1444491.4 | U3: Approved | V3: =IFERROR(ROUNDUP(MONTH(IF(H3<>"",H3,""))/3, 0),"TBD") -> 1 | W3: =IF(I3<>"",IF(W3="",NOW(),W3),"") -> 45692.547
A4: Lancaster SD | B4: Lincoln Elementary | C4: Sandra | D4: 11520 | E4: 112000 | F4: 8'6" x 21'-6" RR | G4: 1 | H4: 45672 | I4: 45823 | J4: 1 | K4: Project Completed | L4: PO | M4: PB | N4: Yes | O4: No | P4: No | S4: Gino | T4: =IFERROR(E4*J4,0) -> 112000 | U4: Approved | V4: =IFERROR(ROUNDUP(MONTH(IF(H4<>"",H4,""))/3, 0),"TBD") -> 1 | W4: =IF(I4<>"",IF(W4="",NOW(),W4),"") -> 45813.652
A5: Fountain Valley SD | B5: Oka ES | C5: Sandra | D5: 11530 | E5: 262487.93 | F5: (1) 48'x40' | G5: 4 | H5: 45673 | I5: 45823 | J5: 1 | K5: Delivered and Completed | L5: Yes | M5: PB | O5: Yes | S5: Moanes | T5: =IFERROR(E5*J5,0) -> 262487.93 | U5: Approved | V5: =IFERROR(ROUNDUP(MONTH(IF(H5<>"",H5,""))/3, 0),"TBD") -> 1 | W5: =IF(I5<>"",IF(W5="",NOW(),W5),"") -> 45692.547
A6: Fountain Valley SD | B6: Newland ES | C6: Sandra | D6: 11529 | E6: 138298.63 | F6: (1) 24'X40' | G6: 2 | H6: 45678 | I6: 45823 | J6: 1 | K6: Delivered and Completed | L6: Yes | M6: PB | O6: Yes | S6: Moanes | T6: =IFERROR(E6*J6,0) -> 138298.63 | U6: Approved | V6: =IFERROR(ROUNDUP(MONTH(IF(H6<>"",H6,""))/3, 0),"TBD") -> 1 | W6: =IF(I6<>"",IF(W6="",NOW(),W6),"") -> 45692.547
A7: Apple Valley USD | B7: Yucca Loma ES | C7: Sandra | D7: 11489 | E7: 1444491.4 | F7: (2) 72X40 | G7: 12 | H7: 45679 | I7: 45811 | J7: 1 | K7: Delivery March 3/4/25 | L7: Yes | M7: Bid | R7: TBD | S7: Gino | T7: =IFERROR(E7*J7,0) -> 1444491.4 | U7: Approved | V7: =IFERROR(ROUNDUP(MONTH(IF(H7<>"",H7,""))/3, 0),"TBD") -> 1 | W7: =IF(I7<>"",IF(W7="",NOW(),W7),"") -> 45692.547
A8: Fountain Valley SD | B8: Plavan ES | C8: Sandra | D8: 11528 | E8: 260370.01 | F8: (1) 48'x40' | G8: 4 | H8: 45680 | I8: 45823 | J8: 1 | L8: Yes | M8: PB | O8: Yes | S8: Moanes | T8: =IFERROR(E8*J8,0) -> 260370.01 | U8: Approved | V8: =IFERROR(ROUNDUP(MONTH(IF(H8<>"",H8,""))/3, 0),"TBD") -> 1 | W8: =IF(I8<>"",IF(W8="",NOW(),W8),"") -> 45692.547
A9: Torrance USD | B9: Torrance ES | C9: Sandra | D9: 11501 | E9: 2448024.2 | F9: (1) 168'x40' | G9: 14 | H9: 45685 | I9: 45901 | J9: 1 | K9: Bldg Onsite | L9: PO | M9: PB | O9: Yes | P9: Yes | S9: Moanes | T9: =IFERROR(E9*J9,0) -> 2448024.2 | U9: Approved | V9: =IFERROR(ROUNDUP(MONTH(IF(H9<>"",H9,""))/3, 0),"TBD") -> 1 | W9: =IF(I9<>"",IF(W9="",NOW(),W9),"") -> 45692.547
A10: Modesto CS | B10: Beyer HS | C10: Joe | D10: 11574 | E10: 246171.81 | F10: (1) 12x40 RR Model C-2 | G10: 1 | H10: 45694 | I10: 45778 | J10: 1 | K10: DSA approved on 11/8/2024 Boyer has been hired by District as GC | L10: PO 251803 | M10: PB | N10: 45551 | O10: 45553 | P10: Yes | S10: Joe | T10: =IFERROR(E10*J10,0) -> 246171.81 | U10: Approved | V10: =IFERROR(ROUNDUP(MONTH(IF(H10<>"",H10,""))/3, 0),"TBD") -> 1 | W10: =IF(I10<>"",IF(W10="",NOW(),W10),"") -> 45692.547
A11: Rio Hondo College | B11: Fire Academy | C11: Sandra | D11: 11442 | E11: 227900.33 | F11: 24x60 Classroom & Office | G11: 2 | H11: 45694 | I11: 45777 | J11: 1 | K11: Bldg Onsite | L11: PO1-230000002430 | O11: Yes | P11: Yes | S11: Moanes | T11: =IFERROR(E11*J11,0) -> 227900.33 | U11: Approved | V11: =IFERROR(ROUNDUP(MONTH(IF(H11<>"",H11,""))/3, 0),"TBD") -> 1 | W11: =IF(I11<>"",IF(W11="",NOW(),W11),"") -> 45692.547
A12: Corona Norco USD | B12: Harada ES | C12: Sandra | D12: 11558 | E12: 998332 | F12: (3) 36x40 | G12: 9 | H12: 45695 | I12: 45768 | J12: 1 | K12: Bldg Onsite | L12: Yes | M12: Bid | R12: TBD | S12: Gino | T12: =IFERROR(E12*J12,0) -> 998332 | U12: Approved | V12: =IFERROR(ROUNDUP(MONTH(IF(H12<>"",H12,""))/3, 0),"TBD") -> 1 | W12: =IF(I12<>"",IF(W12="",NOW(),W12),"") -> 45692.547
A13: Vineland SD | B13: Vineland ES | C13: Joe | D13: 11502 | E13: 3006336.8 | F13: (7) 36X40 Pre-K, TK, Kinder CR | G13: 21 | H13: 45702 | I13: 45812 | J13: 1 | K13: DSA approved 12/4/2024 6 calendar months for delivery after DSA approval | L13: PO 240532 | M13: Bid | N13: Bid | O13: 45383 | P13: Yes | S13: Kenny | T13: =IFERROR(E13*J13,0) -> 3006336.8 | U13: Approved | V13: =IFERROR(ROUNDUP(MONTH(IF(H13<>"",H13,""))/3, 0),"TBD") -> 1 | W13: =IF(I13<>"",IF(W13="",NOW(),W13),"") -> 45692.547
A14: Corona Norco USD | B14: Temescal ES | C14: Sandra | D14: 11559 | E14: 332944 | F14: (1) 36x40 | G14: 3 | H14: 45706 | I14: 45778 | J14: 1 | K14: Bldg Onsite | L14: Yes | M14: Bid | R14: TBD | S14: Gino | T14: =IFERROR(E14*J14,0) -> 332944 | U14: Approved | V14: =IFERROR(ROUNDUP(MONTH(IF(H14<>"",H14,""))/3, 0),"TBD") -> 1 | W14: =IF(I14<>"",IF(W14="",NOW(),W14),"") -> 45692.547
A15: Corona Norco USD | B15: Jefferson ES | C15: Sandra | D15: 11560 | E15: 792600 | F15: (4) 30x32 | G15: 12 | H15: 45709 | I15: 45743 | J15: 1 | K15: Bldg Onsite | L15: Yes | M15: Bid | S15: Gino | T15: =IFERROR(E15*J15,0) -> 792600 | U15: Approved | V15: =IFERROR(ROUNDUP(MONTH(IF(H15<>"",H15,""))/3, 0),"TBD") -> 1 | W15: =IF(I15<>"",IF(W15="",NOW(),W15),"") -> 45692.547
A16: Cajon Valley USD | B16: Meridian ES | C16: Diana | D16: 11519 | E16: 199336 | F16: (1) 12'x40' Restroom Bldg. Model C-2 | G16: 1 | H16: 45723 | I16: 45839 | J16: 1 | K16: No site dates available | L16: PO 12500433 | M16: PB | S16: Gino | T16: =IFERROR(E16*J16,0) -> 199336 | U16: Approved | V16: =IFERROR(ROUNDUP(MONTH(IF(H16<>"",H16,""))/3, 0),"TBD") -> 1 | W16: =IF(I16<>"",IF(W16="",NOW(),W16),"") -> 45692.547
A17: Menifee USD | B17: Hans Christensen ES | C17: Diana | D17: 11588 | E17: 3084567.3 | F17: 180’x40’ TK | G17: 15 | H17: 45726 | I17: 45838 | J17: 1 | L17: Agreement received 12/24 | M17: Bid | R17: TBD | S17: Kenny | T17: =IFERROR(E17*J17,0) -> 3084567.3 | U17: Approved | V17: =IFERROR(ROUNDUP(MONTH(IF(H17<>"",H17,""))/3, 0),"TBD") -> 1 | W17: =IF(I17<>"",IF(W17="",NOW(),W17),"") -> 45692.547
A18: Hesperia USD | B18: Mesa Grande ES | C18: Sandra | D18: 11435 | E18: 817329 | F18: 72X40 TK | G18: 6 | H18: 45727 | I18: 45869 | J18: 1 | L18: Yes | M18: PB | O18: Yes | P18: Yes | R18: TBD | S18: Gino | T18: =IFERROR(E18*J18,0) -> 817329 | U18: Approved | V18: =IFERROR(ROUNDUP(MONTH(IF(H18<>"",H18,""))/3, 0),"TBD") -> 1 | W18: =IF(I18<>"",IF(W18="",NOW(),W18),"") -> 45692.547
A19: Claremont USD | B19: Claremont HS | C19: Sandra | D19: 11507 | E19: 191440 | F19: (1) 24x40 Softball Clubhouse | G19: 2 | H19: 45734 | I19: 45869 | J19: 1 | L19: Contract | M19: Bid | O19: Yes | P19: Yes | S19: Gino | T19: =IFERROR(E19*J19,0) -> 191440 | U19: Approved | V19: =IFERROR(ROUNDUP(MONTH(IF(H19<>"",H19,""))/3, 0),"TBD") -> 1 | W19: =IF(I19<>"",IF(W19="",NOW(),W19),"") -> 45692.547
A20: Hesperia USD | B20: Hollyvale ES | C20: Sandra | D20: 11546 | E20: 420981.5 | F20: (3) 24'x40' | G20: 6 | H20: 45736 | I20: 45869 | J20: 1 | L20: Yes | M20: PB | P20: Yes | S20: Gino | T20: =IFERROR(E20*J20,0) -> 420981.5 | U20: Approved | V20: =IFERROR(ROUNDUP(MONTH(IF(H20<>"",H20,""))/3, 0),"TBD") -> 1 | W20: =IF(I20<>"",IF(W20="",NOW(),W20),"") -> 45692.547
A21: El Centro Elementary | B21: Harding ES | C21: Diana | D21: 11534 | E21: =2593846+94353+98291+29908 -> 2816398 | F21: 108x80 | G21: 18 | H21: 45742 | I21: 45717 | J21: 1 | L21: Yes | M21: Bid | N21: No | O21: Yes | P21: Yes | R21: TBD | S21: Kenny | T21: =IFERROR(E21*J21,0) -> 2816398 | U21: Approved | V21: =IFERROR(ROUNDUP(MONTH(IF(H21<>"",H21,""))/3, 0),"TBD") -> 1 | W21: =IF(I21<>"",IF(W21="",NOW(),W21),"") -> 45692.547
A22: Guadalupe USD | B22: Pasadera Early Childhood Education Center | C22: Joe | D22: 11525 | E22: =21480+1325654.33+294577 -> 1641711.3 | F22: (1) 84x40 Admin Bldg | G22: 7 | H22: 45742 | I22: 45839 | J22: 1 | K22: DSA APPROVED. PO for building received 2/10 | L22: PO 25-00045 (D+E) PO 25-00327 (BUILDING) | M22: Bid | N22: Bid | O22: 45482 | P22: 45476 | S22: Kenny | T22: =IFERROR(E22*J22,0) -> 1641711.3 | U22: Approved | V22: =IFERROR(ROUNDUP(MONTH(IF(H22<>"",H22,""))/3, 0),"TBD") -> 1 | W22: =IF(I22<>"",IF(W22="",NOW(),W22),"") -> 45692.547
A23: Hesperia USD | B23: Mesa Grande | C23: Sandra | D23: 11552 | E23: 623161 | F23: (2) 24'X40' (1) 12'x40' RR | G23: 5 | H23: 45749 | I23: 45869 | J23: 1 | L23: Yes | M23: PB | P23: Yes | S23: Gino | T23: =IFERROR(E23*J23,0) -> 623161 | U23: Approved | V23: =IFERROR(ROUNDUP(MONTH(IF(H23<>"",H23,""))/3, 0),"TBD") -> 2 | W23: =IF(I23<>"",IF(W23="",NOW(),W23),"") -> 45692.547
A24: Hesperia USD | B24: Mesa Grande ES | C24: Sandra | D24: 11616 | E24: 152362 | F24: (1) 24x40 CR | G24: 2 | H24: 45754 | I24: 45869 | J24: 1 | L24: Yes
A25: Beaumont USD | B25: Beaumont Adult School | C25: Diana | D25: 11506 | E25: 1420634.9 | F25: (1) 36x40, (4) 24x40, (1) 12x40 | G25: 12 | H25: 45756 | I25: 45748 | J25: 1 | K25: Monique is finalizing submittals | L25: Contract | M25: PB | N25: 45461 | O25: Yes | P25: 45413 | S25: Gino | T25: =IFERROR(E25*J25,0) -> 1420634.9 | U25: Approved | V25: =IFERROR(ROUNDUP(MONTH(IF(H25<>"",H25,""))/3, 0),"TBD") -> 2 | W25: =IF(I25<>"",IF(W25="",NOW(),W25),"") -> 45692.547
A26: Romoland SD | B26: Ethan Chase MS | C26: Diana | D26: 11604 | E26: 316914.98 | F26: (2) 24'x40' Classrooms | G26: 4 | H26: 45758 | I26: 45809 | J26: 1 | K26: Pending completion of stockpile fees. Customer taking to the board on 2/6. 2/14 - NOI received. | L26: PO-C100672 | M26: PB | N26: 45679 | O26: Yes | P26: Yes | Q26: TBD - PM | R26: TBD - PM | U26: Approved
A27: Romoland SD | B27: Romoland ES | C27: Diana | D27: 11601 | E27: 495340.6 | F27: (2) 24'x40' Classrooms, (1) 12'x40' Model C-2 restroom | G27: 5 | H27: 45768 | I27: 45809 | J27: 1 | K27: Pending completion of stockpile fees. Customer taking to the board on 2/6. 2/14 - NOI received. | L27: PO-100671/72/733 | M27: PB | N27: 45679 | O27: TBD - PM | P27: Yes | Q27: TBD - PM | R27: TBD - PM | S27: Kenny | T27: =IFERROR(E27*J27,0) -> 495340.6 | U27: Approved | V27: =IFERROR(ROUNDUP(MONTH(IF(H27<>"",H27,""))/3, 0),"TBD") -> 2 | W27: =IF(I27<>"",IF(W27="",NOW(),W27),"") -> 45692.547
A28: Romoland SD | B28: Harvest Valley ES | C28: Diana | D28: 11602 | E28: 316914.98 | F28: (2) 24'x40' Classrooms | G28: 4 | H28: 45768 | I28: 45809 | J28: 1 | K28: Pending completion of stockpile fees. Customer taking to the board on 2/6. 2/14 - NOI received. | L28: PO-1000671/72 | M28: PB | N28: 45679 | O28: TBD - PM | P28: Yes | Q28: TBD - PM | R28: TBD - PM | U28: Approved
A29: Romoland SD | B29: Mesa View ES | C29: Diana | D29: 11603 | E29: 316914.98 | F29: (2) 24'x40' Classrooms | G29: 4 | H29: 45768 | I29: 45809 | J29: 1 | K29: Pending completion of stockpile fees. Customer taking to the board on 2/6. 2/14 - NOI received. | L29: PO-1000671/72 | M29: PB | N29: 45679 | O29: TBD - PM | P29: Yes | Q29: TBD - PM | R29: TBD - PM | U29: Approved
A30: Walnut Valley USD | B30: Collegewood | C30: Sandra | D30: 11579 | E30: 603711.04 | F30: (3) 24x40 | G30: 6 | H30: 45771 | I30: 45922 | J30: 1 | L30: PO | M30: PB | N30: Yes | O30: No | P30: No | S30: Moanes | T30: =IFERROR(E30*J30,0) -> 603711.04 | U30: Approved | V30: =IFERROR(ROUNDUP(MONTH(IF(H30<>"",H30,""))/3, 0),"TBD") -> 2 | W30: =IF(I30<>"",IF(W30="",NOW(),W30),"") -> 45692.547
A31: San Bernardino County | B31: Colton | C31: Sandra | D31: 11593 | E31: 1565922.8 | F31: 83-6x36 Special Needs | G31: 6 | H31: 45771 | I31: 45870 | J31: 1 | K31: Bldg Shipping week of 6/2/25 | L31: Contract | M31: Bid | N31: Yes | O31: Yes | P31: Yes | S31: Gino | T31: =IFERROR(E31*J31,0) -> 1565922.8 | U31: Approved | V31: =IFERROR(ROUNDUP(MONTH(IF(H31<>"",H31,""))/3, 0),"TBD") -> 2 | W31: =IF(I31<>"",IF(W31="",NOW(),W31),"") -> 45692.547
A32: Garvey USD | B32: Emerson ES | C32: Sandra | D32: 11586 | E32: 244043 | F32: (1) 24x40 Daycare | G32: 2 | H32: 45778 | I32: 45838 | J32: 1 | K32: Being Delivered week of 6/2/25 | L32: PO | M32: PB | O32: Yes | S32: Moanes | T32: =IFERROR(E32*J32,0) -> 244043 | U32: Approved | V32: =IFERROR(ROUNDUP(MONTH(IF(H32<>"",H32,""))/3, 0),"TBD") -> 2 | W32: =IF(I32<>"",IF(W32="",NOW(),W32),"") -> 45692.547
A33: Norris SD | B33: Veterans ES | C33: Joe | D33: 11533 | E33: 1196120 | F33: (1) 108X40 TK | G33: 9 | H33: 45782 | I33: 45870 | J33: 1 | K33: DSA approved and box is open | L33: Construction Agreement 6/13/2024 | M33: Bid | N33: Bid | O33: 45484 | P33: 45511 | S33: Kenny | T33: =IFERROR(E33*J33,0) -> 1196120 | U33: Approved | V33: =IFERROR(ROUNDUP(MONTH(IF(H33<>"",H33,""))/3, 0),"TBD") -> 2 | W33: =IF(I33<>"",IF(W33="",NOW(),W33),"") -> 45692.547
A34: Norris SD | B34: Olive Drive ES | C34: Joe | D34: 11539 | E34: 847983.87 | F34: (1) 72X40 TK | G34: 6 | H34: 45783 | I34: 45870 | J34: 1 | K34: DSA approved | L34: Construction Agreement 6/13/2024 | M34: Bid | N34: Bid | O34: 45484 | P34: 45511 | S34: Kenny | T34: =IFERROR(E34*J34,0) -> 847983.87 | U34: Approved | V34: =IFERROR(ROUNDUP(MONTH(IF(H34<>"",H34,""))/3, 0),"TBD") -> 2 | W34: =IF(I34<>"",IF(W34="",NOW(),W34),"") -> 45692.547
A35: Marina Landscape | B35: Jesse Brewer Park | C35: Sandra | D35: 11615 | E35: 320036.44 | F35: 12x40 Toilet Building | G35: 1 | H35: 45790 | I35: 45870 | J35: 1 | K35: Bldg Delivered | L35: Yes | T35: =IFERROR(E35*J35,0) -> 320036.44 | U35: Approved | V35: =IFERROR(ROUNDUP(MONTH(IF(H35<>"",H35,""))/3, 0),"TBD") -> 2 | W35: =IF(I35<>"",IF(W35="",NOW(),W35),"") -> 45692.547
A36: Walnut Valley USD | B36: Maple Hills ES | C36: Sandra | D36: 11580 | E36: 963241.27 | F36: (4) 24X40 (1) 12x40 | G36: 9 | H36: 45791 | I36: 45922 | J36: 1 | L36: PO | M36: PB | N36: Yes | O36: No | P36: No | S36: Moanes | T36: =IFERROR(E36*J36,0) -> 963241.27 | U36: Approved | V36: =IFERROR(ROUNDUP(MONTH(IF(H36<>"",H36,""))/3, 0),"TBD") -> 2 | W36: =IF(I36<>"",IF(W36="",NOW(),W36),"") -> 45692.547
A37: Stanislaus USD | B37: Dieterich ES | C37: Joe | D37: 11614 | E37: 254338 | F37: (1) 24x40 ELOP CR Bldg | G37: 2 | H37: 45792 | I37: 45838 | J37: 1 | K37: DSA approved | L37: Signed Agreement | M37: Negotiated | N37: 45737 | O37: 45757 | P37: 45743 | Q37: 45757 | R37: 45778 | S37: Kenny | T37: =IFERROR(E37*J37,0) -> 254338 | U37: Approved
A38: Stanislaus USD | B38: Chrysler ES | C38: Joe | D38: 11613 | E38: 254338 | F38: (1) 24x40 ELOP CR Bldg | G38: 2 | H38: 45796 | I38: 45838 | J38: 1 | K38: DSA approved | L38: Signed Agreement | M38: Negotiated | N38: 45737 | O38: 45757 | P38: 45743 | Q38: 45757 | R38: 45778 | S38: Kenny | T38: =IFERROR(E38*J38,0) -> 254338 | U38: Approved
A39: Stanislaus USD | B39: Baptist ES | C39: Joe | D39: 11612 | E39: 254338 | F39: (1) 24x40 ELOP CR Bldg | G39: 2 | H39: 45797 | I39: 45838 | J39: 1 | K39: DSA approved | L39: Signed Agreement | M39: Negotiated | N39: 45737 | O39: 45757 | P39: 45743 | Q39: 45757 | R39: 45778 | S39: Kenny | T39: =IFERROR(E39*J39,0) -> 254338 | U39: Approved
A40: Calexico USD | B40: Kennedy ES | C40: Diana | D40: 11535 | E40: 728293 | F40: (1) 48x40 TK Classroom | G40: 4 | H40: 45799 | I40: 45839 | J40: 1 | K40: In Engineering, AOR is changing to OTC project | L40: Yes | M40: Bid | N40: N/A | O40: Yes | P40: 45449 | S40: Kenny | T40: =IFERROR(E40*J40,0) -> 728293 | U40: Approved | V40: =IFERROR(ROUNDUP(MONTH(IF(H40<>"",H40,""))/3, 0),"TBD") -> 2 | W40: =IF(I40<>"",IF(W40="",NOW(),W40),"") -> 45692.547
A41: Briggs ESD | B41: Olivelands ES | C41: Joe | D41: 11527 | E41: 865637.29 | F41: (1) 72x40 TK | G41: 6 | H41: 45800 | I41: 45901 | J41: 1 | K41: DSA submission on 1/7/2025 DSA comments 2/19 | L41: Contract Agreement | M41: Bid | N41: Bid | O41: 45482 | P41: 45499 | S41: Kenny | T41: =IFERROR(E41*J41,0) -> 865637.29 | U41: Approved | V41: =IFERROR(ROUNDUP(MONTH(IF(H41<>"",H41,""))/3, 0),"TBD") -> 2 | W41: =IF(I41<>"",IF(W41="",NOW(),W41),"") -> 45692.547
A42: Menifee USD | B42: Hans Christensen ES | C42: Diana | D42: 11588 | E42: 244569.11 | F42: (1) 12'x40' Restroom Building | G42: 1 | H42: 45804 | I42: 45839 | J42: 1 | K42: Project being negotiated with GC and District. Should be finalized by end of January. Architect submitting to DSA March, 2025. Drawings were sent to the architect on Friday 3/21. | L42: Yes | M42: BID | N42: 45772 | O42: Yes | P42: 45658 | Q42: Yes | R42: Yes | S42: Kenny | T42: =IFERROR(E42*J42,0) -> 244569.11 | U42: Approved | V42: =IFERROR(ROUNDUP(MONTH(IF(H42<>"",H42,""))/3, 0),"TBD") -> 2 | W42: =IF(I42<>"",IF(W42="",NOW(),W42),"") -> 45692.547
A43: Hesperia USD | B43: Joshua Circle ES | C43: Sandra | D43: 11550 | E43: 280655 | F43: (2) 24'X40' | G43: 4 | H43: 45805 | I43: 45900 | J43: 1 | K43: Back Check | L43: Yes | M43: PB | P43: Yes | S43: Gino | T43: =IFERROR(E43*J43,0) -> 280655 | U43: Approved | V43: =IFERROR(ROUNDUP(MONTH(IF(H43<>"",H43,""))/3, 0),"TBD") -> 2 | W43: =IF(I43<>"",IF(W43="",NOW(),W43),"") -> 45692.547
A44: Hesperia USD | B44: Juniper ES | C44: Sandra | D44: 11619 | E44: 828966.58 | F44: (3) 24x40 & (1) C RR | G44: 7 | H44: 45805 | I44: 45900 | J44: 1 | L44: PO 253273 | M44: PB | P44: Yes | S44: Gino | T44: =IFERROR(E44*J44,0) -> 828966.58 | U44: Approved | V44: =IFERROR(ROUNDUP(MONTH(IF(H44<>"",H44,""))/3, 0),"TBD") -> 2 | W44: =IF(I44<>"",IF(W44="",NOW(),W44),"") -> 45692.547
A45: Hesperia USD | B45: Joshua Circle ES | C45: Sandra | D45: 11623 | E45: 152362 | F45: (1) 24x40 CR | G45: 2 | H45: 45810 | I45: 45900 | J45: 1 | L45: PO 253274
A46: Vista USD | B46: Vista Magnet MS | C46: Diana | D46: 11605 | E46: 153956.79 | F46: (1) 24'x40' CR | G46: 2 | H46: 45811 | I46: 46009 | J46: 1 | K46: DSA Appointment will be OTC and will be scheduled on 2/6 but AOR is anticipating DSA issuing the appoint for 7 days after. Board approval of our proposal will also take place on 2/6. Received signed proposal. In DSA. 3.25.25 - DSA approved. Customer has requested 6/5 delivery. | L46: PO-0000069807_05100 | M46: PB | S46: Kenny | T46: =IFERROR(E46*J46,0) -> 153956.79 | U46: Approved | V46: =IFERROR(ROUNDUP(MONTH(IF(H46<>"",H46,""))/3, 0),"TBD") -> 2 | W46: =IF(I46<>"",IF(W46="",NOW(),W46),"") -> 45692.547
A47: Hesperia USD | B47: Juniper ES | C47: Sandra | D47: 11551 | E47: 280655 | F47: (2) 24'X40' | G47: 4 | H47: 45811 | I47: 45900 | J47: 1 | L47: Yes | M47: PB | P47: Yes | S47: Gino | T47: =IFERROR(E47*J47,0) -> 280655 | U47: Approved | V47: =IFERROR(ROUNDUP(MONTH(IF(H47<>"",H47,""))/3, 0),"TBD") -> 2 | W47: =IF(I47<>"",IF(W47="",NOW(),W47),"") -> 45692.547
A48: Torrance USD | B48: Carr ES | C48: Sandra | D48: 11500 | E48: 2392640.9 | F48: (1) 168'x40' | G48: 14 | H48: 45812 | I48: 45962 | J48: 1 | K48: Production | L48: PO 24-05409-M | M48: PB | P48: Yes | R48: TBD | S48: Moanes | T48: =IFERROR(E48*J48,0) -> 2392640.9 | U48: Approved | V48: =IFERROR(ROUNDUP(MONTH(IF(H48<>"",H48,""))/3, 0),"TBD") -> 2 | W48: =IF(I48<>"",IF(W48="",NOW(),W48),"") -> 45692.547
A49: Hesperia USD | B49: Kingston ES | C49: Sandra | D49: 11622 | E49: 152362 | F49: (1) 24x40 CR | G49: 2 | H49: 45813 | I49: 45900 | J49: 1 | L49: Yes
A50: Hesperia USD | B50: Krystal ES | C50: Sandra | D50: 11621 | E50: 171547.96 | F50: (1) 24x40 CR W/Sprinklers | G50: 2 | H50: 45814 | I50: 45900 | J50: 1 | L50: Yes | U50: Approved
A51: Palm Springs USD | B51: Bella Vista ES | C51: Diana | D51: 11564 | E51: 621295.64 | F51: 8’-6” x 16’-7” RR (2) 36'x40’ TK Classroom | G51: 7 | H51: 45817 | I51: 45874 | J51: 1 | K51: This is priority site, customer would like delivery by 6/24 and completion by 7/17/25. | L51: PO - C-0005213 | M51: PB | N51: Pending Adel Release | O51: No | P51: No | R51: TBD | S51: Gino | T51: =IFERROR(E51*J51,0) -> 621295.64 | U51: Approved (Pending CCD Approval for restroom) | V51: =IFERROR(ROUNDUP(MONTH(IF(H51<>"",H51,""))/3, 0),"TBD") -> 2 | W51: =IF(I51<>"",IF(W51="",NOW(),W51),"") -> 45692.547
A52: Palm Springs USD | B52: Cabot Yerxa ES | C52: Diana | D52: 11521 | E52: 713569.32 | F52: 8’-6” x 16’-7” RR, (1) 36’x40’ TK Classroom, (1) 24'x40' Classroom | G52: 6 | H52: 45818 | I52: 45877 | J52: 1 | K52: This is priority site, customer would like the delivery of the 24'x40' building by 7/15 and the 36'x40' & RR by 8/4. | L52: PO - C-0005215 | M52: PB | N52: Pending Adel Release | O52: No | P52: Yes | R52: TBD | S52: Gino | T52: =IFERROR(E52*J52,0) -> 713569.32 | U52: Approved (Pending CCD Approval for restroom) | V52: =IFERROR(ROUNDUP(MONTH(IF(H52<>"",H52,""))/3, 0),"TBD") -> 2 | W52: =IF(I52<>"",IF(W52="",NOW(),W52),"") -> 45841.57
A53: East Whittier SD | B53: Scott Ave ES | C53: Sandra | D53: 11611 | E53: 159382.02 | F53: (1) 12x40 Toilet | G53: 1 | H53: 45821 | I53: 45880 | J53: 1 | K53: DSA Approved | L53: PO | U53: Approved
A54: East Whittier SD | B54: Ocean View ES | C54: Sandra | D54: 11590 | E54: 157449.02 | F54: (1) 12x40 Toilet | G54: 1 | H54: 45824 | I54: 45880 | J54: 1 | K54: DSA Approved | L54: PO | M54: PB | O54: Yes | S54: Moanes | T54: =IFERROR(E54*J54,0) -> 157449.02 | U54: Approved | V54: =IFERROR(ROUNDUP(MONTH(IF(H54<>"",H54,""))/3, 0),"TBD") -> 2 | W54: =IF(I54<>"",IF(W54="",NOW(),W54),"") -> 45692.547
A55: Colton USD | B55: Colton MS | C55: Sandra | D55: 11606 | E55: 160087 | F55: (1) 24x40 CR w/RR | G55: 2 | H55: 45825 | I55: 45894 | J55: 1 | K55: Customer has not finalized site contractor. We are working | L55: PO 256614 | U55: Approved
A56: Helendale SD | B56: ACE/RMS | C56: Sandra | D56: 11505 | E56: 479820.52 | F56: 48x40 Weight Room | G56: 4 | H56: 45825 | I56: 45964 | J56: 1 | K56: Waiting on CCD approval for ceiling height change ans submittals | L56: PO 250634 | O56: Yes | P56: Yes | R56: TBD | S56: Gino | T56: =IFERROR(E56*J56,0) -> 479820.52 | U56: Approved | V56: =IFERROR(ROUNDUP(MONTH(IF(H56<>"",H56,""))/3, 0),"TBD") -> 2 | W56: =IF(I56<>"",IF(W56="",NOW(),W56),"") -> 45692.547
A57: Palm Springs USD | B57: Cathedral City ES | C57: Diana | D57: 11561 | E57: 831305.99 | F57: 8’-6” x 32’-7” RR (2) 36’x40’ TK Classroom | G57: 7 | H57: 45827 | I57: 45923 | J57: 1 | K57: This is priority site, customer would like delivery of the two 36'x40' classrooms by 9/5 and RR by 9/10. | L57: PO -C-0005212 | M57: PB | N57: Pending Adel Release | O57: No | P57: No | S57: Gino | T57: =IFERROR(E57*J57,0) -> 831305.99 | U57: Approved (Pending CCD Approval for restroom) | V57: =IFERROR(ROUNDUP(MONTH(IF(H57<>"",H57,""))/3, 0),"TBD") -> 2 | W57: =IF(I57<>"",IF(W57="",NOW(),W57),"") -> 45692.547
A58: Beaumont USD | B58: Summerwind Trails School | C58: Diana | D58: 11607 | E58: 637823.27 | F58: (1) 48'x40' (1) 24'x40' CR, (1) 12'x40' RR Bldg. | G58: 7 | H58: 45828 | I58: 45870 | J58: 1 | K58: GC working on updating the schedule. True occupancy date TBD. Push up in manufacturing ASAP | L58: Signed Agreement | M58: PB | N58: 45709 | O58: No | P58: 45735 | S58: Gino | T58: =IFERROR(E58*J58,0) -> 637823.27 | U58: Approved | V58: =IFERROR(ROUNDUP(MONTH(IF(H58<>"",H58,""))/3, 0),"TBD") -> 2 | W58: =IF(I58<>"",IF(W58="",NOW(),W58),"") -> 45692.547
A59: Norwalk La Mirada USD | B59: Hutchinson MS | C59: Sandra | D59: 11517 | E59: 2244195.3 | F59: 72x48 | G59: 6 | H59: 45831 | I59: 46020 | J59: 1 | K59: In production delivery late Septemeber | L59: Yes | M59: PB | N59: Yes | O59: Yes | P59: Yes | R59: TBD | S59: Moanes | T59: =IFERROR(E59*J59,0) -> 2244195.3 | U59: Approved | V59: =IFERROR(ROUNDUP(MONTH(IF(H59<>"",H59,""))/3, 0),"TBD") -> 2 | W59: =IF(I59<>"",IF(W59="",NOW(),W59),"") -> 45692.547
A60: Beaumont USD | B60: Mountain View MS | C60: Diana | D60: 11609 | E60: 783895.41 | F60: (2) 48'x40' CRs, (1) 12'x40' RR Bldg. | G60: 9 | H60: 45835 | I60: 45898 | J60: 1 | K60: GC working on updating the schedule. True occupancy date TBD. Push up in manufacturing ASAP | L60: C-0012789 | M60: PB | N60: 45709 | O60: No | P60: 45735 | T60: =IFERROR(E60*J60,0) -> 783895.41 | U60: Approved | W60: =IF(I60<>"",IF(W60="",NOW(),W60),"") -> 45692.547
A61: WillScot | B61: Stockpile #1 Restrooms | C61: Diana | D61: 11626 | E61: 1867762.7 | F61: 12'x40' Restroom Buildings Model C-2 | G61: 12 | H61: 45838 | I61: 45839 | J61: 1 | K61: FOB SCM Gate per the following schedule 1ea. 7/1, 1ea. July/Aug., 1ea. Aug., 9ea. Fall 2025 | L61: PO | M61: Negotiated | N61: 45807 | O61: No | P61: Stockpile | U61: Approved
A62: Silver Valley | B62: Silver Valley Health Center | C62: Sandra | D62: 11523 | E62: 408151 | F62: (1) 36x40 Office Bldg | G62: 3 | H62: 45841 | I62: 45936 | J62: 1 | K62: Pending Submittals | L62: PO 250846 | S62: Gino | T62: =IFERROR(E62*J62,0) -> 408151 | U62: Approved | V62: =IFERROR(ROUNDUP(MONTH(IF(H62<>"",H62,""))/3, 0),"TBD") -> 3 | W62: =IF(I62<>"",IF(W62="",NOW(),W62),"") -> 45692.547
A63: Lawndale | B63: Anderson ES | C63: Sandra | D63: 11583 | E63: 320391 | F63: (1) 40x32 Headstart Classroom | G63: 4 | H63: 45846 | I63: 45931 | J63: 1 | K63: Pouring Foundation | L63: PO-5237 | M63: PB | O63: Yes | R63: TBD | S63: Moanes | T63: =IFERROR(E63*J63,0) -> 320391 | U63: Approved (Revision approved) | V63: =IFERROR(ROUNDUP(MONTH(IF(H63<>"",H63,""))/3, 0),"TBD") -> 3 | W63: =IF(I63<>"",IF(W63="",NOW(),W63),"") -> 45813.652
A64: Menifee USD | B64: Callie Kirkpatrick ES | C64: Diana | D64: 11587 | E64: 1842640.3 | F64: (1) 144'x40' | G64: 12 | H64: 45847 | I64: 45978 | J64: 1 | K64: GC confirmed that they are still targetting 10/7 site delivery. | L64: Yes | M64: RFP | N64: Yes | O64: No | P64: Yes | R64: TBD | T64: =IFERROR(E64*J64,0) -> 1842640.3 | U64: Approved | W64: =IF(I64<>"",IF(W64="",NOW(),W64),"") -> 45692.547
A65: Palm Springs USD | B65: Katherine Finchy ES | C65: Diana | D65: 11570 | E65: 480954.99 | F65: 8’-6” x 32’-7” RR 36’x40’ TK Classroom | G65: 4 | H65: 45848 | I65: 45898 | J65: 1 | K65: GC working on updating the schedule. True occupancy date TBD. | L65: PO - C-0005221 | M65: PB | N65: Pending Adel Release | O65: No | P65: No | S65: Gino | T65: =IFERROR(E65*J65,0) -> 480954.99 | U65: Approved (Pending CCD Approval for restroom) | V65: =IFERROR(ROUNDUP(MONTH(IF(H65<>"",H65,""))/3, 0),"TBD") -> 3 | W65: =IF(I65<>"",IF(W65="",NOW(),W65),"") -> 45692.547
A66: Sweetwater USD | B66: East Hills Academy | C66: Diana | D66: 11510 | E66: 463190.78 | F66: 40x32 Office Building | G66: 4 | H66: 45849 | I66: 45919 | J66: 1 | K66: Pending Subcontractor Contracts | L66: Contract | M66: PB | N66: 45534 | O66: Yes | P66: 45435 | R66: TBD | S66: Keizah | T66: =IFERROR(E66*J66,0) -> 463190.78 | U66: Approved | V66: =IFERROR(ROUNDUP(MONTH(IF(H66<>"",H66,""))/3, 0),"TBD") -> 3 | W66: =IF(I66<>"",IF(W66="",NOW(),W66),"") -> 45692.547
A67: Oceanside USD | B67: Surfside | C67: Sandra | D67: 11562 | E67: 11797264 | F67: Various/BID | G67: 66 | H67: 45854 | I67: 45992 | J67: 1 | L67: Yes | M67: Bid | P67: Yes | R67: TBD | S67: Kenny | T67: =IFERROR(E67*J67,0) -> 11797264 | U67: Approved (Pending several CCDs for client requested changes) | V67: =IFERROR(ROUNDUP(MONTH(IF(H67<>"",H67,""))/3, 0),"TBD") -> 3 | W67: =IF(I67<>"",IF(W67="",NOW(),W67),"") -> 45692.547
A68: Palm Springs USD | B68: Rio Vista ES | C68: Diana | D68: 11572 | E68: 831305.99 | F68: 8’-6” x 32’-7” RR (2) 36’x40’ TK Classroom | G68: 7 | H68: 45855 | I68: 45898 | J68: 1 | K68: GC working on updating the schedule. True occupancy date TBD. | L68: PO - C-0005214 | M68: PB | N68: Pending Adel Release | O68: No | P68: No | S68: Gino | T68: =IFERROR(E68*J68,0) -> 831305.99 | U68: Late June | V68: =IFERROR(ROUNDUP(MONTH(IF(H68<>"",H68,""))/3, 0),"TBD") -> 3 | W68: =IF(I68<>"",IF(W68="",NOW(),W68),"") -> 45692.547
A69: Lowell Joint SD | B69: El Portal ES | C69: Sandra | D69: 11575 | E69: 3639876 | F69: (2) 108x60 CR Pod w/ RR | G69: 18 | H69: 45861 | I69: 46027 | J69: 1 | K69: DSA Approved. Can build Sooner if needed- Received Colors Collette has placed order for Tackboard as it is not standard. CCD for canopy has been submitted waiting on approval | L69: PO | M69: PB | N69: 45590 | O69: No | P69: Yes | S69: Moanes | T69: =IFERROR(E69*J69,0) -> 3639876 | U69: Approved | V69: =IFERROR(ROUNDUP(MONTH(IF(H69<>"",H69,""))/3, 0),"TBD") -> 3 | W69: =IF(I69<>"",IF(W69="",NOW(),W69),"") -> 45813.652
A70: Nuview SD | B70: Nuview Elementary | C70: Sandra | D70: 11584 | E70: 479846.47 | F70: (1) 12X40 Toilet (1) 48x40 Classroom | G70: 5 | H70: 45863 | I70: 45931 | J70: 1 | K70: Waiting on Casework Color Selection | L70: PO & Signed Proposal | M70: PB | O70: Yes | R70: TBD | S70: Gino | T70: =IFERROR(E70*J70,0) -> 479846.47 | U70: Approved (Addendum also approved) | V70: =IFERROR(ROUNDUP(MONTH(IF(H70<>"",H70,""))/3, 0),"TBD") -> 3 | W70: =IF(I70<>"",IF(W70="",NOW(),W70),"") -> 45813.652
A71: Beverly Hills USD | B71: Beverly Hills HS | C71: Sandra | D71: 11540 | E71: 263148.49 | F71: 12x40 Toilet Building | G71: 1 | H71: 45868 | I71: 45931 | J71: 1 | K71: Customer would like Building delivered beginning of Septemeber. They have decided to proceed with EPOXY and Mo is submitting change order. | L71: Yes | M71: PB | S71: Moanes | T71: =IFERROR(E71*J71,0) -> 263148.49 | U71: Approved | V71: =IFERROR(ROUNDUP(MONTH(IF(H71<>"",H71,""))/3, 0),"TBD") -> 3 | W71: =IF(I71<>"",IF(W71="",NOW(),W71),"") -> 45692.547
A72: Beaumont USD | B72: San Gorgonio MS | C72: Diana | D72: 11608 | E72: 783895.41 | F72: (2) 48'x40' CRs, (1) 12'x40' RR Bldg. | G72: 9 | H72: 45869 | I72: 45898 | J72: 1 | K72: GC working on updating the schedule. True occupancy date TBD ASAP | L72: C-0012788 | M72: PB | N72: 45709 | O72: No | P72: 45735 | S72: Gino | T72: =IFERROR(E72*J72,0) -> 783895.41 | U72: Approved | V72: =IFERROR(ROUNDUP(MONTH(IF(H72<>"",H72,""))/3, 0),"TBD") -> 3 | W72: =IF(I72<>"",IF(W72="",NOW(),W72),"") -> 45692.547
A73: Garvey USD | B73: Williams ES | C73: Sandra | D73: 11585 | E73: 1156466.6 | F73: (1) 72x40 Headstart Bldg | G73: 6 | H73: 45880 | I73: 45957 | J73: 1 | K73: DSA Approved awaiting submittals from customer | L73: PO | M73: PB | O73: Yes | S73: Moanes | T73: =IFERROR(E73*J73,0) -> 1156466.6 | U73: Approved | V73: =IFERROR(ROUNDUP(MONTH(IF(H73<>"",H73,""))/3, 0),"TBD") -> 3 | W73: =IF(I73<>"",IF(W73="",NOW(),W73),"") -> 45692.547
A74: Lowell Joint SD | B74: Rancho Starbuck | C74: Sandra | D74: 11576 | E74: 2532016.4 | F74: 156x60 CR Pod w/ RR | G74: 13 | H74: 45894 | I74: 46027 | J74: 1 | K74: Received remainder of submittals 7/24/25. Estimating is working on a change order cost for the additional low voltage | L74: PO U99B0035 | M74: PB | N74: 45590 | O74: No | P74: Yes | S74: Moanes | T74: =IFERROR(E74*J74,0) -> 2532016.4 | U74: Approved | V74: =IFERROR(ROUNDUP(MONTH(IF(H74<>"",H74,""))/3, 0),"TBD") -> 3 | W74: =IF(I74<>"",IF(W74="",NOW(),W74),"") -> 45692.547
A75: Magnolia Public Schools | B75: Magnolia Science Academy 5 | C75: Sandra | D75: 11512 | E75: 25000000 | F75: New Campus | G75: 84 | H75: 45895 | I75: 46327 | J75: 1 | K75: See Ryan for Comments | L75: Yes | M75: PB | S75: Mehdi | T75: =IFERROR(E75*J75,0) -> 25000000 | U75: Approved (Pending CCD for VE) | V75: =IFERROR(ROUNDUP(MONTH(IF(H75<>"",H75,""))/3, 0),"TBD") -> 3 | W75: =IF(I75<>"",IF(W75="",NOW(),W75),"") -> 45692.547
A76: San Diego USD | B76: Fremont ES - iHigh Virtual Academy | C76: Diana | D76: 11531 | E76: 2222772.8 | F76: (1) 36’x40’ Music Bldg. 401 (1) 8’-6” x 16’-7” Staff Restroom Bldg. 501-502 (1) 12’x40’ Student Restroom Bldg. Model B 503-504 (1) 24’x40’ Mild/Mod 506 (1) 24’x40’ Food Service 505 (1) 24’x40’ CR 3 108 (1) 36’x40’ CR 2 107 (1) 36’x40’ CR 1 106 (1) 24’x40’ Mod/Severe 105 (1) 24’x40’ Nurse w/ office and 2-rrs 102 (1) 12’x40’ Work Room 101 | G76: 22 | H76: 45922 | I76: 45992 | J76: 1 | L76: Yes | M76: Bid | N76: N/A | O76: No | P76: Yes | T76: =IFERROR(E76*J76,0) -> 2222772.8 | U76: Approved | V76: =IFERROR(ROUNDUP(MONTH(IF(H76<>"",H76,""))/3, 0),"TBD") -> 3 | W76: =IF(I76<>"",IF(W76="",NOW(),W76),"") -> 45692.547
A77: Covina Valley USD | B77: Covina HS | C77: Sandra | D77: 11581 | E77: 693726 | F77: (1) 24x40 Concession Building | G77: 2 | H77: 45930 | I77: 45989 | J77: 1 | K77: Met with GC and they Would like Bldg Delivered 10/23/25 | L77: Yes | S77: Moanes | T77: =IFERROR(E77*J77,0) -> 693726 | U77: Approved | V77: =IFERROR(ROUNDUP(MONTH(IF(H77<>"",H77,""))/3, 0),"TBD") -> 3 | W77: =IF(I77<>"",IF(W77="",NOW(),W77),"") -> 45813.652
A78: Pasadena USD | B78: McKinley School | C78: Sandra | D78: 11625 | E78: 809913.1 | F78: (1) 60x40 Admin Building | G78: 5 | H78: 45938 | I78: 45931 | J78: 1 | K78: DSA returned updates with comments to architect.They would like us to build as soon as its done. Would like to install as close as possible in August. Submittals out 7/1. | L78: PO1-250000003295 | S78: Joe
A79: Unified Modular | B79: Mojave USD | C79: Quinton/Diana | D79: 11524 | E79: 249912.61 | F79: (2) 12'x40' Restroom Buildings Model A-2,B-2 | G79: 2 | H79: 45939 | I79: 45901 | J79: 1 | K79: DSA approval expected the week of 7/28 customer would like an update on how soon we can manufacture after the DSA box is open. | L79: 50% deposit received | M79: Negotiated | N79: Yes | O79: Yes | P79: Yes | S79: Moanes | T79: =IFERROR(E79*J79,0) -> 249912.61 | U79: Unknown | W79: =IF(I79<>"",IF(W79="",NOW(),W79),"") -> 45692.547
A80: Ventura USD | B80: Portola ES | C80: Diana | D80: 11595 | E80: =383982.63+18503.39 -> 402486.02 | F80: (1) 12x60 Restroom | G80: 1 | H80: 45943 | I80: 45962 | J80: 1 | K80: DSA Approved. Sent customer final/updated pricing - final agreement forthcoming. PO received on 8/27 | L80: Purchase Order - PO26-00766 | M80: PB | P80: Yes | R80: TBD | S80: Joe | T80: =IFERROR(E80*J80,0) -> 402486.02 | U80: Approved | V80: =IFERROR(ROUNDUP(MONTH(IF(H80<>"",H80,""))/3, 0),"TBD") -> 4 | W80: =IF(I80<>"",IF(W80="",NOW(),W80),"") -> 45692.547
A81: Pasadena USD | B81: Don Benito Fundamental School | C81: Sandra | D81: 11634 | E81: 721260 | F81: (1) 48x40 Admin Bldg | G81: 4 | H81: 45946 | I81: 45992 | J81: 1 | K81: Submitting to DSA 8/1/25 | S81: Joe | T81: =IFERROR(E81*J81,0) -> 721260 | U81: Mid September
A82: Pasadena USD | B82: Webster ES | C82: Sandra | D82: 11635 | E82: 857751 | F82: (1) 48x40 Admin Bldg | G82: 4 | H82: 45952 | I82: 45992 | J82: 1 | K82: PO Received | S82: Joe | T82: =IFERROR(E82*J82,0) -> 857751 | U82: Mid September
A83: Palm Springs USD | B83: Julius Corsini ES | C83: Diana | D83: 11569 | E83: 193345.99 | F83: 8’-6”x32’-7” RR | G83: 1 | H83: 45957 | I83: 45898 | J83: 1 | K83: GC working on updating the schedule. True occupancy date TBD. | L83: PO - C-0005211 | M83: PB | N83: Pending Adel Release | O83: No | P83: No | S83: Gino | T83: =IFERROR(E83*J83,0) -> 193345.99 | U83: Approved (Pending CCD Approval for restroom) | V83: =IFERROR(ROUNDUP(MONTH(IF(H83<>"",H83,""))/3, 0),"TBD") -> 4 | W83: =IF(I83<>"",IF(W83="",NOW(),W83),"") -> 45692.547
A84: Los Banos USD | B84: Miano ES | C84: Joe | D84: 11617 | E84: 212665.05 | F84: (1) 12x40 Restroom Model C-2 | G84: 1 | H84: 45958 | I84: 45962 | J84: 1 | K84: DSA approved | L84: PO 252096 | M84: PB | N84: 45628 | O84: 45772 | P84: 45775 | Q84: 45772 | R84: 45771 | S84: Joe | T84: =IFERROR(E84*J84,0) -> 212665.05 | U84: Approved | V84: =IFERROR(ROUNDUP(MONTH(IF(H84<>"",H84,""))/3, 0),"TBD") -> 4 | W84: =IF(I84<>"",IF(W84="",NOW(),W84),"") -> 45692.547
A85: Inglewood USD | B85: Oak St. Prep K- Phase 1 | C85: Sandra | D85: 11526 | E85: 4276229 | F85: (1) 216x40 and (1) 144x40 | G85: 30 | H85: 45959 | I85: 46174 | J85: 0.9 | K85: Submittals are out. Met with customer and CM. | L85: PO1-260000000273 | M85: PB | N85: Yes | O85: No | P85: Trying | S85: Moanes | T85: =IFERROR(E85*J85,0) -> 3848606.1 | U85: Approved | V85: =IFERROR(ROUNDUP(MONTH(IF(H85<>"",H85,""))/3, 0),"TBD") -> 4 | W85: =IF(I85<>"",IF(W85="",NOW(),W85),"") -> 45692.547
A86: Murrieta USD | B86: E Hale Curan | C86: Diana | D86: 11632 | E86: 238630.22 | F86: (1) 12'x40' Restroom Model C-2 | G86: 1 | H86: 45975 | I86: 46113 | J86: 1 | K86: Executed Agreement received. | L86: C-0001477 | M86: PB | O86: No | P86: 45856 | Q86: TBD | R86: TBD | U86: Late September | W86: =IF(I86<>"",IF(W86="",NOW(),W86),"") -> 45813.652
A87: Hesperia USD | B87: Hollyvale | C87: Sandra | D87: 11637 | E87: 876581 | F87: (1) 72x40 TK | G87: 6 | H87: 45978 | I87: 46174 | J87: 1 | L87: Yes | M87: PB | P87: Yes | R87: TBD | S87: Gino | T87: =IFERROR(E87*J87,0) -> 876581 | U87: Approved (need plans from Roger) | V87: =IFERROR(ROUNDUP(MONTH(IF(H87<>"",H87,""))/3, 0),"TBD") -> 4 | W87: =IF(I87<>"",IF(W87="",NOW(),W87),"") -> 45692.547
A88: Menifee USD | B88: Bell Mountain ES | C88: Diana | D88: 11641 | E88: 791806.51 | F88: (5) 24'x40' classrooms dual slope with sink and wood foundation | G88: 10 | H88: 45985 | I88: 46022 | J88: 0.3 | K88: Being submitted to DSA 7/11/2025. Modular buildings are under Neff's contract. 7.8.2025 | U88: NOT RELEASED TO ENGINEERING
A89: Montebello USD | B89: Eastmont Intermediate ELOP | C89: Diana | D89: 11600 | E89: 380119 | F89: (1) 12'x40' RR Bldg. | G89: 1 | H89: 45996 | I89: 45901 | J89: 1 | K89: Drawings out for customer review. | L89: Signed Agreement | M89: Bid | N89: No | O89: Yes | P89: Yes | Q89: 45842 | R89: TBD - PM | S89: Moanes | T89: =IFERROR(E89*J89,0) -> 380119 | U89: Late September | W89: =IF(I89<>"",IF(W89="",NOW(),W89),"") -> 45692.547
A90: East Whittier SD | B90: Orchard ES | C90: Sandra | D90: 11592 | E90: 157449.02 | F90: (1) 12x40 Toilet | G90: 1 | H90: 46001 | I90: 45898 | J90: 1 | K90: Pending DSA Approval | L90: PO | M90: PB | O90: Yes | S90: Moanes | T90: =IFERROR(E90*J90,0) -> 157449.02 | U90: Late September | V90: =IFERROR(ROUNDUP(MONTH(IF(H90<>"",H90,""))/3, 0),"TBD") -> 4 | W90: =IF(I90<>"",IF(W90="",NOW(),W90),"") -> 45692.547
A91: Bothman Construction | B91: San Juan USD GIS Charter School | C91: Joe | D91: 11599 | E91: =43390+1332549 -> 1375939 | F91: (1) 84x40 TK | G91: 7 | H91: 46002 | I91: 46037 | J91: 1 | K91: DSA approved | L91: Yes | M91: Design Build | N91: 45807 | P91: 45735 | S91: Joe | T91: =IFERROR(E91*J91,0) -> 1375939 | U91: Approved | V91: =IFERROR(ROUNDUP(MONTH(IF(H91<>"",H91,""))/3, 0),"TBD") -> 4 | W91: =IF(I91<>"",IF(W91="",NOW(),W91),"") -> 45692.547
A92: East Whittier SD | B92: Laurel ES | C92: Sandra | D92: 11591 | E92: 157449.02 | F92: (1) 12x40 Toilet | G92: 1 | H92: 46002 | I92: 45898 | J92: 1 | K92: Pending DSA Approval | L92: PO | M92: PB | O92: Yes | R92: 45580 | S92: Moanes | T92: =IFERROR(E92*J92,0) -> 157449.02 | U92: Late September | V92: =IFERROR(ROUNDUP(MONTH(IF(H92<>"",H92,""))/3, 0),"TBD") -> 4 | W92: =IF(I92<>"",IF(W92="",NOW(),W92),"") -> 45692.547
A93: East Whittier SD | B93: Mulberry ES | C93: Sandra | D93: 11610 | E93: 159382.02 | F93: (1) 12x40 Toilet | G93: 1 | H93: 46003 | I93: 45898 | J93: 1 | K93: Pending DSA Approval- | L93: PO | U93: Late September

Sheet Simulation-Production
B1: 3 | D1: 5 | H1: 12 | I1: 13 | K1: 0 | L1: =(L2-$K$2)/(365/12) -> 1.9068493 | M1: =(M2-$K$2)/30.5 -> 2.9180328 | N1: =(N2-$K$2)/30.5 -> 3.9016393 | O1: =(O2-$K$2)/30.5 -> 4.9180328 | P1: =(P2-$K$2)/30.5 -> 5.9016393 | Q1: =(Q2-$K$2)/30.5 -> 6.9180328 | R1: =(R2-$K$2)/30.5 -> 7.9344262 | S1: =(S2-$K$2)/30.5 -> 8.9180328 | T1: =(T2-$K$2)/30.5 -> 9.9344262 | ... CA1: =(CA2-$K$2)/30.5 -> 68.786885
A2: # | B2: Project | C2: Contract Signed Date | D2: Contract Amount | E2: Production Start Date | F2: District Occupancy Date | G2: Duration | H2: End Date | I2: Line | K2: 45658 | L2: =EOMONTH(K2,1) -> 45716 | M2: =EOMONTH(L2,1) -> 45747 | N2: =EOMONTH(M2,1) -> 45777 | O2: =EOMONTH(N2,1) -> 45808 | P2: =EOMONTH(O2,1) -> 45838 | Q2: =EOMONTH(P2,1) -> 45869 | R2: =EOMONTH(Q2,1) -> 45900 | S2: =EOMONTH(R2,1) -> 45930 | ... CA2: =EOMONTH(BZ2,1) -> 47756 | CC2: Check
A3: ='Closed Deals 25'!D4 -> 11520 | B3: ='Closed Deals 25'!B4 -> Lincoln Elementary | D3: ='Closed Deals 25'!E4 -> 112000 | E3: ='Closed Deals 25'!H4 -> 45672 | F3: ='Closed Deals 25'!I4 -> 45823 | G3: =IFERROR(F3-E3,F3) -> 151 | H3: =G3+E3 -> 45823 | I3: 1 | J3: =IF(I3=1,ROW(),"") -> 3 | K3: =IF(AND($E3<=K$2, K$2<EDATE($E3,6)), (0.73*$D3)/6, 0) -> 0 | L3: =IF(AND($E3<=L$2, L$2<EDATE($E3,6)), (0.73*$D3)/6, 0) -> 13626.667 | M3: =IF(AND($E3<=M$2, M$2<EDATE($E3,6)), (0.73*$D3)/6, 0) -> 13626.667 | N3: =IF(AND($E3<=N$2, N$2<EDATE($E3,6)), (0.73*$D3)/6, 0) -> 13626.667 | O3: =IF(AND($E3<=O$2, O$2<EDATE($E3,6)), (0.73*$D3)/6, 0) -> 13626.667 | P3: =IF(AND($E3<=P$2, P$2<EDATE($E3,6)), (0.73*$D3)/6, 0) -> 13626.667 | Q3: =IF(AND($E3<=Q$2, Q$2<EDATE($E3,6)), (0.73*$D3)/6, 0) -> 0 | R3: =IF(AND($E3<=R$2, R$2<EDATE($E3,6)), (0.73*$D3)/6, 0) -> 0 | ... CA3: =IF(AND($E3<=CA$2, CA$2<EDATE($E3,6)), (0.73*$D3)/6, 0) -> 0 | CC3: =SUM(K3:CA3)-(D3-H3) -> 1956.3333
A4: ='Closed Deals 25'!D5 -> 11530 | B4: ='Closed Deals 25'!B5 -> Oka ES | D4: ='Closed Deals 25'!E5 -> 262487.93 | E4: ='Closed Deals 25'!H5 -> 45673 | F4: ='Closed Deals 25'!I5 -> 45823 | G4: =IFERROR(F4-E4,F4) -> 150 | H4: =G4+E4 -> 45823 | I4: 2 | J4: =IF(I4=1,ROW(),"") | K4: =IF(AND($E4<=K$2, K$2<EDATE($E4,6)), (0.73*$D4)/6, 0) -> 0 | L4: =IF(AND($E4<=L$2, L$2<EDATE($E4,6)), (0.73*$D4)/6, 0) -> 31936.031 | M4: =IF(AND($E4<=M$2, M$2<EDATE($E4,6)), (0.73*$D4)/6, 0) -> 31936.031 | N4: =IF(AND($E4<=N$2, N$2<EDATE($E4,6)), (0.73*$D4)/6, 0) -> 31936.031 | O4: =IF(AND($E4<=O$2, O$2<EDATE($E4,6)), (0.73*$D4)/6, 0) -> 31936.031 | P4: =IF(AND($E4<=P$2, P$2<EDATE($E4,6)), (0.73*$D4)/6, 0) -> 31936.031 | Q4: =IF(AND($E4<=Q$2, Q$2<EDATE($E4,6)), (0.73*$D4)/6, 0) -> 0 | R4: =IF(AND($E4<=R$2, R$2<EDATE($E4,6)), (0.73*$D4)/6, 0) -> 0 | ... CA4: =IF(AND($E4<=CA$2, CA$2<EDATE($E4,6)), (0.73*$D4)/6, 0) -> 0 | CC4: =SUM(K4:CA4)-(D4-H4) -> -56984.773
A5: ='Closed Deals 25'!D6 -> 11529 | B5: ='Closed Deals 25'!B6 -> Newland ES | D5: ='Closed Deals 25'!E6 -> 138298.63 | E5: ='Closed Deals 25'!H6 -> 45678 | F5: ='Closed Deals 25'!I6 -> 45823 | G5: =IFERROR(F5-E5,F5) -> 145 | H5: =G5+E5 -> 45823 | I5: 3 | J5: =IF(I5=1,ROW(),"") | K5: =IF(AND($E5<=K$2, K$2<EDATE($E5,6)), (0.73*$D5)/6, 0) -> 0 | L5: =IF(AND($E5<=L$2, L$2<EDATE($E5,6)), (0.73*$D5)/6, 0) -> 16826.333 | M5: =IF(AND($E5<=M$2, M$2<EDATE($E5,6)), (0.73*$D5)/6, 0) -> 16826.333 | N5: =IF(AND($E5<=N$2, N$2<EDATE($E5,6)), (0.73*$D5)/6, 0) -> 16826.333 | O5: =IF(AND($E5<=O$2, O$2<EDATE($E5,6)), (0.73*$D5)/6, 0) -> 16826.333 | P5: =IF(AND($E5<=P$2, P$2<EDATE($E5,6)), (0.73*$D5)/6, 0) -> 16826.333 | Q5: =IF(AND($E5<=Q$2, Q$2<EDATE($E5,6)), (0.73*$D5)/6, 0) -> 0 | R5: =IF(AND($E5<=R$2, R$2<EDATE($E5,6)), (0.73*$D5)/6, 0) -> 0 | ... CA5: =IF(AND($E5<=CA$2, CA$2<EDATE($E5,6)), (0.73*$D5)/6, 0) -> 0 | CC5: =SUM(K5:CA5)-(D5-H5) -> -8343.9634
A6: ='Closed Deals 25'!D7 -> 11489 | B6: ='Closed Deals 25'!B7 -> Yucca Loma ES | D6: ='Closed Deals 25'!E7 -> 1444491.4 | E6: ='Closed Deals 25'!H7 -> 45679 | F6: ='Closed Deals 25'!I7 -> 45811 | G6: =IFERROR(F6-E6,F6) -> 132 | H6: =G6+E6 -> 45811 | I6: 1 | J6: =IF(I6=1,ROW(),"") -> 6 | K6: =IF(AND($E6<=K$2, K$2<EDATE($E6,6)), (0.73*$D6)/6, 0) -> 0 | L6: =IF(AND($E6<=L$2, L$2<EDATE($E6,6)), (0.73*$D6)/6, 0) -> 175746.45 | M6: =IF(AND($E6<=M$2, M$2<EDATE($E6,6)), (0.73*$D6)/6, 0) -> 175746.45 | N6: =IF(AND($E6<=N$2, N$2<EDATE($E6,6)), (0.73*$D6)/6, 0) -> 175746.45 | O6: =IF(AND($E6<=O$2, O$2<EDATE($E6,6)), (0.73*$D6)/6, 0) -> 175746.45 | P6: =IF(AND($E6<=P$2, P$2<EDATE($E6,6)), (0.73*$D6)/6, 0) -> 175746.45 | Q6: =IF(AND($E6<=Q$2, Q$2<EDATE($E6,6)), (0.73*$D6)/6, 0) -> 0 | R6: =IF(AND($E6<=R$2, R$2<EDATE($E6,6)), (0.73*$D6)/6, 0) -> 0 | ... CA6: =IF(AND($E6<=CA$2, CA$2<EDATE($E6,6)), (0.73*$D6)/6, 0) -> 0 | CC6: =SUM(K6:CA6)-(D6-H6) -> -519948.14
A7: ='Closed Deals 25'!D8 -> 11528 | B7: ='Closed Deals 25'!B8 -> Plavan ES | D7: ='Closed Deals 25'!E8 -> 260370.01 | E7: ='Closed Deals 25'!H8 -> 45680 | F7: ='Closed Deals 25'!I8 -> 45823 | G7: =IFERROR(F7-E7,F7) -> 143 | H7: =G7+E7 -> 45823 | I7: 1 | J7: =IF(I7=1,ROW(),"") -> 7 | K7: =IF(AND($E7<=K$2, K$2<EDATE($E7,6)), (0.73*$D7)/6, 0) -> 0 | L7: =IF(AND($E7<=L$2, L$2<EDATE($E7,6)), (0.73*$D7)/6, 0) -> 31678.351 | M7: =IF(AND($E7<=M$2, M$2<EDATE($E7,6)), (0.73*$D7)/6, 0) -> 31678.351 | N7: =IF(AND($E7<=N$2, N$2<EDATE($E7,6)), (0.73*$D7)/6, 0) -> 31678.351 | O7: =IF(AND($E7<=O$2, O$2<EDATE($E7,6)), (0.73*$D7)/6, 0) -> 31678.351 | P7: =IF(AND($E7<=P$2, P$2<EDATE($E7,6)), (0.73*$D7)/6, 0) -> 31678.351 | Q7: =IF(AND($E7<=Q$2, Q$2<EDATE($E7,6)), (0.73*$D7)/6, 0) -> 0 | R7: =IF(AND($E7<=R$2, R$2<EDATE($E7,6)), (0.73*$D7)/6, 0) -> 0 | ... CA7: =IF(AND($E7<=CA$2, CA$2<EDATE($E7,6)), (0.73*$D7)/6, 0) -> 0 | CC7: =SUM(K7:CA7)-(D7-H7) -> -56155.254
A8: ='Closed Deals 25'!D9 -> 11501 | B8: ='Closed Deals 25'!B9 -> Torrance ES | D8: ='Closed Deals 25'!E9 -> 2448024.2 | E8: ='Closed Deals 25'!H9 -> 45685 | F8: ='Closed Deals 25'!I9 -> 45901 | G8: =IFERROR(F8-E8,F8) -> 216 | H8: =G8+E8 -> 45901 | I8: 1 | K8: =IF(AND($E8<=K$2, K$2<EDATE($E8,6)), (0.73*$D8)/6, 0) -> 0 | L8: =IF(AND($E8<=L$2, L$2<EDATE($E8,6)), (0.73*$D8)/6, 0) -> 297842.95 | M8: =IF(AND($E8<=M$2, M$2<EDATE($E8,6)), (0.73*$D8)/6, 0) -> 297842.95 | N8: =IF(AND($E8<=N$2, N$2<EDATE($E8,6)), (0.73*$D8)/6, 0) -> 297842.95 | O8: =IF(AND($E8<=O$2, O$2<EDATE($E8,6)), (0.73*$D8)/6, 0) -> 297842.95 | P8: =IF(AND($E8<=P$2, P$2<EDATE($E8,6)), (0.73*$D8)/6, 0) -> 297842.95 | Q8: =IF(AND($E8<=Q$2, Q$2<EDATE($E8,6)), (0.73*$D8)/6, 0) -> 0 | R8: =IF(AND($E8<=R$2, R$2<EDATE($E8,6)), (0.73*$D8)/6, 0) -> 0 | ... CA8: =IF(AND($E8<=CA$2, CA$2<EDATE($E8,6)), (0.73*$D8)/6, 0) -> 0 | CC8: =SUM(K8:CA8)-(D8-H8) -> -912908.49
A9: ='Closed Deals 25'!D10 -> 11574 | B9: ='Closed Deals 25'!B10 -> Beyer HS | D9: ='Closed Deals 25'!E10 -> 246171.81 | E9: ='Closed Deals 25'!H10 -> 45694 | F9: 45884 | G9: =IFERROR(F9-E9,F9) -> 190 | H9: =G9+E9 -> 45884 | I9: 1 | K9: =IF(AND($E9<=K$2, K$2<EDATE($E9,6)), (0.73*$D9)/6, 0) -> 0 | L9: =IF(AND($E9<=L$2, L$2<EDATE($E9,6)), (0.73*$D9)/6, 0) -> 29950.904 | M9: =IF(AND($E9<=M$2, M$2<EDATE($E9,6)), (0.73*$D9)/6, 0) -> 29950.904 | N9: =IF(AND($E9<=N$2, N$2<EDATE($E9,6)), (0.73*$D9)/6, 0) -> 29950.904 | O9: =IF(AND($E9<=O$2, O$2<EDATE($E9,6)), (0.73*$D9)/6, 0) -> 29950.904 | P9: =IF(AND($E9<=P$2, P$2<EDATE($E9,6)), (0.73*$D9)/6, 0) -> 29950.904 | Q9: =IF(AND($E9<=Q$2, Q$2<EDATE($E9,6)), (0.73*$D9)/6, 0) -> 29950.904 | R9: =IF(AND($E9<=R$2, R$2<EDATE($E9,6)), (0.73*$D9)/6, 0) -> 0 | ... CA9: =IF(AND($E9<=CA$2, CA$2<EDATE($E9,6)), (0.73*$D9)/6, 0) -> 0 | CC9: =SUM(K9:CA9)-(D9-H9) -> -20582.389
A10: ='Closed Deals 25'!D11 -> 11442 | B10: ='Closed Deals 25'!B11 -> Fire Academy | D10: ='Closed Deals 25'!E11 -> 227900.33 | E10: ='Closed Deals 25'!H11 -> 45694 | F10: 45884 | G10: =IFERROR(F10-E10,F10) -> 190 | H10: =G10+E10 -> 45884 | I10: 2 | K10: =IF(AND($E10<=K$2, K$2<EDATE($E10,6)), (0.73*$D10)/6, 0) -> 0 | L10: =IF(AND($E10<=L$2, L$2<EDATE($E10,6)), (0.73*$D10)/6, 0) -> 27727.873 | M10: =IF(AND($E10<=M$2, M$2<EDATE($E10,6)), (0.73*$D10)/6, 0) -> 27727.873 | N10: =IF(AND($E10<=N$2, N$2<EDATE($E10,6)), (0.73*$D10)/6, 0) -> 27727.873 | O10: =IF(AND($E10<=O$2, O$2<EDATE($E10,6)), (0.73*$D10)/6, 0) -> 27727.873 | P10: =IF(AND($E10<=P$2, P$2<EDATE($E10,6)), (0.73*$D10)/6, 0) -> 27727.873 | Q10: =IF(AND($E10<=Q$2, Q$2<EDATE($E10,6)), (0.73*$D10)/6, 0) -> 27727.873 | R10: =IF(AND($E10<=R$2, R$2<EDATE($E10,6)), (0.73*$D10)/6, 0) -> 0 | ... CA10: =IF(AND($E10<=CA$2, CA$2<EDATE($E10,6)), (0.73*$D10)/6, 0) -> 0 | CC10: =SUM(K10:CA10)-(D10-H10) -> -15649.089
A11: ='Closed Deals 25'!D12 -> 11558 | B11: ='Closed Deals 25'!B12 -> Harada ES | D11: ='Closed Deals 25'!E12 -> 998332 | E11: ='Closed Deals 25'!H12 -> 45695 | F11: ='Closed Deals 25'!I12 -> 45768 | G11: =IFERROR(F11-E11,F11) -> 73 | H11: =G11+E11 -> 45768 | I11: 2 | K11: =IF(AND($E11<=K$2, K$2<EDATE($E11,6)), (0.73*$D11)/6, 0) -> 0 | L11: =IF(AND($E11<=L$2, L$2<EDATE($E11,6)), (0.73*$D11)/6, 0) -> 121463.73 | M11: =IF(AND($E11<=M$2, M$2<EDATE($E11,6)), (0.73*$D11)/6, 0) -> 121463.73 | N11: =IF(AND($E11<=N$2, N$2<EDATE($E11,6)), (0.73*$D11)/6, 0) -> 121463.73 | O11: =IF(AND($E11<=O$2, O$2<EDATE($E11,6)), (0.73*$D11)/6, 0) -> 121463.73 | P11: =IF(AND($E11<=P$2, P$2<EDATE($E11,6)), (0.73*$D11)/6, 0) -> 121463.73 | Q11: =IF(AND($E11<=Q$2, Q$2<EDATE($E11,6)), (0.73*$D11)/6, 0) -> 121463.73 | R11: =IF(AND($E11<=R$2, R$2<EDATE($E11,6)), (0.73*$D11)/6, 0) -> 0 | ... CA11: =IF(AND($E11<=CA$2, CA$2<EDATE($E11,6)), (0.73*$D11)/6, 0) -> 0 | CC11: =SUM(K11:CA11)-(D11-H11) -> -223781.64
A12: ='Closed Deals 25'!D13 -> 11502 | B12: ='Closed Deals 25'!B13 -> Vineland ES | D12: ='Closed Deals 25'!E13 -> 3006336.8 | E12: ='Closed Deals 25'!H13 -> 45702 | H12: =G12+E12 -> 45702 | I12: 2 | K12: =IF(AND($E12<=K$2, K$2<EDATE($E12,6)), (0.73*$D12)/6, 0) -> 0 | L12: =IF(AND($E12<=L$2, L$2<EDATE($E12,6)), (0.73*$D12)/6, 0) -> 365770.97 | M12: =IF(AND($E12<=M$2, M$2<EDATE($E12,6)), (0.73*$D12)/6, 0) -> 365770.97 | N12: =IF(AND($E12<=N$2, N$2<EDATE($E12,6)), (0.73*$D12)/6, 0) -> 365770.97 | O12: =IF(AND($E12<=O$2, O$2<EDATE($E12,6)), (0.73*$D12)/6, 0) -> 365770.97 | P12: =IF(AND($E12<=P$2, P$2<EDATE($E12,6)), (0.73*$D12)/6, 0) -> 365770.97 | Q12: =IF(AND($E12<=Q$2, Q$2<EDATE($E12,6)), (0.73*$D12)/6, 0) -> 365770.97 | R12: =IF(AND($E12<=R$2, R$2<EDATE($E12,6)), (0.73*$D12)/6, 0) -> 0 | ... CA12: =IF(AND($E12<=CA$2, CA$2<EDATE($E12,6)), (0.73*$D12)/6, 0) -> 0 | CC12: =SUM(K12:CA12)-(D12-H12) -> -766008.92
A13: ='Closed Deals 25'!D14 -> 11559 | B13: ='Closed Deals 25'!B14 -> Temescal ES | D13: ='Closed Deals 25'!E14 -> 332944 | E13: ='Closed Deals 25'!H14 -> 45706 | H13: =G13+E13 -> 45706 | I13: 2 | K13: =IF(AND($E13<=K$2, K$2<EDATE($E13,6)), (0.73*$D13)/6, 0) -> 0 | L13: =IF(AND($E13<=L$2, L$2<EDATE($E13,6)), (0.73*$D13)/6, 0) -> 40508.187 | M13: =IF(AND($E13<=M$2, M$2<EDATE($E13,6)), (0.73*$D13)/6, 0) -> 40508.187 | N13: =IF(AND($E13<=N$2, N$2<EDATE($E13,6)), (0.73*$D13)/6, 0) -> 40508.187 | O13: =IF(AND($E13<=O$2, O$2<EDATE($E13,6)), (0.73*$D13)/6, 0) -> 40508.187 | P13: =IF(AND($E13<=P$2, P$2<EDATE($E13,6)), (0.73*$D13)/6, 0) -> 40508.187 | Q13: =IF(AND($E13<=Q$2, Q$2<EDATE($E13,6)), (0.73*$D13)/6, 0) -> 40508.187 | R13: =IF(AND($E13<=R$2, R$2<EDATE($E13,6)), (0.73*$D13)/6, 0) -> 0 | ... CA13: =IF(AND($E13<=CA$2, CA$2<EDATE($E13,6)), (0.73*$D13)/6, 0) -> 0 | CC13: =SUM(K13:CA13)-(D13-H13) -> -44188.88
A14: ='Closed Deals 25'!D15 -> 11560 | B14: ='Closed Deals 25'!B15 -> Jefferson ES | D14: ='Closed Deals 25'!E15 -> 792600 | E14: ='Closed Deals 25'!H15 -> 45709 | F14: ='Closed Deals 25'!I15 -> 45743 | G14: =IFERROR(F14-E14,F14) -> 34 | H14: =G14+E14 -> 45743 | I14: 2 | K14: =IF(AND($E14<=K$2, K$2<EDATE($E14,6)), (0.73*$D14)/6, 0) -> 0 | L14: =IF(AND($E14<=L$2, L$2<EDATE($E14,6)), (0.73*$D14)/6, 0) -> 96433 | M14: =IF(AND($E14<=M$2, M$2<EDATE($E14,6)), (0.73*$D14)/6, 0) -> 96433 | N14: =IF(AND($E14<=N$2, N$2<EDATE($E14,6)), (0.73*$D14)/6, 0) -> 96433 | O14: =IF(AND($E14<=O$2, O$2<EDATE($E14,6)), (0.73*$D14)/6, 0) -> 96433 | P14: =IF(AND($E14<=P$2, P$2<EDATE($E14,6)), (0.73*$D14)/6, 0) -> 96433 | Q14: =IF(AND($E14<=Q$2, Q$2<EDATE($E14,6)), (0.73*$D14)/6, 0) -> 96433 | R14: =IF(AND($E14<=R$2, R$2<EDATE($E14,6)), (0.73*$D14)/6, 0) -> 0 | ... CA14: =IF(AND($E14<=CA$2, CA$2<EDATE($E14,6)), (0.73*$D14)/6, 0) -> 0 | CC14: =SUM(K14:CA14)-(D14-H14) -> -168259
A15: ='Closed Deals 25'!D16 -> 11519 | B15: ='Closed Deals 25'!B16 -> Meridian ES | D15: ='Closed Deals 25'!E16 -> 199336 | E15: ='Closed Deals 25'!H16 -> 45723 | F15: ='Closed Deals 25'!I16 -> 45839 | G15: =IFERROR(F15-E15,F15) -> 116 | H15: =G15+E15 -> 45839 | I15: 3 | K15: =IF(AND($E15<=K$2, K$2<EDATE($E15,6)), (0.73*$D15)/6, 0) -> 0 | L15: =IF(AND($E15<=L$2, L$2<EDATE($E15,6)), (0.73*$D15)/6, 0) -> 0 | M15: =IF(AND($E15<=M$2, M$2<EDATE($E15,6)), (0.73*$D15)/6, 0) -> 24252.547 | N15: =IF(AND($E15<=N$2, N$2<EDATE($E15,6)), (0.73*$D15)/6, 0) -> 24252.547 | O15: =IF(AND($E15<=O$2, O$2<EDATE($E15,6)), (0.73*$D15)/6, 0) -> 24252.547 | P15: =IF(AND($E15<=P$2, P$2<EDATE($E15,6)), (0.73*$D15)/6, 0) -> 24252.547 | Q15: =IF(AND($E15<=Q$2, Q$2<EDATE($E15,6)), (0.73*$D15)/6, 0) -> 24252.547 | R15: =IF(AND($E15<=R$2, R$2<EDATE($E15,6)), (0.73*$D15)/6, 0) -> 24252.547 | ... CA15: =IF(AND($E15<=CA$2, CA$2<EDATE($E15,6)), (0.73*$D15)/6, 0) -> 0 | CC15: =SUM(K15:CA15)-(D15-H15) -> -7981.72
A16: ='Closed Deals 25'!D17 -> 11588 | B16: ='Closed Deals 25'!B17 -> Hans Christensen ES | D16: ='Closed Deals 25'!E17 -> 3084567.3 | E16: ='Closed Deals 25'!H17 -> 45726 | F16: ='Closed Deals 25'!I17 -> 45838 | G16: =IFERROR(F16-E16,F16) -> 112 | H16: =G16+E16 -> 45838 | I16: 3 | K16: =IF(AND($E16<=K$2, K$2<EDATE($E16,6)), (0.73*$D16)/6, 0) -> 0 | L16: =IF(AND($E16<=L$2, L$2<EDATE($E16,6)), (0.73*$D16)/6, 0) -> 0 | M16: =IF(AND($E16<=M$2, M$2<EDATE($E16,6)), (0.73*$D16)/6, 0) -> 375289.02 | N16: =IF(AND($E16<=N$2, N$2<EDATE($E16,6)), (0.73*$D16)/6, 0) -> 375289.02 | O16: =IF(AND($E16<=O$2, O$2<EDATE($E16,6)), (0.73*$D16)/6, 0) -> 375289.02 | P16: =IF(AND($E16<=P$2, P$2<EDATE($E16,6)), (0.73*$D16)/6, 0) -> 375289.02 | Q16: =IF(AND($E16<=Q$2, Q$2<EDATE($E16,6)), (0.73*$D16)/6, 0) -> 375289.02 | R16: =IF(AND($E16<=R$2, R$2<EDATE($E16,6)), (0.73*$D16)/6, 0) -> 375289.02 | ... CA16: =IF(AND($E16<=CA$2, CA$2<EDATE($E16,6)), (0.73*$D16)/6, 0) -> 0 | CC16: =SUM(K16:CA16)-(D16-H16) -> -786995.17
A17: ='Closed Deals 25'!D18 -> 11435 | B17: ='Closed Deals 25'!B18 -> Mesa Grande ES | D17: ='Closed Deals 25'!E18 -> 817329 | E17: ='Closed Deals 25'!H18 -> 45727 | F17: ='Closed Deals 25'!I18 -> 45869 | G17: =IFERROR(F17-E17,F17) -> 142 | H17: =G17+E17 -> 45869 | I17: 3 | K17: =IF(AND($E17<=K$2, K$2<EDATE($E17,6)), (0.73*$D17)/6, 0) -> 0 | L17: =IF(AND($E17<=L$2, L$2<EDATE($E17,6)), (0.73*$D17)/6, 0) -> 0 | M17: =IF(AND($E17<=M$2, M$2<EDATE($E17,6)), (0.73*$D17)/6, 0) -> 99441.695 | N17: =IF(AND($E17<=N$2, N$2<EDATE($E17,6)), (0.73*$D17)/6, 0) -> 99441.695 | O17: =IF(AND($E17<=O$2, O$2<EDATE($E17,6)), (0.73*$D17)/6, 0) -> 99441.695 | P17: =IF(AND($E17<=P$2, P$2<EDATE($E17,6)), (0.73*$D17)/6, 0) -> 99441.695 | Q17: =IF(AND($E17<=Q$2, Q$2<EDATE($E17,6)), (0.73*$D17)/6, 0) -> 99441.695 | R17: =IF(AND($E17<=R$2, R$2<EDATE($E17,6)), (0.73*$D17)/6, 0) -> 99441.695 | ... CA17: =IF(AND($E17<=CA$2, CA$2<EDATE($E17,6)), (0.73*$D17)/6, 0) -> 0 | CC17: =SUM(K17:CA17)-(D17-H17) -> -174809.83
A18: ='Closed Deals 25'!D19 -> 11507 | B18: ='Closed Deals 25'!B19 -> Claremont HS | D18: ='Closed Deals 25'!E19 -> 191440 | E18: ='Closed Deals 25'!H19 -> 45734 | F18: ='Closed Deals 25'!I19 -> 45869 | G18: =IFERROR(F18-E18,F18) -> 135 | H18: =G18+E18 -> 45869 | I18: 3 | K18: =IF(AND($E18<=K$2, K$2<EDATE($E18,6)), (0.73*$D18)/6, 0) -> 0 | L18: =IF(AND($E18<=L$2, L$2<EDATE($E18,6)), (0.73*$D18)/6, 0) -> 0 | M18: =IF(AND($E18<=M$2, M$2<EDATE($E18,6)), (0.73*$D18)/6, 0) -> 23291.867 | N18: =IF(AND($E18<=N$2, N$2<EDATE($E18,6)), (0.73*$D18)/6, 0) -> 23291.867 | O18: =IF(AND($E18<=O$2, O$2<EDATE($E18,6)), (0.73*$D18)/6, 0) -> 23291.867 | P18: =IF(AND($E18<=P$2, P$2<EDATE($E18,6)), (0.73*$D18)/6, 0) -> 23291.867 | Q18: =IF(AND($E18<=Q$2, Q$2<EDATE($E18,6)), (0.73*$D18)/6, 0) -> 23291.867 | R18: =IF(AND($E18<=R$2, R$2<EDATE($E18,6)), (0.73*$D18)/6, 0) -> 23291.867 | ... CA18: =IF(AND($E18<=CA$2, CA$2<EDATE($E18,6)), (0.73*$D18)/6, 0) -> 0 | CC18: =SUM(K18:CA18)-(D18-H18) -> -5819.8
A19: ='Closed Deals 25'!D20 -> 11546 | B19: ='Closed Deals 25'!B20 -> Hollyvale ES | D19: ='Closed Deals 25'!E20 -> 420981.5 | E19: ='Closed Deals 25'!H20 -> 45736 | F19: ='Closed Deals 25'!I20 -> 45869 | G19: =IFERROR(F19-E19,F19) -> 133 | H19: =G19+E19 -> 45869 | I19: 3 | K19: =IF(AND($E19<=K$2, K$2<EDATE($E19,6)), (0.73*$D19)/6, 0) -> 0 | L19: =IF(AND($E19<=L$2, L$2<EDATE($E19,6)), (0.73*$D19)/6, 0) -> 0 | M19: =IF(AND($E19<=M$2, M$2<EDATE($E19,6)), (0.73*$D19)/6, 0) -> 51219.416 | N19: =IF(AND($E19<=N$2, N$2<EDATE($E19,6)), (0.73*$D19)/6, 0) -> 51219.416 | O19: =IF(AND($E19<=O$2, O$2<EDATE($E19,6)), (0.73*$D19)/6, 0) -> 51219.416 | P19: =IF(AND($E19<=P$2, P$2<EDATE($E19,6)), (0.73*$D19)/6, 0) -> 51219.416 | Q19: =IF(AND($E19<=Q$2, Q$2<EDATE($E19,6)), (0.73*$D19)/6, 0) -> 51219.416 | R19: =IF(AND($E19<=R$2, R$2<EDATE($E19,6)), (0.73*$D19)/6, 0) -> 51219.416 | ... CA19: =IF(AND($E19<=CA$2, CA$2<EDATE($E19,6)), (0.73*$D19)/6, 0) -> 0 | CC19: =SUM(K19:CA19)-(D19-H19) -> -67796.005
A20: ='Closed Deals 25'!D21 -> 11534 | B20: ='Closed Deals 25'!B21 -> Harding ES | D20: ='Closed Deals 25'!E21 -> 2816398 | E20: ='Closed Deals 25'!H21 -> 45742 | F20: 45884 | G20: =IFERROR(F20-E20,F20) -> 142 | H20: =G20+E20 -> 45884 | I20: 3 | K20: =IF(AND($E20<=K$2, K$2<EDATE($E20,6)), (0.73*$D20)/6, 0) -> 0 | L20: =IF(AND($E20<=L$2, L$2<EDATE($E20,6)), (0.73*$D20)/6, 0) -> 0 | M20: =IF(AND($E20<=M$2, M$2<EDATE($E20,6)), (0.73*$D20)/6, 0) -> 342661.76 | N20: =IF(AND($E20<=N$2, N$2<EDATE($E20,6)), (0.73*$D20)/6, 0) -> 342661.76 | O20: =IF(AND($E20<=O$2, O$2<EDATE($E20,6)), (0.73*$D20)/6, 0) -> 342661.76 | P20: =IF(AND($E20<=P$2, P$2<EDATE($E20,6)), (0.73*$D20)/6, 0) -> 342661.76 | Q20: =IF(AND($E20<=Q$2, Q$2<EDATE($E20,6)), (0.73*$D20)/6, 0) -> 342661.76 | R20: =IF(AND($E20<=R$2, R$2<EDATE($E20,6)), (0.73*$D20)/6, 0) -> 342661.76 | ... CA20: =IF(AND($E20<=CA$2, CA$2<EDATE($E20,6)), (0.73*$D20)/6, 0) -> 0 | CC20: =SUM(K20:CA20)-(D20-H20) -> -714543.46
A21: ='Closed Deals 25'!D22 -> 11525 | B21: ='Closed Deals 25'!B22 -> Pasadera Early Childhood Education Center | D21: ='Closed Deals 25'!E22 -> 1641711.3 | E21: ='Closed Deals 25'!H22 -> 45742 | F21: 45717 | G21: =IFERROR(F21-E21,F21) -> -25 | H21: =G21+E21 -> 45717 | I21: 3 | K21: =IF(AND($E21<=K$2, K$2<EDATE($E21,6)), (0.73*$D21)/6, 0) -> 0 | L21: =IF(AND($E21<=L$2, L$2<EDATE($E21,6)), (0.73*$D21)/6, 0) -> 0 | M21: =IF(AND($E21<=M$2, M$2<EDATE($E21,6)), (0.73*$D21)/6, 0) -> 199741.55 | N21: =IF(AND($E21<=N$2, N$2<EDATE($E21,6)), (0.73*$D21)/6, 0) -> 199741.55 | O21: =IF(AND($E21<=O$2, O$2<EDATE($E21,6)), (0.73*$D21)/6, 0) -> 199741.55 | P21: =IF(AND($E21<=P$2, P$2<EDATE($E21,6)), (0.73*$D21)/6, 0) -> 199741.55 | Q21: =IF(AND($E21<=Q$2, Q$2<EDATE($E21,6)), (0.73*$D21)/6, 0) -> 199741.55 | R21: =IF(AND($E21<=R$2, R$2<EDATE($E21,6)), (0.73*$D21)/6, 0) -> 199741.55 | ... CA21: =IF(AND($E21<=CA$2, CA$2<EDATE($E21,6)), (0.73*$D21)/6, 0) -> 0 | CC21: =SUM(K21:CA21)-(D21-H21) -> -397545.06
A22: ='Closed Deals 25'!D23 -> 11552 | B22: ='Closed Deals 25'!B23 -> Mesa Grande | D22: ='Closed Deals 25'!E23 -> 623161 | E22: ='Closed Deals 25'!H23 -> 45749 | F22: ='Closed Deals 25'!I23 -> 45869 | G22: =IFERROR(F22-E22,F22) -> 120 | H22: =G22+E22 -> 45869 | I22: 1 | K22: =IF(AND($E22<=K$2, K$2<EDATE($E22,6)), (0.73*$D22)/6, 0) -> 0 | L22: =IF(AND($E22<=L$2, L$2<EDATE($E22,6)), (0.73*$D22)/6, 0) -> 0 | M22: =IF(AND($E22<=M$2, M$2<EDATE($E22,6)), (0.73*$D22)/6, 0) -> 0 | N22: =IF(AND($E22<=N$2, N$2<EDATE($E22,6)), (0.73*$D22)/6, 0) -> 75817.922 | O22: =IF(AND($E22<=O$2, O$2<EDATE($E22,6)), (0.73*$D22)/6, 0) -> 75817.922 | P22: =IF(AND($E22<=P$2, P$2<EDATE($E22,6)), (0.73*$D22)/6, 0) -> 75817.922 | Q22: =IF(AND($E22<=Q$2, Q$2<EDATE($E22,6)), (0.73*$D22)/6, 0) -> 75817.922 | R22: =IF(AND($E22<=R$2, R$2<EDATE($E22,6)), (0.73*$D22)/6, 0) -> 75817.922 | ... CA22: =IF(AND($E22<=CA$2, CA$2<EDATE($E22,6)), (0.73*$D22)/6, 0) -> 0 | CC22: =SUM(K22:CA22)-(D22-H22) -> -122384.47
A23: ='Closed Deals 25'!D24 -> 11616 | B23: ='Closed Deals 25'!B24 -> Mesa Grande ES | D23: ='Closed Deals 25'!E24 -> 152362 | E23: ='Closed Deals 25'!H24 -> 45754 | F23: 45884 | G23: =IFERROR(F23-E23,F23) -> 130 | H23: =G23+E23 -> 45884 | I23: 1 | K23: =IF(AND($E23<=K$2, K$2<EDATE($E23,6)), (0.73*$D23)/6, 0) -> 0 | L23: =IF(AND($E23<=L$2, L$2<EDATE($E23,6)), (0.73*$D23)/6, 0) -> 0 | M23: =IF(AND($E23<=M$2, M$2<EDATE($E23,6)), (0.73*$D23)/6, 0) -> 0 | N23: =IF(AND($E23<=N$2, N$2<EDATE($E23,6)), (0.73*$D23)/6, 0) -> 18537.377 | O23: =IF(AND($E23<=O$2, O$2<EDATE($E23,6)), (0.73*$D23)/6, 0) -> 18537.377 | P23: =IF(AND($E23<=P$2, P$2<EDATE($E23,6)), (0.73*$D23)/6, 0) -> 18537.377 | Q23: =IF(AND($E23<=Q$2, Q$2<EDATE($E23,6)), (0.73*$D23)/6, 0) -> 18537.377 | R23: =IF(AND($E23<=R$2, R$2<EDATE($E23,6)), (0.73*$D23)/6, 0) -> 18537.377 | ... CA23: =IF(AND($E23<=CA$2, CA$2<EDATE($E23,6)), (0.73*$D23)/6, 0) -> 0 | CC23: =SUM(K23:CA23)-(D23-H23) -> 4746.26
A24: ='Closed Deals 25'!D25 -> 11506 | B24: ='Closed Deals 25'!B25 -> Beaumont Adult School | D24: ='Closed Deals 25'!E25 -> 1420634.9 | E24: ='Closed Deals 25'!H25 -> 45756 | F24: ='Closed Deals 25'!I25 -> 45748 | G24: =IFERROR(F24-E24,F24) -> -8 | H24: =G24+E24 -> 45748 | K24: =IF(AND($E24<=K$2, K$2<EDATE($E24,6)), (0.73*$D24)/6, 0) -> 0 | L24: =IF(AND($E24<=L$2, L$2<EDATE($E24,6)), (0.73*$D24)/6, 0) -> 0 | M24: =IF(AND($E24<=M$2, M$2<EDATE($E24,6)), (0.73*$D24)/6, 0) -> 0 | N24: =IF(AND($E24<=N$2, N$2<EDATE($E24,6)), (0.73*$D24)/6, 0) -> 172843.92 | O24: =IF(AND($E24<=O$2, O$2<EDATE($E24,6)), (0.73*$D24)/6, 0) -> 172843.92 | P24: =IF(AND($E24<=P$2, P$2<EDATE($E24,6)), (0.73*$D24)/6, 0) -> 172843.92 | Q24: =IF(AND($E24<=Q$2, Q$2<EDATE($E24,6)), (0.73*$D24)/6, 0) -> 172843.92 | R24: =IF(AND($E24<=R$2, R$2<EDATE($E24,6)), (0.73*$D24)/6, 0) -> 172843.92 | ... CA24: =IF(AND($E24<=CA$2, CA$2<EDATE($E24,6)), (0.73*$D24)/6, 0) -> 0 | CC24: =SUM(K24:CA24)-(D24-H24) -> -337823.44
A25: ='Closed Deals 25'!D26 -> 11604 | B25: ='Closed Deals 25'!B26 -> Ethan Chase MS | D25: ='Closed Deals 25'!E26 -> 316914.98 | E25: ='Closed Deals 25'!H26 -> 45758 | F25: ='Closed Deals 25'!I26 -> 45809 | G25: =IFERROR(F25-E25,F25) -> 51 | H25: =G25+E25 -> 45809 | I25: 1 | K25: =IF(AND($E25<=K$2, K$2<EDATE($E25,6)), (0.73*$D25)/6, 0) -> 0 | L25: =IF(AND($E25<=L$2, L$2<EDATE($E25,6)), (0.73*$D25)/6, 0) -> 0 | M25: =IF(AND($E25<=M$2, M$2<EDATE($E25,6)), (0.73*$D25)/6, 0) -> 0 | N25: =IF(AND($E25<=N$2, N$2<EDATE($E25,6)), (0.73*$D25)/6, 0) -> 38557.989 | O25: =IF(AND($E25<=O$2, O$2<EDATE($E25,6)), (0.73*$D25)/6, 0) -> 38557.989 | P25: =IF(AND($E25<=P$2, P$2<EDATE($E25,6)), (0.73*$D25)/6, 0) -> 38557.989 | Q25: =IF(AND($E25<=Q$2, Q$2<EDATE($E25,6)), (0.73*$D25)/6, 0) -> 38557.989 | R25: =IF(AND($E25<=R$2, R$2<EDATE($E25,6)), (0.73*$D25)/6, 0) -> 38557.989 | ... CA25: =IF(AND($E25<=CA$2, CA$2<EDATE($E25,6)), (0.73*$D25)/6, 0) -> 0 | CC25: =SUM(K25:CA25)-(D25-H25) -> -39758.045
A26: ='Closed Deals 25'!D27 -> 11601 | B26: ='Closed Deals 25'!B27 -> Romoland ES | D26: ='Closed Deals 25'!E27 -> 495340.6 | E26: ='Closed Deals 25'!H27 -> 45768 | F26: ='Closed Deals 25'!I27 -> 45809 | I26: 2 | K26: =IF(AND($E26<=K$2, K$2<EDATE($E26,6)), (0.73*$D26)/6, 0) -> 0 | L26: =IF(AND($E26<=L$2, L$2<EDATE($E26,6)), (0.73*$D26)/6, 0) -> 0 | M26: =IF(AND($E26<=M$2, M$2<EDATE($E26,6)), (0.73*$D26)/6, 0) -> 0 | N26: =IF(AND($E26<=N$2, N$2<EDATE($E26,6)), (0.73*$D26)/6, 0) -> 60266.44 | O26: =IF(AND($E26<=O$2, O$2<EDATE($E26,6)), (0.73*$D26)/6, 0) -> 60266.44 | P26: =IF(AND($E26<=P$2, P$2<EDATE($E26,6)), (0.73*$D26)/6, 0) -> 60266.44 | Q26: =IF(AND($E26<=Q$2, Q$2<EDATE($E26,6)), (0.73*$D26)/6, 0) -> 60266.44 | R26: =IF(AND($E26<=R$2, R$2<EDATE($E26,6)), (0.73*$D26)/6, 0) -> 60266.44 | ... CA26: =IF(AND($E26<=CA$2, CA$2<EDATE($E26,6)), (0.73*$D26)/6, 0) -> 0 | CC26: =SUM(K26:CA26)-(D26-H26) -> -133741.96
A27: ='Closed Deals 25'!D28 -> 11602 | B27: ='Closed Deals 25'!B28 -> Harvest Valley ES | D27: ='Closed Deals 25'!E28 -> 316914.98 | E27: ='Closed Deals 25'!H28 -> 45768 | F27: 45884 | G27: =IFERROR(F27-E27,F27) -> 116 | I27: 2 | K27: =IF(AND($E27<=K$2, K$2<EDATE($E27,6)), (0.73*$D27)/6, 0) -> 0 | L27: =IF(AND($E27<=L$2, L$2<EDATE($E27,6)), (0.73*$D27)/6, 0) -> 0 | M27: =IF(AND($E27<=M$2, M$2<EDATE($E27,6)), (0.73*$D27)/6, 0) -> 0 | N27: =IF(AND($E27<=N$2, N$2<EDATE($E27,6)), (0.73*$D27)/6, 0) -> 38557.989 | O27: =IF(AND($E27<=O$2, O$2<EDATE($E27,6)), (0.73*$D27)/6, 0) -> 38557.989 | P27: =IF(AND($E27<=P$2, P$2<EDATE($E27,6)), (0.73*$D27)/6, 0) -> 38557.989 | Q27: =IF(AND($E27<=Q$2, Q$2<EDATE($E27,6)), (0.73*$D27)/6, 0) -> 38557.989 | R27: =IF(AND($E27<=R$2, R$2<EDATE($E27,6)), (0.73*$D27)/6, 0) -> 38557.989 | ... CA27: =IF(AND($E27<=CA$2, CA$2<EDATE($E27,6)), (0.73*$D27)/6, 0) -> 0 | CC27: =SUM(K27:CA27)-(D27-H27) -> -85567.045
A28: ='Closed Deals 25'!D32 -> 11586 | B28: ='Closed Deals 25'!B32 -> Emerson ES | D28: ='Closed Deals 25'!E32 -> 244043 | E28: ='Closed Deals 25'!H32 -> 45778 | F28: ='Closed Deals 25'!I32 -> 45838 | K28: =IF(AND($E28<=K$2, K$2<EDATE($E28,6)), (0.73*$D28)/6, 0) -> 0 | L28: =IF(AND($E28<=L$2, L$2<EDATE($E28,6)), (0.73*$D28)/6, 0) -> 0 | M28: =IF(AND($E28<=M$2, M$2<EDATE($E28,6)), (0.73*$D28)/6, 0) -> 0 | N28: =IF(AND($E28<=N$2, N$2<EDATE($E28,6)), (0.73*$D28)/6, 0) -> 0 | O28: =IF(AND($E28<=O$2, O$2<EDATE($E28,6)), (0.73*$D28)/6, 0) -> 29691.898 | P28: =IF(AND($E28<=P$2, P$2<EDATE($E28,6)), (0.73*$D28)/6, 0) -> 29691.898 | Q28: =IF(AND($E28<=Q$2, Q$2<EDATE($E28,6)), (0.73*$D28)/6, 0) -> 29691.898 | R28: =IF(AND($E28<=R$2, R$2<EDATE($E28,6)), (0.73*$D28)/6, 0) -> 29691.898 | ... CA28: =IF(AND($E28<=CA$2, CA$2<EDATE($E28,6)), (0.73*$D28)/6, 0) -> 0 | CC28: =SUM(K28:CA28)-(D28-H28) -> -65891.61
A29: ='Closed Deals 25'!D33 -> 11533 | B29: ='Closed Deals 25'!B33 -> Veterans ES | D29: ='Closed Deals 25'!E33 -> 1196120 | E29: ='Closed Deals 25'!H33 -> 45782 | F29: 45884 | G29: =IFERROR(F29-E29,F29) -> 102 | I29: 2 | K29: =IF(AND($E29<=K$2, K$2<EDATE($E29,6)), (0.73*$D29)/6, 0) -> 0 | L29: =IF(AND($E29<=L$2, L$2<EDATE($E29,6)), (0.73*$D29)/6, 0) -> 0 | M29: =IF(AND($E29<=M$2, M$2<EDATE($E29,6)), (0.73*$D29)/6, 0) -> 0 | N29: =IF(AND($E29<=N$2, N$2<EDATE($E29,6)), (0.73*$D29)/6, 0) -> 0 | O29: =IF(AND($E29<=O$2, O$2<EDATE($E29,6)), (0.73*$D29)/6, 0) -> 145527.93 | P29: =IF(AND($E29<=P$2, P$2<EDATE($E29,6)), (0.73*$D29)/6, 0) -> 145527.93 | Q29: =IF(AND($E29<=Q$2, Q$2<EDATE($E29,6)), (0.73*$D29)/6, 0) -> 145527.93 | R29: =IF(AND($E29<=R$2, R$2<EDATE($E29,6)), (0.73*$D29)/6, 0) -> 145527.93 | ... CA29: =IF(AND($E29<=CA$2, CA$2<EDATE($E29,6)), (0.73*$D29)/6, 0) -> 0 | CC29: =SUM(K29:CA29)-(D29-H29) -> -322952.4
A30: ='Closed Deals 25'!D34 -> 11539 | B30: ='Closed Deals 25'!B34 -> Olive Drive ES | D30: ='Closed Deals 25'!E34 -> 847983.87 | E30: ='Closed Deals 25'!H34 -> 45783 | F30: 45838 | G30: =IFERROR(F30-E30,F30) -> 55 | I30: 2 | K30: =IF(AND($E30<=K$2, K$2<EDATE($E30,6)), (0.73*$D30)/6, 0) -> 0 | L30: =IF(AND($E30<=L$2, L$2<EDATE($E30,6)), (0.73*$D30)/6, 0) -> 0 | M30: =IF(AND($E30<=M$2, M$2<EDATE($E30,6)), (0.73*$D30)/6, 0) -> 0 | N30: =IF(AND($E30<=N$2, N$2<EDATE($E30,6)), (0.73*$D30)/6, 0) -> 0 | O30: =IF(AND($E30<=O$2, O$2<EDATE($E30,6)), (0.73*$D30)/6, 0) -> 103171.37 | P30: =IF(AND($E30<=P$2, P$2<EDATE($E30,6)), (0.73*$D30)/6, 0) -> 103171.37 | Q30: =IF(AND($E30<=Q$2, Q$2<EDATE($E30,6)), (0.73*$D30)/6, 0) -> 103171.37 | R30: =IF(AND($E30<=R$2, R$2<EDATE($E30,6)), (0.73*$D30)/6, 0) -> 103171.37 | ... CA30: =IF(AND($E30<=CA$2, CA$2<EDATE($E30,6)), (0.73*$D30)/6, 0) -> 0 | CC30: =SUM(K30:CA30)-(D30-H30) -> -228955.64
A31: ='Closed Deals 25'!D35 -> 11615 | B31: ='Closed Deals 25'!B35 -> Jesse Brewer Park | D31: ='Closed Deals 25'!E35 -> 320036.44 | E31: ='Closed Deals 25'!H35 -> 45790 | F31: 45884 | G31: =IFERROR(F31-E31,F31) -> 94 | I31: 2 | K31: =IF(AND($E31<=K$2, K$2<EDATE($E31,6)), (0.73*$D31)/6, 0) -> 0 | L31: =IF(AND($E31<=L$2, L$2<EDATE($E31,6)), (0.73*$D31)/6, 0) -> 0 | M31: =IF(AND($E31<=M$2, M$2<EDATE($E31,6)), (0.73*$D31)/6, 0) -> 0 | N31: =IF(AND($E31<=N$2, N$2<EDATE($E31,6)), (0.73*$D31)/6, 0) -> 0 | O31: =IF(AND($E31<=O$2, O$2<EDATE($E31,6)), (0.73*$D31)/6, 0) -> 38937.767 | P31: =IF(AND($E31<=P$2, P$2<EDATE($E31,6)), (0.73*$D31)/6, 0) -> 38937.767 | Q31: =IF(AND($E31<=Q$2, Q$2<EDATE($E31,6)), (0.73*$D31)/6, 0) -> 38937.767 | R31: =IF(AND($E31<=R$2, R$2<EDATE($E31,6)), (0.73*$D31)/6, 0) -> 38937.767 | ... CA31: =IF(AND($E31<=CA$2, CA$2<EDATE($E31,6)), (0.73*$D31)/6, 0) -> 0 | CC31: =SUM(K31:CA31)-(D31-H31) -> -86409.839
A32: ='Closed Deals 25'!D36 -> 11580 | B32: ='Closed Deals 25'!B36 -> Maple Hills ES | D32: ='Closed Deals 25'!E36 -> 963241.27 | E32: ='Closed Deals 25'!H36 -> 45791 | F32: 45884 | G32: =IFERROR(F32-E32,F32) -> 93 | I32: 2 | K32: =IF(AND($E32<=K$2, K$2<EDATE($E32,6)), (0.73*$D32)/6, 0) -> 0 | L32: =IF(AND($E32<=L$2, L$2<EDATE($E32,6)), (0.73*$D32)/6, 0) -> 0 | M32: =IF(AND($E32<=M$2, M$2<EDATE($E32,6)), (0.73*$D32)/6, 0) -> 0 | N32: =IF(AND($E32<=N$2, N$2<EDATE($E32,6)), (0.73*$D32)/6, 0) -> 0 | O32: =IF(AND($E32<=O$2, O$2<EDATE($E32,6)), (0.73*$D32)/6, 0) -> 117194.35 | P32: =IF(AND($E32<=P$2, P$2<EDATE($E32,6)), (0.73*$D32)/6, 0) -> 117194.35 | Q32: =IF(AND($E32<=Q$2, Q$2<EDATE($E32,6)), (0.73*$D32)/6, 0) -> 117194.35 | R32: =IF(AND($E32<=R$2, R$2<EDATE($E32,6)), (0.73*$D32)/6, 0) -> 117194.35 | ... CA32: =IF(AND($E32<=CA$2, CA$2<EDATE($E32,6)), (0.73*$D32)/6, 0) -> 0 | CC32: =SUM(K32:CA32)-(D32-H32) -> -260075.14
A33: ='Closed Deals 25'!D37 -> 11614 | B33: ='Closed Deals 25'!B37 -> Dieterich ES | D33: ='Closed Deals 25'!E37 -> 254338 | E33: ='Closed Deals 25'!H37 -> 45792 | F33: ='Closed Deals 25'!I37 -> 45838 | G33: =IFERROR(F33-E33,F33) -> 46 | I33: 2 | K33: =IF(AND($E33<=K$2, K$2<EDATE($E33,6)), (0.73*$D33)/6, 0) -> 0 | L33: =IF(AND($E33<=L$2, L$2<EDATE($E33,6)), (0.73*$D33)/6, 0) -> 0 | M33: =IF(AND($E33<=M$2, M$2<EDATE($E33,6)), (0.73*$D33)/6, 0) -> 0 | N33: =IF(AND($E33<=N$2, N$2<EDATE($E33,6)), (0.73*$D33)/6, 0) -> 0 | O33: =IF(AND($E33<=O$2, O$2<EDATE($E33,6)), (0.73*$D33)/6, 0) -> 30944.457 | P33: =IF(AND($E33<=P$2, P$2<EDATE($E33,6)), (0.73*$D33)/6, 0) -> 30944.457 | Q33: =IF(AND($E33<=Q$2, Q$2<EDATE($E33,6)), (0.73*$D33)/6, 0) -> 30944.457 | R33: =IF(AND($E33<=R$2, R$2<EDATE($E33,6)), (0.73*$D33)/6, 0) -> 30944.457 | ... CA33: =IF(AND($E33<=CA$2, CA$2<EDATE($E33,6)), (0.73*$D33)/6, 0) -> 0 | CC33: =SUM(K33:CA33)-(D33-H33) -> -68671.26
A34: ='Closed Deals 25'!D38 -> 11613 | B34: ='Closed Deals 25'!B38 -> Chrysler ES | D34: ='Closed Deals 25'!E38 -> 254338 | E34: ='Closed Deals 25'!H38 -> 45796 | F34: 45884 | G34: =IFERROR(F34-E34,F34) -> 88 | I34: 2 | K34: =IF(AND($E34<=K$2, K$2<EDATE($E34,6)), (0.73*$D34)/6, 0) -> 0 | L34: =IF(AND($E34<=L$2, L$2<EDATE($E34,6)), (0.73*$D34)/6, 0) -> 0 | M34: =IF(AND($E34<=M$2, M$2<EDATE($E34,6)), (0.73*$D34)/6, 0) -> 0 | N34: =IF(AND($E34<=N$2, N$2<EDATE($E34,6)), (0.73*$D34)/6, 0) -> 0 | O34: =IF(AND($E34<=O$2, O$2<EDATE($E34,6)), (0.73*$D34)/6, 0) -> 30944.457 | P34: =IF(AND($E34<=P$2, P$2<EDATE($E34,6)), (0.73*$D34)/6, 0) -> 30944.457 | Q34: =IF(AND($E34<=Q$2, Q$2<EDATE($E34,6)), (0.73*$D34)/6, 0) -> 30944.457 | R34: =IF(AND($E34<=R$2, R$2<EDATE($E34,6)), (0.73*$D34)/6, 0) -> 30944.457 | ... CA34: =IF(AND($E34<=CA$2, CA$2<EDATE($E34,6)), (0.73*$D34)/6, 0) -> 0 | CC34: =SUM(K34:CA34)-(D34-H34) -> -68671.26
A35: ='Closed Deals 25'!D39 -> 11612 | B35: ='Closed Deals 25'!B39 -> Baptist ES | D35: ='Closed Deals 25'!E39 -> 254338 | E35: ='Closed Deals 25'!H39 -> 45797 | F35: ='Closed Deals 25'!I39 -> 45838 | G35: =IFERROR(F35-E35,F35) -> 41 | I35: 2 | K35: =IF(AND($E35<=K$2, K$2<EDATE($E35,6)), (0.73*$D35)/6, 0) -> 0 | L35: =IF(AND($E35<=L$2, L$2<EDATE($E35,6)), (0.73*$D35)/6, 0) -> 0 | M35: =IF(AND($E35<=M$2, M$2<EDATE($E35,6)), (0.73*$D35)/6, 0) -> 0 | N35: =IF(AND($E35<=N$2, N$2<EDATE($E35,6)), (0.73*$D35)/6, 0) -> 0 | O35: =IF(AND($E35<=O$2, O$2<EDATE($E35,6)), (0.73*$D35)/6, 0) -> 30944.457 | P35: =IF(AND($E35<=P$2, P$2<EDATE($E35,6)), (0.73*$D35)/6, 0) -> 30944.457 | Q35: =IF(AND($E35<=Q$2, Q$2<EDATE($E35,6)), (0.73*$D35)/6, 0) -> 30944.457 | R35: =IF(AND($E35<=R$2, R$2<EDATE($E35,6)), (0.73*$D35)/6, 0) -> 30944.457 | ... CA35: =IF(AND($E35<=CA$2, CA$2<EDATE($E35,6)), (0.73*$D35)/6, 0) -> 0 | CC35: =SUM(K35:CA35)-(D35-H35) -> -68671.26
A36: ='Closed Deals 25'!D40 -> 11535 | B36: ='Closed Deals 25'!B40 -> Kennedy ES | D36: ='Closed Deals 25'!E40 -> 728293 | E36: ='Closed Deals 25'!H40 -> 45799 | F36: ='Closed Deals 25'!I40 -> 45839 | G36: =IFERROR(F36-E36,F36) -> 40 | I36: 1 | K36: =IF(AND($E36<=K$2, K$2<EDATE($E36,6)), (0.73*$D36)/6, 0) -> 0 | L36: =IF(AND($E36<=L$2, L$2<EDATE($E36,6)), (0.73*$D36)/6, 0) -> 0 | M36: =IF(AND($E36<=M$2, M$2<EDATE($E36,6)), (0.73*$D36)/6, 0) -> 0 | N36: =IF(AND($E36<=N$2, N$2<EDATE($E36,6)), (0.73*$D36)/6, 0) -> 0 | O36: =IF(AND($E36<=O$2, O$2<EDATE($E36,6)), (0.73*$D36)/6, 0) -> 88608.982 | P36: =IF(AND($E36<=P$2, P$2<EDATE($E36,6)), (0.73*$D36)/6, 0) -> 88608.982 | Q36: =IF(AND($E36<=Q$2, Q$2<EDATE($E36,6)), (0.73*$D36)/6, 0) -> 88608.982 | R36: =IF(AND($E36<=R$2, R$2<EDATE($E36,6)), (0.73*$D36)/6, 0) -> 88608.982 | ... CA36: =IF(AND($E36<=CA$2, CA$2<EDATE($E36,6)), (0.73*$D36)/6, 0) -> 0 | CC36: =SUM(K36:CA36)-(D36-H36) -> -196639.11
A37: ='Closed Deals 25'!D46 -> 11605 | B37: ='Closed Deals 25'!B46 -> Vista Magnet MS | D37: ='Closed Deals 25'!E46 -> 153956.79 | E37: ='Closed Deals 25'!H46 -> 45811 | F37: ='Closed Deals 25'!I46 -> 46009 | G37: =IFERROR(F37-E37,F37) -> 198 | I37: 2 | K37: =IF(AND($E37<=K$2, K$2<EDATE($E37,6)), (0.73*$D37)/6, 0) -> 0 | L37: =IF(AND($E37<=L$2, L$2<EDATE($E37,6)), (0.73*$D37)/6, 0) -> 0 | M37: =IF(AND($E37<=M$2, M$2<EDATE($E37,6)), (0.73*$D37)/6, 0) -> 0 | N37: =IF(AND($E37<=N$2, N$2<EDATE($E37,6)), (0.73*$D37)/6, 0) -> 0 | O37: =IF(AND($E37<=O$2, O$2<EDATE($E37,6)), (0.73*$D37)/6, 0) -> 0 | P37: =IF(AND($E37<=P$2, P$2<EDATE($E37,6)), (0.73*$D37)/6, 0) -> 18731.409 | Q37: =IF(AND($E37<=Q$2, Q$2<EDATE($E37,6)), (0.73*$D37)/6, 0) -> 18731.409 | R37: =IF(AND($E37<=R$2, R$2<EDATE($E37,6)), (0.73*$D37)/6, 0) -> 18731.409 | ... CA37: =IF(AND($E37<=CA$2, CA$2<EDATE($E37,6)), (0.73*$D37)/6, 0) -> 0 | CC37: =SUM(K37:CA37)-(D37-H37) -> -41568.333
A38: ='Closed Deals 25'!D47 -> 11551 | B38: ='Closed Deals 25'!B47 -> Juniper ES | D38: ='Closed Deals 25'!E47 -> 280655 | E38: ='Closed Deals 25'!H47 -> 45811 | F38: 45838 | G38: =IFERROR(F38-E38,F38) -> 27 | I38: 1 | K38: =IF(AND($E38<=K$2, K$2<EDATE($E38,6)), (0.73*$D38)/6, 0) -> 0 | L38: =IF(AND($E38<=L$2, L$2<EDATE($E38,6)), (0.73*$D38)/6, 0) -> 0 | M38: =IF(AND($E38<=M$2, M$2<EDATE($E38,6)), (0.73*$D38)/6, 0) -> 0 | N38: =IF(AND($E38<=N$2, N$2<EDATE($E38,6)), (0.73*$D38)/6, 0) -> 0 | O38: =IF(AND($E38<=O$2, O$2<EDATE($E38,6)), (0.73*$D38)/6, 0) -> 0 | P38: =IF(AND($E38<=P$2, P$2<EDATE($E38,6)), (0.73*$D38)/6, 0) -> 34146.358 | Q38: =IF(AND($E38<=Q$2, Q$2<EDATE($E38,6)), (0.73*$D38)/6, 0) -> 34146.358 | R38: =IF(AND($E38<=R$2, R$2<EDATE($E38,6)), (0.73*$D38)/6, 0) -> 34146.358 | ... CA38: =IF(AND($E38<=CA$2, CA$2<EDATE($E38,6)), (0.73*$D38)/6, 0) -> 0 | CC38: =SUM(K38:CA38)-(D38-H38) -> -75776.85
A39: ='Closed Deals 25'!D48 -> 11500 | B39: ='Closed Deals 25'!B48 -> Carr ES | D39: ='Closed Deals 25'!E48 -> 2392640.9 | E39: ='Closed Deals 25'!H48 -> 45812 | F39: 45853 | G39: =IFERROR(F39-E39,F39) -> 41 | I39: 2 | K39: =IF(AND($E39<=K$2, K$2<EDATE($E39,6)), (0.73*$D39)/6, 0) -> 0 | L39: =IF(AND($E39<=L$2, L$2<EDATE($E39,6)), (0.73*$D39)/6, 0) -> 0 | M39: =IF(AND($E39<=M$2, M$2<EDATE($E39,6)), (0.73*$D39)/6, 0) -> 0 | N39: =IF(AND($E39<=N$2, N$2<EDATE($E39,6)), (0.73*$D39)/6, 0) -> 0 | O39: =IF(AND($E39<=O$2, O$2<EDATE($E39,6)), (0.73*$D39)/6, 0) -> 0 | P39: =IF(AND($E39<=P$2, P$2<EDATE($E39,6)), (0.73*$D39)/6, 0) -> 291104.64 | Q39: =IF(AND($E39<=Q$2, Q$2<EDATE($E39,6)), (0.73*$D39)/6, 0) -> 291104.64 | R39: =IF(AND($E39<=R$2, R$2<EDATE($E39,6)), (0.73*$D39)/6, 0) -> 291104.64 | ... CA39: =IF(AND($E39<=CA$2, CA$2<EDATE($E39,6)), (0.73*$D39)/6, 0) -> 0 | CC39: =SUM(K39:CA39)-(D39-H39) -> -646013.03
A40: ='Closed Deals 25'!D49 -> 11622 | B40: ='Closed Deals 25'!B49 -> Kingston ES | D40: ='Closed Deals 25'!E49 -> 152362 | E40: ='Closed Deals 25'!H49 -> 45813 | F40: 45838 | G40: =IFERROR(F40-E40,F40) -> 25 | I40: 2 | K40: =IF(AND($E40<=K$2, K$2<EDATE($E40,6)), (0.73*$D40)/6, 0) -> 0 | L40: =IF(AND($E40<=L$2, L$2<EDATE($E40,6)), (0.73*$D40)/6, 0) -> 0 | M40: =IF(AND($E40<=M$2, M$2<EDATE($E40,6)), (0.73*$D40)/6, 0) -> 0 | N40: =IF(AND($E40<=N$2, N$2<EDATE($E40,6)), (0.73*$D40)/6, 0) -> 0 | O40: =IF(AND($E40<=O$2, O$2<EDATE($E40,6)), (0.73*$D40)/6, 0) -> 0 | P40: =IF(AND($E40<=P$2, P$2<EDATE($E40,6)), (0.73*$D40)/6, 0) -> 18537.377 | Q40: =IF(AND($E40<=Q$2, Q$2<EDATE($E40,6)), (0.73*$D40)/6, 0) -> 18537.377 | R40: =IF(AND($E40<=R$2, R$2<EDATE($E40,6)), (0.73*$D40)/6, 0) -> 18537.377 | ... CA40: =IF(AND($E40<=CA$2, CA$2<EDATE($E40,6)), (0.73*$D40)/6, 0) -> 0 | CC40: =SUM(K40:CA40)-(D40-H40) -> -41137.74
A41: ='Closed Deals 25'!D50 -> 11621 | B41: ='Closed Deals 25'!B50 -> Krystal ES | D41: ='Closed Deals 25'!E50 -> 171547.96 | E41: ='Closed Deals 25'!H50 -> 45814 | F41: ='Closed Deals 25'!I50 -> 45900 | G41: =IFERROR(F41-E41,F41) -> 86 | I41: 2 | K41: =IF(AND($E41<=K$2, K$2<EDATE($E41,6)), (0.73*$D41)/6, 0) -> 0 | L41: =IF(AND($E41<=L$2, L$2<EDATE($E41,6)), (0.73*$D41)/6, 0) -> 0 | M41: =IF(AND($E41<=M$2, M$2<EDATE($E41,6)), (0.73*$D41)/6, 0) -> 0 | N41: =IF(AND($E41<=N$2, N$2<EDATE($E41,6)), (0.73*$D41)/6, 0) -> 0 | O41: =IF(AND($E41<=O$2, O$2<EDATE($E41,6)), (0.73*$D41)/6, 0) -> 0 | P41: =IF(AND($E41<=P$2, P$2<EDATE($E41,6)), (0.73*$D41)/6, 0) -> 20871.668 | Q41: =IF(AND($E41<=Q$2, Q$2<EDATE($E41,6)), (0.73*$D41)/6, 0) -> 20871.668 | R41: =IF(AND($E41<=R$2, R$2<EDATE($E41,6)), (0.73*$D41)/6, 0) -> 20871.668 | ... CA41: =IF(AND($E41<=CA$2, CA$2<EDATE($E41,6)), (0.73*$D41)/6, 0) -> 0 | CC41: =SUM(K41:CA41)-(D41-H41) -> -46317.949
A42: ='Closed Deals 25'!D51 -> 11564 | B42: ='Closed Deals 25'!B51 -> Bella Vista ES | D42: ='Closed Deals 25'!E51 -> 621295.64 | E42: ='Closed Deals 25'!H51 -> 45817 | F42: 45874 | G42: =IFERROR(F42-E42,F42) -> 57 | I42: 2 | K42: =IF(AND($E42<=K$2, K$2<EDATE($E42,6)), (0.73*$D42)/6, 0) -> 0 | L42: =IF(AND($E42<=L$2, L$2<EDATE($E42,6)), (0.73*$D42)/6, 0) -> 0 | M42: =IF(AND($E42<=M$2, M$2<EDATE($E42,6)), (0.73*$D42)/6, 0) -> 0 | N42: =IF(AND($E42<=N$2, N$2<EDATE($E42,6)), (0.73*$D42)/6, 0) -> 0 | O42: =IF(AND($E42<=O$2, O$2<EDATE($E42,6)), (0.73*$D42)/6, 0) -> 0 | P42: =IF(AND($E42<=P$2, P$2<EDATE($E42,6)), (0.73*$D42)/6, 0) -> 75590.97 | Q42: =IF(AND($E42<=Q$2, Q$2<EDATE($E42,6)), (0.73*$D42)/6, 0) -> 75590.97 | R42: =IF(AND($E42<=R$2, R$2<EDATE($E42,6)), (0.73*$D42)/6, 0) -> 75590.97 | ... CA42: =IF(AND($E42<=CA$2, CA$2<EDATE($E42,6)), (0.73*$D42)/6, 0) -> 0 | CC42: =SUM(K42:CA42)-(D42-H42) -> -167749.82
